Workbook

Sheet Definations
A1: x5 | B1: 1
A4: x | B4: x2 | C4: a
A5: Project Communications Management Terms | B5: Acknowledgment | C5: Acknowledgment The receiver signals that the message has been received. An acknowledgment shows receipt of the message, but not necessarily agreement with the message.
B6: active listening | C6: Active listening The receiver confirms that the message is being received through feedback, questions, prompts for clarity, and other signs of confirmation.
B7: Choice of media | C7: Choice of media The best modality to use when communicating that is relevant to the information being communicated.
B8: Communication assumptions | C8: Communication assumptions Anything that the project management team believes to be true but hasn’t proven to be true. For example, the project management team may assume that all of the project team can be reached via cell phone, but parts of the world, as of this writing, don’t have a cell signal.
B9: Communication barrier | C9: Communication barrier Anything that prohibits communication from occurring.
B10: Communication channels formula | C10: Communication channels formula N(N – 1)/2, where N represents the number of identified stakeholders. This formula reveals the total number of communication channels within a project.
B11: Communication constraints | C11: Communication constraints Anything that limits the project management team’s options. When it comes to communication constraints, geographical locales, incompatible communications software, and even limited communications technology can constrain the project team.
B12: Communications management plan | C12: Communications management plan A project management subsidiary plan that defines the stakeholders who need specific information, the person who will supply the information, the schedule for the information to be supplied, and the approved modality to provide the information.
B13: Decoder | C13: Decoder The device that decodes a message as it is being received.
B14: Effective listening | C14: Effective listening The receiver is involved in the listening experience by paying attention to visual cues from the speaker and paralingual characteristics, and by asking relevant questions. Encoder The device that encodes the message being sent.
B15: Feedback | C15: Feedback The sender confirms that the receiver understands the message by directly asking for a response, questions for clarification, or other confirmation.
B16: Influence/impact grid | C16: Influence/impact grid Stakeholders are mapped on a grid based on their influence over the project in relation to their influence over the project execution.
B17: Information presentation tools | C17: Information presentation tools A software package that allows the project management team to present the project’s health through graphics, spreadsheets, and text. (Think of Microsoft Project.)
... B30: Push communication | C30: Push communication This approach pushes the information from the sender to the receiver without any real acknowledgment that the information was really received or understood. Consider letters, faxes, voicemail messages, e-mails, and other communications modalities that the sender packages and sends to receivers through some intermediary network. Receiver The person who receives the message. Sender The person who is sending the message. Sender–receiver models Feedback loops and barriers to communications. Stakeholder notifications Notices to the stakeholders about resolved issues, approved changes, and the overall health of the project. Status review meeting A regularly scheduled meeting to discuss the status of the project and its progress toward completing the project scope statement. Time reporting system A system to record the actual time to complete project activities.
A31: Project Cost Management Terms | B31: Cost variance (CV) | C31: Cost variance (CV) The difference of the earned value amount and the cumulative actual costs of the project. The formula is CV = EV – AC.
B32: Definitive estimate | C32: Definitive estimate This estimate type is one of the most accurate. It’s used late in the planning processes and is associated with bottomup estimating. You need the WBS in order to create the definitive estimate. The range of variance for the estimate can be from –5 percent to +10 percent.
B33: Direct costs | C33: Direct costs Costs are attributed directly to the project work and cannot be shared among projects (for example, airfare, hotels, long-distance phone charges, and so on).
B34: Earned value (EV) | C34: Earned value (EV) Earned value is the physical work completed to date and the authorized budget for that work. It is the percentage of the BAC that represents the actual work completed in the project.
B35: Estimate at completion (EAC) | C35: Estimate at completion (EAC) These forecasting formulas predict the likely completed costs of the project based on current scenarios within the project.
B36: Estimate to complete (ETC) | C36: Estimate to complete (ETC) An earned value management formula that predicts how much funding the project will require to be completed. Three variations of this formula are based on conditions the project may be experiencing.
B37: Fixed costs | C37: Fixed costs Costs that remain constant throughout the life of the project (the cost of a piece of rented equipment for the project, the cost of a consultant brought on to the project, and so on).
B38: Funding limit reconciliation | C38: Funding limit reconciliation An organization’s approach to managing cash flow against the project deliverables based on a schedule, milestone accomplishment, or data constraints.
B39: Indirect costs | C39: Indirect costs Costs that are representative of more than one project (for example, utilities for the performing organization, access to a training room, project management software license, and so on).
B40: Known unknown | C40: Known unknown An event that will likely happen within the project, but when it will happen and to what degree is unknown. These events, such as delays, are usually risk-related.
B41: Learning curve | C41: Learning curve An approach that assumes the cost per unit decreases the more units workers complete, because workers learn as they complete the required work.
B42: Oligopoly | C42: Oligopoly A market condition where the market is so tight that the actions of one vendor affect the actions of all the others.
B43: Opportunity cost | C43: Opportunity cost The total cost of the opportunity that is refused to realize an opposing opportunity.
... B79: Work package | C79: Work package The smallest item in the work breakdown structure. Cost aggregation Costs are parallel to each WBS work package. The costs of each work package are aggregated to their corresponding control accounts. Each control account then is aggregated to the sum of the project costs. Cost baseline A time-lapse exposure of when the project monies are to be spent in relation to cumulative values of the work completed in the project. Cost budgeting The cost aggregation achieved by assigning specific dollar amounts for each of the scheduled activities or, more likely, for each of the work packages in the WBS. Cost budgeting applies the cost estimates over time. Cost change control system A system that examines any changes associated with scope changes, the cost of materials, and the cost of any other resources, and the associated impact on the overall project cost. Cost management plan The cost management plan dictates how cost variances will be managed. Cost of poor quality The monies spent to recover from not adhering to the expected level of quality. Examples may include rework, defect repair, loss of life or limb because safety precautions were not taken, loss of sales, and loss of customers. This is also known as the cost of nonconformance to quality. Cost of quality The monies spent to attain the expected level of quality within a project. Examples include training, testing, and safety precautions. Cost performance index (CPI) Measures the project based on its financial performance. The formula is CPI = EV/AC.
A80: Project Integration Management Terms | B80: Assumption log | C80: Assumption log An assumption is something that is believed to be true or false, but it has not yet been proven to be true or false. Assumptions that prove wrong can become risks for the project. All identified project assumptions are recorded in the assumption log for testing and analysis, and the outcomes are recorded.
B81: Benefit/cost ratio (BCR) models | C81: Benefit/cost ratio (BCR) models This is an example of a benefits comparison model. It examines the benefit-to-cost ratio.
B82: Change control board (CCB) | C82: Change control board (CCB) A committee that evaluates the worthiness of a proposed change and either approves or rejects the proposed change.
B83: Change control system (CCS) | C83: Change control system (CCS) The change control system communicates the process for controlling changes to the project deliverables. This system works with the configuration management system and seeks to control and document proposals to change the project’s product.
B84: Change log | C84: Change log All changes that enter into a project are recorded in the change log. The characteristics of the change, such as the time, cost, risk, and scope details, are also recorded.
B85: Change management plan | C85: Change management plan This plan details the project procedures for entertaining change requests: how change requests are managed, documented, approved, or declined.
B86: Closure processes | C86: Closure processes This final process group of the project management life cycle is responsible for closing the project phase or project. This is where project documentation is archived and project contracts are also closed.
B87: Communications management plan | C87: Communications management plan This plan defines who will get what information, how they will receive it, and in what modality the communication will take place.
B88: Configuration identification | C88: Configuration identification This includes the labeling of the components, how changes are made to the product, and the accountability of the changes.
B89: Configuration management plan | C89: Configuration management plan This plan is an input to the control scope process. It defines how changes to the features and functions of the project deliverable, the product scope, may enter the project.
B90: Configuration management system | C90: Configuration management system This system defines how stakeholders are allowed to submit change requests, the conditions for approving a change request, and how approved change requests are validated in the project scope. Configuration management also documents the characteristics and functions of the project’s products and any changes to a product’s characteristics.
B91: Configuration status accounting | C91: Configuration status accounting The organization of the product materials, details, and prior product documentation. Configuration verification and auditing The scope verification and completeness auditing of project or phase deliverables to ensure that they are in alignment with the project plan.
B92: Contract closure | C92: Contract closure The formal verification of the contract completeness by the vendor and the performing organization.
... B119: Scoring models | C119: Scoring models These models use a common set of values for all of the projects up for selection. For example, values can be profitability, complexity, customer demand, and so on. tacit knowledge Knowledge that’s more difficult to express because it’s personal beliefs, values, knowledge gain from experience, and “know-how” when doing a task.
A120: Project Management Fundamental Terms | B120: A Guide to the Project Management Body of Knowledge (PMBOK Guide) | C120: A Guide to the Project Management Body of Knowledge (PMBOK Guide) The PMI publication that defines widely accepted project management practices. The CAPM and the PMP exam are based on this book.
B121: Application areas | C121: Application areas The areas of expertise, industry, or function where a project is centered. Examples of application areas include architecture, IT, health care, and manufacturing.
B122: Business value | C122: Business value A quantifiable return on investment. The return can be tangible, such as equipment, money, or market share. The return can also be intangible, such as brand recognition, trademarks, and reputation.
B123: Certified Associate in Project Management (CAPM) | C123: Certified Associate in Project Management (CAPM) A person who has slightly less project management experience than a PMP, but who has qualified for and then passed the CAPM examination.
B124: Cultural and social environment | C124: Cultural and social environment Defines how a project affects people and how those people may affect the project. Cultural and social environments include the economic, educational, ethical, religious, demographic, and ethnic composition of the people affected by the project.
B125: Deliverable | C125: Deliverable A product, service, or result created by a project. Projects can have multiple deliverables.
B126: General management skills | C126: General management skills These include the application of accounting, procurement, sales and marketing, contracting, manufacturing, logistics, strategic planning, human resource management, standards and regulations, and information technology. International and political environment The consideration of the local and international laws, languages, communication challenges, time zone differences, and other non-collocated issues that affect a project’s ability to progress.
B127: Interpersonal skills | C127: Interpersonal skills The ability to interact, lead, motivate, and manage people.
B128: Iron Triangle of Project Management | C128: Iron Triangle of Project Management A triangle with the characteristics of time, cost, and scope. Time, cost, and scope each constitute one side of the triangle; if any side of the Iron Triangle is not in balance with the other sides, the project will suffer. The Iron Triangle of Project Management is also known as the Triple Constraints of Project Management, as all projects are constrained by time, cost, and scope.
B129: Physical environment | C129: Physical environment The physical structure and surroundings that affect a project’s work.
B130: Process groups | C130: Process groups A collection of related processes in project management. There are five process groups and 49 project management processes. The five process groups are Initiating, Planning, Executing, Monitoring and Controlling, and Closing.
B131: Program | C131: Program A collection of related projects working in unison toward a common deliverable.
B132: Progressive elaboration | C132: Progressive elaboration The process of gathering project details. This process uses deductive reasoning, logic, and a series of information-gathering techniques to identify details about a project, product, or solution.
... B145: Work performance reports | C145: Work performance reports Work performance reports is the formatted communication of work performance information. Work performance reports communicate what’s happening in the project through status reports, memos, dashboards, or other modalities. Hybrid structure An organization that creates a blend of the functional, matrix, and project-oriented structures. Multidivisional structure Describe organizations that have duplication of efforts within the organization, but not within each department or division of the organization. Project manager has little authority in this structure and the functional manager controls the project budget. Organic or simple Describes a loosely organized business or organization. There likely aren’t big formal departments and people work alongside one another regardless of roles and titles. The project manager likely has little control over the project resources and may not be called a project manager. Organizational process assets Organizational process assets include organizational processes, policies, procedures, and items from a corporate knowledge base. Organizational process assets are grouped into two categories to consider: processes, policies and procedures, and organizational knowledge bases. Organizational Knowledge Repositories Organizational knowledge repositories are the databases, files, and historical information that you can use to help better plan and manage your projects. This is an organizational process asset that is created internally to your organization through the ongoing work of operations and other projects. Organizational System A system can create things by working with multiple components that the individual components could not create if they worked alone. The structure of the organization and the governance framework creates constraints that affect how the project manager makes decisions within the project. The organizational system directly affects how the project manager utilizes their power, influence, leadership, and even political capital, to get things done in the environment. Project management office (PMO) A business unit that centralizes the operations and procedures of all projects within the organization. The PMO can be supportive, controlling, or directive. Project-oriented structure An organization that assigns a project team to one project for the duration of the project life cycle. The project manager has high-to-almost-complete project power. Strong matrix structure An organization where organizational resources are pooled into one project team, but the functional managers have less project power than the project manager. Virtual organization Uses a network structure to communicate and interact with other groups and departments. A point of contact exists for each department and these department point of contact receive and send all messages for the department. Weak matrix structure An organization where organizational resources are pooled into one project team, but the functional managers have more project power than the project manager.
A146: Project Manager Role | B146: active listening | C146: active listening The message receiver restates what’s been said to fully understand and confirm the message and it provides an opportunity for the sender to clarify the message if needed.
B147: active problem solving | C147: active problem solving Active problem solving begins with problem definition. Problem definition is the ability to discern between the cause and effect of the problem. Root-cause analysis looks beyond the immediate symptoms to the cause of the symptoms—which then affords opportunities for solutions.
B148: avoiding power | C148: avoiding power The project manager refuses to act, get involved, or make decisions.
B149: charismatic leadership | C149: charismatic leadership The leader is motivating, has highenergy, and inspires the team through strong convictions about what’s possible and what the team can achieve. Positive thinking and a can-do mentality are characteristics of a charismatic leader.
B150: expert power | C150: expert power The project manager has deep skills and experience in a discipline (for example, years of working in IT helps an IT project manager better manage IT projects). ingratiating power The project manager aims to gain favor with the project team and stakeholders through flattery.
B151: informational power | C151: informational power The individual has power and control of the data gathering and distribution of information. interactional leadership The leader is a hybrid of transactional, transformational, and charismatic leaders. The interactional leader wants the team to act, is excited and inspired about the project work, yet still holds the team accountable for their results. guilt-based power The project manager can make the team and stakeholders feel guilty to gain compliance in the project. leadership Leadership is about aligning, motivating, and inspiring the project team members to do the right thing, build trust, think creatively, and to challenge the status quo. laissez-faire leadership The leader takes a “hands-off” approach to the project. This means the project team makes decisions, takes initiative in the actions, and creates goals. While this approach can provide autonomy, it can make the leader appear absent when it comes to project decisions. management Management utilizes positional power to maintain, administrate, control, and focus on getting things done without challenging the status quo of the project and organization. media selection Based on the audience and the message being sent, the media should be in alignment with the message. meeting management Meetings are forms of communication. How the meeting is led, managed, and controlled all influence the message being delivered. Agendas, minutes, and order are mandatory for effective communications within a meeting. personal or charismatic power The project manager has a warm personality that others like. presentation In formal presentations, the presenter’s oral and body language, visual aids, and handouts all influence the message being delivered.
B152: PMI Talent Triangle | C152: PMI Talent Triangle Defines three areas of PDUs for PMI certified professionals to maintain their certification. The PMI Talent Triangle includes technical project management, leadership, and strategic and business management.
B153: positional power | C153: positional power The project manager’s power is because of the position she has as the project manager. This is also known as formal, authoritative, and legitimate power.
B154: pressure-based power | C154: pressure-based power The project manager can restrict choices to get the project team to perform and do the project work.
B155: Professional Development Units (PDUs) | C155: Professional Development Units (PDUs) PDUs are earned after the PMP to maintain the PMP certification. PMPs are required to earn 60 PDUs per three-year certification cycle. Of the 60 PDUs, a minimum of 35 hours must come from educational opportunities.
B156: project manager | C156: project manager The role of leading the project team and managing the project resources to effectively achieve the objectives of the project. punitive or coercive power The project manager can punish the project team.
B157: referent power | C157: referent power The project manager is respected or admired because of the team’s past experiences with the project manager. This is about the project manager’s credibility in the organization.
B158: reward power | C158: reward power The project manager can reward the project team. sender-receiver models Communication requires a sender and a receiver. Within this model may be multiple avenues to complete the flow of communication, but barriers to effective communication may be present as well. servant leadership The leader puts others first and focuses on the needs of the people he serves. Servant leaders provide opportunity for growth, education, autonomy within the project, and the well-being of others. The primary focus of servant leadership is service to others. situational power The project manager has power because of certain situations in the organization. style The tone, structure, and formality of the message being sent should be in alignment with the audience and the content of the message. transactional leadership The leader emphasizes the goals of the project and rewards and disincentives for the project team. This is sometimes called management by exception as it’s the exception that is reward or punished. transformational leadership The leader inspires and motivates the project team to achieve the project goals. Transformational leaders aim to empower the project team to act, be innovative in the project work, and accomplish through ambition. or fold page in half. Read the term, recite the definition, and then look at this side of
A159: Project Quality Management Terms | B159: Activity network diagram | C159: Activity network diagram These diagrams, such as the project network diagram, show the flow of the project work.
B160: Affinity diagram | C160: Affinity diagram This diagram breaks down ideas, solutions, causes, and project components and groups them together with other similar ideas and components.
B161: Benchmarking | C161: Benchmarking Comparing any two similar entities to measure their performance.
B162: Cause-and-effect diagrams | C162: Cause-and-effect diagrams Diagrams that show the relationship between variables within a process and how those relationships may contribute to inadequate quality. The diagrams can help organize both the process and team opinions, as well as generate discussion on finding a solution to ensure quality.
B163: Checklist | C163: Checklist A simple approach to ensure that work is completed according to the quality policy.
B164: Control chart | C164: Control chart A quality control chart that maps the performance of project work over time.
B165: Control quality | C165: Control quality An inspection-driven process that measures work results to confirm that the project is meeting the relevant quality standards.
B166: Cost of conformance | C166: Cost of conformance This is the cost associated with the monies spent to attain the expected level of quality. It is also known as the cost of quality.
B167: Cost of nonconformance to quality | C167: Cost of nonconformance to quality The cost associated with not satisfying quality expectations. This is also known as the cost of poor quality.
B168: Cost-benefit analysis | C168: Cost-benefit analysis A process to study the trade-offs between costs and the benefits realized from those costs.
B169: Design of experiments | C169: Design of experiments An approach that relies on statistical scenarios to determine what variables within a project will result in the best outcome.
B170: External QA | C170: External QA Assurance provided to the external customers of the project.
B171: Flowchart | C171: Flowchart A diagram illustrating how components within a system are related. Flowcharts show the relation between components, as well as help the project team determine where quality issues may be present and, once done, plan accordingly.
... B188: Trend analysis | C188: Trend analysis The science of using past results to predict future performance. Work performance information The results of the project work as needed. This includes technical performance measures, project status, information on what the project has created to date, corrective actions, and performance reports.
A189: Project Resources Management Terms | B189: Adjourning | C189: Adjourning Once the project is done, either the team moves onto other assignments as a unit, or the project team is disbanded and individual team members go on to other work.
B190: Authority power | C190: Authority power Project management team members may have authority over other project team members, may have the ability to make decisions, and perhaps even sign approvals for project work and purchases.
B191: Coercive power | C191: Coercive power The project manager has the authority to discipline the project team members. This is also known as penalty power.
B192: Collaborate/Problem solving | C192: Collaborate/Problem solving This approach confronts the problem head-on and is the preferred method of conflict resolution. Multiple viewpoints and perspectives contribute to the solution.
B193: Collective bargaining agreement constraints | C193: Collective bargaining agreement constraints Contracts and agreements with unions or other employee groups may serve as constraints on the project.
B194: Competency | C194: Competency This attribute defines what talents, skills, and capabilities are needed to complete the project work.
B195: Compromising | C195: Compromising This approach requires that both parties give up something.
B196: expert power | C196: Expert power The project manager’s authority comes both from experience with the technology the project focuses on and from expertise in managing projects. Forcing power The person with the power makes the decision.
B197: Formal power | C197: Formal power The project manager has been assigned the role of project manager by senior management and is in charge of the project.
B198: Forming | C198: Forming The project team meets and learns about their roles and responsibilities on the project. Little interaction among the project team happens in this stage as the team is learning about the project and project manager.
B199: Herzberg’s Theory of Motivation | C199: Herzberg’s Theory of Motivation Frederick Herzberg’s theory of the motivating agents and hygiene agents that affect a person’s willingness to excel in his career.
B200: Hierarchical organizational chart | C200: Hierarchical organizational chart A chart showing the relationship between superior and subordinate employees, groups, disciplines, and even departments.
B201: Issue log | C201: Issue log A logbook of the issues the project team has identified and dates as to when the issues must be resolved by. The issue log may also include team members or stakeholders who are responsible for finding a solution to the identified issues.
... B216: Vroom’s Expectancy Theory | C216: Vroom’s Expectancy Theory This theory states that people will behave based on what they expect as a result of their behavior. In other words, people will work in relation to the expected reward.
A217: Project Risk Management Terms | B217: Acceptance | C217: Acceptance A risk response appropriate for both positive and negative risks, but often used for smaller risks within a project.
...

Sheet Data
A1: x | B1: x | C1: x | D1: x | E1: x | F1: x | G1: x | H1: 1 | I1: 2 | J1: 3 | K1: 4 | L1: 5 | M1: 6 | N1: 7 | O1: 8 | P1: 9 | Q1: 10 | R1: 11 | S1: 12 | T1: 13 | U1: 14 | V1: 15 | W1: a
A2: x | B2: 1 | C2: Project Management Fundamental Terms | D2: Project Management Fundamental Terms | E2: =LEN(D2) -> 36 | F2: x | G2: x | H2: x | I2: x | J2: x
A3: =C3=D3 -> FALSE | B3: =B2+1 -> 2 | C3: Project Management Fundamental Terms | D3: A Guide to the Project Management Body of Knowledge (PMBOK Guide) | E3: =LEN(D3) -> 65 | F3: 1 | G3: =IF(F3=1,1,G2+1) -> 1 | H3: =IF($G3=H$1,$D3,"") -> A Guide to the Project Management Body of Knowledge (PMBOK Guide) | I3: =IF($G4=I$1,$D4,"") -> The PMI publication that defines widely accepted project management practices. The CAPM and the PMP exam are based on this book. | J3: =IF($G5=J$1,$D5,"") | K3: =IF($G6=K$1,$D6,"") | L3: =IF($G7=L$1,$D7,"") | M3: =IF($G8=M$1,$D8,"") | N3: =IF($G9=N$1,$D9,"") | O3: =IF($G10=O$1,$D10,"") | P3: =IF($G11=P$1,$D11,"") | Q3: =IF($G12=Q$1,$D12,"") | R3: =IF($G13=R$1,$D13,"") | S3: =IF($G14=S$1,$D14,"") | T3: =IF($G15=T$1,$D15,"") | U3: =IF($G16=U$1,$D16,"") | V3: =IF($G17=V$1,$D17,"") | W3: =CONCATENATE(H3," ",I3," ",J3," ",K3," ",L3," ",M3," ",N3," ",O3," ",P3," ",Q3," ",R3," ",S3," ",T3," ",U3," ",V3) -> A Guide to the Project Management Body of Knowledge (PMBOK Guide) The PMI publication that defines widely accepted project management practices. The CAPM and the PMP exam are based on this book.
A4: =C4=D4 -> FALSE | B4: =B3+1 -> 3 | C4: Project Management Fundamental Terms | D4: The PMI publication that defines widely accepted project management practices. The CAPM and the PMP exam are based on this book. | E4: =LEN(D4) -> 128 | G4: =IF(F4=1,1,G3+1) -> 2 | H4: =IF($G4=H$1,$D4,"") | I4: =IF($G5=I$1,$D5,"") | J4: =IF($G6=J$1,$D6,"") | K4: =IF($G7=K$1,$D7,"") | L4: =IF($G8=L$1,$D8,"") | M4: =IF($G9=M$1,$D9,"") | N4: =IF($G10=N$1,$D10,"") | O4: =IF($G11=O$1,$D11,"") | P4: =IF($G12=P$1,$D12,"") | Q4: =IF($G13=Q$1,$D13,"") | R4: =IF($G14=R$1,$D14,"") | S4: =IF($G15=S$1,$D15,"") | T4: =IF($G16=T$1,$D16,"") | U4: =IF($G17=U$1,$D17,"") | V4: =IF($G18=V$1,$D18,"") | W4: =CONCATENATE(H4," ",I4," ",J4," ",K4," ",L4," ",M4," ",N4," ",O4," ",P4," ",Q4," ",R4," ",S4," ",T4," ",U4," ",V4)
A5: =C5=D5 -> FALSE | B5: =B4+1 -> 4 | C5: Project Management Fundamental Terms | D5: Application areas | E5: =LEN(D5) -> 17 | F5: 1 | G5: =IF(F5=1,1,G4+1) -> 1 | H5: =IF($G5=H$1,$D5,"") -> Application areas | I5: =IF($G6=I$1,$D6,"") -> The areas of expertise, industry, or function where a project is centered. Examples of application areas include architecture, IT, health care, and manufacturing. | J5: =IF($G7=J$1,$D7,"") | K5: =IF($G8=K$1,$D8,"") | L5: =IF($G9=L$1,$D9,"") | M5: =IF($G10=M$1,$D10,"") | N5: =IF($G11=N$1,$D11,"") | O5: =IF($G12=O$1,$D12,"") | P5: =IF($G13=P$1,$D13,"") | Q5: =IF($G14=Q$1,$D14,"") | R5: =IF($G15=R$1,$D15,"") | S5: =IF($G16=S$1,$D16,"") | T5: =IF($G17=T$1,$D17,"") | U5: =IF($G18=U$1,$D18,"") | V5: =IF($G19=V$1,$D19,"") | W5: =CONCATENATE(H5," ",I5," ",J5," ",K5," ",L5," ",M5," ",N5," ",O5," ",P5," ",Q5," ",R5," ",S5," ",T5," ",U5," ",V5) -> Application areas The areas of expertise, industry, or function where a project is centered. Examples of application areas include architecture, IT, health care, and manufacturing.
A6: =C6=D6 -> FALSE | B6: =B5+1 -> 5 | C6: Project Management Fundamental Terms | D6: The areas of expertise, industry, or function where a project is centered. Examples of application areas include architecture, IT, health care, and manufacturing. | E6: =LEN(D6) -> 162 | G6: =IF(F6=1,1,G5+1) -> 2 | H6: =IF($G6=H$1,$D6,"") | I6: =IF($G7=I$1,$D7,"") | J6: =IF($G8=J$1,$D8,"") | K6: =IF($G9=K$1,$D9,"") | L6: =IF($G10=L$1,$D10,"") | M6: =IF($G11=M$1,$D11,"") | N6: =IF($G12=N$1,$D12,"") | O6: =IF($G13=O$1,$D13,"") | P6: =IF($G14=P$1,$D14,"") | Q6: =IF($G15=Q$1,$D15,"") | R6: =IF($G16=R$1,$D16,"") | S6: =IF($G17=S$1,$D17,"") | T6: =IF($G18=T$1,$D18,"") | U6: =IF($G19=U$1,$D19,"") | V6: =IF($G20=V$1,$D20,"") | W6: =CONCATENATE(H6," ",I6," ",J6," ",K6," ",L6," ",M6," ",N6," ",O6," ",P6," ",Q6," ",R6," ",S6," ",T6," ",U6," ",V6)
A7: =C7=D7 -> FALSE | B7: =B6+1 -> 6 | C7: Project Management Fundamental Terms | D7: Business value | E7: =LEN(D7) -> 14 | F7: 1 | G7: =IF(F7=1,1,G6+1) -> 1 | H7: =IF($G7=H$1,$D7,"") -> Business value | I7: =IF($G8=I$1,$D8,"") -> A quantifiable return on investment. The return can be tangible, such as equipment, money, or market share. The return can also be intangible, such as brand recognition, trademarks, and reputation. | J7: =IF($G9=J$1,$D9,"") | K7: =IF($G10=K$1,$D10,"") | L7: =IF($G11=L$1,$D11,"") | M7: =IF($G12=M$1,$D12,"") | N7: =IF($G13=N$1,$D13,"") | O7: =IF($G14=O$1,$D14,"") | P7: =IF($G15=P$1,$D15,"") | Q7: =IF($G16=Q$1,$D16,"") | R7: =IF($G17=R$1,$D17,"") | S7: =IF($G18=S$1,$D18,"") | T7: =IF($G19=T$1,$D19,"") | U7: =IF($G20=U$1,$D20,"") | V7: =IF($G21=V$1,$D21,"") | W7: =CONCATENATE(H7," ",I7," ",J7," ",K7," ",L7," ",M7," ",N7," ",O7," ",P7," ",Q7," ",R7," ",S7," ",T7," ",U7," ",V7) -> Business value A quantifiable return on investment. The return can be tangible, such as equipment, money, or market share. The return can also be intangible, such as brand recognition, trademarks, and reputation.
A8: =C8=D8 -> FALSE | B8: =B7+1 -> 7 | C8: Project Management Fundamental Terms | D8: A quantifiable return on investment. The return can be tangible, such as equipment, money, or market share. The return can also be intangible, such as brand recognition, trademarks, and reputation. | E8: =LEN(D8) -> 197 | G8: =IF(F8=1,1,G7+1) -> 2 | H8: =IF($G8=H$1,$D8,"") | I8: =IF($G9=I$1,$D9,"") | J8: =IF($G10=J$1,$D10,"") | K8: =IF($G11=K$1,$D11,"") | L8: =IF($G12=L$1,$D12,"") | M8: =IF($G13=M$1,$D13,"") | N8: =IF($G14=N$1,$D14,"") | O8: =IF($G15=O$1,$D15,"") | P8: =IF($G16=P$1,$D16,"") | Q8: =IF($G17=Q$1,$D17,"") | R8: =IF($G18=R$1,$D18,"") | S8: =IF($G19=S$1,$D19,"") | T8: =IF($G20=T$1,$D20,"") | U8: =IF($G21=U$1,$D21,"") | V8: =IF($G22=V$1,$D22,"") | W8: =CONCATENATE(H8," ",I8," ",J8," ",K8," ",L8," ",M8," ",N8," ",O8," ",P8," ",Q8," ",R8," ",S8," ",T8," ",U8," ",V8)
A9: =C9=D9 -> FALSE | B9: =B8+1 -> 8 | C9: Project Management Fundamental Terms | D9: Certified Associate in Project Management (CAPM) | E9: =LEN(D9) -> 48 | F9: 1 | G9: =IF(F9=1,1,G8+1) -> 1 | H9: =IF($G9=H$1,$D9,"") -> Certified Associate in Project Management (CAPM) | I9: =IF($G10=I$1,$D10,"") -> A person who has slightly less project management experience than a PMP, but who has qualified for and then passed the CAPM examination. | J9: =IF($G11=J$1,$D11,"") | K9: =IF($G12=K$1,$D12,"") | L9: =IF($G13=L$1,$D13,"") | M9: =IF($G14=M$1,$D14,"") | N9: =IF($G15=N$1,$D15,"") | O9: =IF($G16=O$1,$D16,"") | P9: =IF($G17=P$1,$D17,"") | Q9: =IF($G18=Q$1,$D18,"") | R9: =IF($G19=R$1,$D19,"") | S9: =IF($G20=S$1,$D20,"") | T9: =IF($G21=T$1,$D21,"") | U9: =IF($G22=U$1,$D22,"") | V9: =IF($G23=V$1,$D23,"") | W9: =CONCATENATE(H9," ",I9," ",J9," ",K9," ",L9," ",M9," ",N9," ",O9," ",P9," ",Q9," ",R9," ",S9," ",T9," ",U9," ",V9) -> Certified Associate in Project Management (CAPM) A person who has slightly less project management experience than a PMP, but who has qualified for and then passed the CAPM examination.
A10: =C10=D10 -> FALSE | B10: =B9+1 -> 9 | C10: Project Management Fundamental Terms | D10: A person who has slightly less project management experience than a PMP, but who has qualified for and then passed the CAPM examination. | E10: =LEN(D10) -> 136 | G10: =IF(F10=1,1,G9+1) -> 2 | H10: =IF($G10=H$1,$D10,"") | I10: =IF($G11=I$1,$D11,"") | J10: =IF($G12=J$1,$D12,"") | K10: =IF($G13=K$1,$D13,"") | L10: =IF($G14=L$1,$D14,"") | M10: =IF($G15=M$1,$D15,"") | N10: =IF($G16=N$1,$D16,"") | O10: =IF($G17=O$1,$D17,"") | P10: =IF($G18=P$1,$D18,"") | Q10: =IF($G19=Q$1,$D19,"") | R10: =IF($G20=R$1,$D20,"") | S10: =IF($G21=S$1,$D21,"") | T10: =IF($G22=T$1,$D22,"") | U10: =IF($G23=U$1,$D23,"") | V10: =IF($G24=V$1,$D24,"") | W10: =CONCATENATE(H10," ",I10," ",J10," ",K10," ",L10," ",M10," ",N10," ",O10," ",P10," ",Q10," ",R10," ",S10," ",T10," ",U10," ",V10)
A11: =C11=D11 -> FALSE | B11: =B10+1 -> 10 | C11: Project Management Fundamental Terms | D11: Cultural and social environment | E11: =LEN(D11) -> 31 | F11: 1 | G11: =IF(F11=1,1,G10+1) -> 1 | H11: =IF($G11=H$1,$D11,"") -> Cultural and social environment | I11: =IF($G12=I$1,$D12,"") -> Defines how a project affects people and how those people may affect the project. Cultural and social environments include the economic, educational, ethical, religious, demographic, and ethnic composition of the people affected by the project. | J11: =IF($G13=J$1,$D13,"") | K11: =IF($G14=K$1,$D14,"") | L11: =IF($G15=L$1,$D15,"") | M11: =IF($G16=M$1,$D16,"") | N11: =IF($G17=N$1,$D17,"") | O11: =IF($G18=O$1,$D18,"") | P11: =IF($G19=P$1,$D19,"") | Q11: =IF($G20=Q$1,$D20,"") | R11: =IF($G21=R$1,$D21,"") | S11: =IF($G22=S$1,$D22,"") | T11: =IF($G23=T$1,$D23,"") | U11: =IF($G24=U$1,$D24,"") | V11: =IF($G25=V$1,$D25,"") | W11: =CONCATENATE(H11," ",I11," ",J11," ",K11," ",L11," ",M11," ",N11," ",O11," ",P11," ",Q11," ",R11," ",S11," ",T11," ",U11," ",V11) -> Cultural and social environment Defines how a project affects people and how those people may affect the project. Cultural and social environments include the economic, educational, ethical, religious, demographic, and ethnic composition of the people affected by the project.
A12: =C12=D12 -> FALSE | B12: =B11+1 -> 11 | C12: Project Management Fundamental Terms | D12: Defines how a project affects people and how those people may affect the project. Cultural and social environments include the economic, educational, ethical, religious, demographic, and ethnic composition of the people affected by the project. | E12: =LEN(D12) -> 244 | G12: =IF(F12=1,1,G11+1) -> 2 | H12: =IF($G12=H$1,$D12,"") | I12: =IF($G13=I$1,$D13,"") | J12: =IF($G14=J$1,$D14,"") | K12: =IF($G15=K$1,$D15,"") | L12: =IF($G16=L$1,$D16,"") | M12: =IF($G17=M$1,$D17,"") | N12: =IF($G18=N$1,$D18,"") | O12: =IF($G19=O$1,$D19,"") | P12: =IF($G20=P$1,$D20,"") | Q12: =IF($G21=Q$1,$D21,"") | R12: =IF($G22=R$1,$D22,"") | S12: =IF($G23=S$1,$D23,"") | T12: =IF($G24=T$1,$D24,"") | U12: =IF($G25=U$1,$D25,"") | V12: =IF($G26=V$1,$D26,"") | W12: =CONCATENATE(H12," ",I12," ",J12," ",K12," ",L12," ",M12," ",N12," ",O12," ",P12," ",Q12," ",R12," ",S12," ",T12," ",U12," ",V12)
A13: =C13=D13 -> FALSE | B13: =B12+1 -> 12 | C13: Project Management Fundamental Terms | D13: Deliverable | E13: =LEN(D13) -> 11 | F13: 1 | G13: =IF(F13=1,1,G12+1) -> 1 | H13: =IF($G13=H$1,$D13,"") -> Deliverable | I13: =IF($G14=I$1,$D14,"") -> A product, service, or result created by a project. Projects can have multiple deliverables. | J13: =IF($G15=J$1,$D15,"") | K13: =IF($G16=K$1,$D16,"") | L13: =IF($G17=L$1,$D17,"") | M13: =IF($G18=M$1,$D18,"") | N13: =IF($G19=N$1,$D19,"") | O13: =IF($G20=O$1,$D20,"") | P13: =IF($G21=P$1,$D21,"") | Q13: =IF($G22=Q$1,$D22,"") | R13: =IF($G23=R$1,$D23,"") | S13: =IF($G24=S$1,$D24,"") | T13: =IF($G25=T$1,$D25,"") | U13: =IF($G26=U$1,$D26,"") | V13: =IF($G27=V$1,$D27,"") | W13: =CONCATENATE(H13," ",I13," ",J13," ",K13," ",L13," ",M13," ",N13," ",O13," ",P13," ",Q13," ",R13," ",S13," ",T13," ",U13," ",V13) -> Deliverable A product, service, or result created by a project. Projects can have multiple deliverables.
A14: =C14=D14 -> FALSE | B14: =B13+1 -> 13 | C14: Project Management Fundamental Terms | D14: A product, service, or result created by a project. Projects can have multiple deliverables. | E14: =LEN(D14) -> 92 | G14: =IF(F14=1,1,G13+1) -> 2 | H14: =IF($G14=H$1,$D14,"") | I14: =IF($G15=I$1,$D15,"") | J14: =IF($G16=J$1,$D16,"") | K14: =IF($G17=K$1,$D17,"") | L14: =IF($G18=L$1,$D18,"") | M14: =IF($G19=M$1,$D19,"") | N14: =IF($G20=N$1,$D20,"") | O14: =IF($G21=O$1,$D21,"") | P14: =IF($G22=P$1,$D22,"") | Q14: =IF($G23=Q$1,$D23,"") | R14: =IF($G24=R$1,$D24,"") | S14: =IF($G25=S$1,$D25,"") | T14: =IF($G26=T$1,$D26,"") | U14: =IF($G27=U$1,$D27,"") | V14: =IF($G28=V$1,$D28,"") | W14: =CONCATENATE(H14," ",I14," ",J14," ",K14," ",L14," ",M14," ",N14," ",O14," ",P14," ",Q14," ",R14," ",S14," ",T14," ",U14," ",V14)
A15: =C15=D15 -> FALSE | B15: =B14+1 -> 14 | C15: Project Management Fundamental Terms | D15: General management skills | E15: =LEN(D15) -> 25 | F15: 1 | G15: =IF(F15=1,1,G14+1) -> 1 | H15: =IF($G15=H$1,$D15,"") -> General management skills | I15: =IF($G16=I$1,$D16,"") -> These include the application of accounting, procurement, sales and marketing, contracting, manufacturing, logistics, strategic planning, human resource management, standards and regulations, and information technology. | J15: =IF($G17=J$1,$D17,"") -> International and political environment | K15: =IF($G18=K$1,$D18,"") -> The consideration of the local and international laws, languages, communication challenges, time zone differences, and other non-collocated issues that affect a project’s ability to progress. | L15: =IF($G19=L$1,$D19,"") | M15: =IF($G20=M$1,$D20,"") | N15: =IF($G21=N$1,$D21,"") | O15: =IF($G22=O$1,$D22,"") | P15: =IF($G23=P$1,$D23,"") | Q15: =IF($G24=Q$1,$D24,"") | R15: =IF($G25=R$1,$D25,"") | S15: =IF($G26=S$1,$D26,"") | T15: =IF($G27=T$1,$D27,"") | U15: =IF($G28=U$1,$D28,"") | V15: =IF($G29=V$1,$D29,"") | W15: =CONCATENATE(H15," ",I15," ",J15," ",K15," ",L15," ",M15," ",N15," ",O15," ",P15," ",Q15," ",R15," ",S15," ",T15," ",U15," ",V15) -> General management skills These include the application of accounting, procurement, sales and marketing, contracting, manufacturing, logistics, strategic planning, human resource management, standards and regulations, and information technology. International and political environment The consideration of the local and international laws, languages, communication challenges, time zone differences, and other non-collocated issues that affect a project’s ability to progress.
A16: =C16=D16 -> FALSE | B16: =B15+1 -> 15 | C16: Project Management Fundamental Terms | D16: These include the application of accounting, procurement, sales and marketing, contracting, manufacturing, logistics, strategic planning, human resource management, standards and regulations, and information technology. | E16: =LEN(D16) -> 219 | G16: =IF(F16=1,1,G15+1) -> 2 | H16: =IF($G16=H$1,$D16,"") | I16: =IF($G17=I$1,$D17,"") | J16: =IF($G18=J$1,$D18,"") | K16: =IF($G19=K$1,$D19,"") | L16: =IF($G20=L$1,$D20,"") | M16: =IF($G21=M$1,$D21,"") | N16: =IF($G22=N$1,$D22,"") | O16: =IF($G23=O$1,$D23,"") | P16: =IF($G24=P$1,$D24,"") | Q16: =IF($G25=Q$1,$D25,"") | R16: =IF($G26=R$1,$D26,"") | S16: =IF($G27=S$1,$D27,"") | T16: =IF($G28=T$1,$D28,"") | U16: =IF($G29=U$1,$D29,"") | V16: =IF($G30=V$1,$D30,"") | W16: =CONCATENATE(H16," ",I16," ",J16," ",K16," ",L16," ",M16," ",N16," ",O16," ",P16," ",Q16," ",R16," ",S16," ",T16," ",U16," ",V16)
A17: =C17=D17 -> FALSE | B17: =B16+1 -> 16 | C17: Project Management Fundamental Terms | D17: International and political environment | E17: =LEN(D17) -> 39 | G17: =IF(F17=1,1,G16+1) -> 3 | H17: =IF($G17=H$1,$D17,"") | I17: =IF($G18=I$1,$D18,"") | J17: =IF($G19=J$1,$D19,"") | K17: =IF($G20=K$1,$D20,"") | L17: =IF($G21=L$1,$D21,"") | M17: =IF($G22=M$1,$D22,"") | N17: =IF($G23=N$1,$D23,"") | O17: =IF($G24=O$1,$D24,"") | P17: =IF($G25=P$1,$D25,"") | Q17: =IF($G26=Q$1,$D26,"") | R17: =IF($G27=R$1,$D27,"") | S17: =IF($G28=S$1,$D28,"") | T17: =IF($G29=T$1,$D29,"") | U17: =IF($G30=U$1,$D30,"") | V17: =IF($G31=V$1,$D31,"") | W17: =CONCATENATE(H17," ",I17," ",J17," ",K17," ",L17," ",M17," ",N17," ",O17," ",P17," ",Q17," ",R17," ",S17," ",T17," ",U17," ",V17)
A18: =C18=D18 -> FALSE | B18: =B17+1 -> 17 | C18: Project Management Fundamental Terms | D18: The consideration of the local and international laws, languages, communication challenges, time zone differences, and other non-collocated issues that affect a project’s ability to progress. | E18: =LEN(D18) -> 191 | G18: =IF(F18=1,1,G17+1) -> 4 | H18: =IF($G18=H$1,$D18,"") | I18: =IF($G19=I$1,$D19,"") | J18: =IF($G20=J$1,$D20,"") | K18: =IF($G21=K$1,$D21,"") | L18: =IF($G22=L$1,$D22,"") | M18: =IF($G23=M$1,$D23,"") | N18: =IF($G24=N$1,$D24,"") | O18: =IF($G25=O$1,$D25,"") | P18: =IF($G26=P$1,$D26,"") | Q18: =IF($G27=Q$1,$D27,"") | R18: =IF($G28=R$1,$D28,"") | S18: =IF($G29=S$1,$D29,"") | T18: =IF($G30=T$1,$D30,"") | U18: =IF($G31=U$1,$D31,"") | V18: =IF($G32=V$1,$D32,"") | W18: =CONCATENATE(H18," ",I18," ",J18," ",K18," ",L18," ",M18," ",N18," ",O18," ",P18," ",Q18," ",R18," ",S18," ",T18," ",U18," ",V18)
A19: =C19=D19 -> FALSE | B19: =B18+1 -> 18 | C19: Project Management Fundamental Terms | D19: Interpersonal skills | E19: =LEN(D19) -> 20 | F19: 1 | G19: =IF(F19=1,1,G18+1) -> 1 | H19: =IF($G19=H$1,$D19,"") -> Interpersonal skills | I19: =IF($G20=I$1,$D20,"") -> The ability to interact, lead, motivate, and manage people. | J19: =IF($G21=J$1,$D21,"") | K19: =IF($G22=K$1,$D22,"") | L19: =IF($G23=L$1,$D23,"") | M19: =IF($G24=M$1,$D24,"") | N19: =IF($G25=N$1,$D25,"") | O19: =IF($G26=O$1,$D26,"") | P19: =IF($G27=P$1,$D27,"") | Q19: =IF($G28=Q$1,$D28,"") | R19: =IF($G29=R$1,$D29,"") | S19: =IF($G30=S$1,$D30,"") | T19: =IF($G31=T$1,$D31,"") | U19: =IF($G32=U$1,$D32,"") | V19: =IF($G33=V$1,$D33,"") | W19: =CONCATENATE(H19," ",I19," ",J19," ",K19," ",L19," ",M19," ",N19," ",O19," ",P19," ",Q19," ",R19," ",S19," ",T19," ",U19," ",V19) -> Interpersonal skills The ability to interact, lead, motivate, and manage people.
A20: =C20=D20 -> FALSE | B20: =B19+1 -> 19 | C20: Project Management Fundamental Terms | D20: The ability to interact, lead, motivate, and manage people. | E20: =LEN(D20) -> 59 | G20: =IF(F20=1,1,G19+1) -> 2 | H20: =IF($G20=H$1,$D20,"") | I20: =IF($G21=I$1,$D21,"") | J20: =IF($G22=J$1,$D22,"") | K20: =IF($G23=K$1,$D23,"") | L20: =IF($G24=L$1,$D24,"") | M20: =IF($G25=M$1,$D25,"") | N20: =IF($G26=N$1,$D26,"") | O20: =IF($G27=O$1,$D27,"") | P20: =IF($G28=P$1,$D28,"") | Q20: =IF($G29=Q$1,$D29,"") | R20: =IF($G30=R$1,$D30,"") | S20: =IF($G31=S$1,$D31,"") | T20: =IF($G32=T$1,$D32,"") | U20: =IF($G33=U$1,$D33,"") | V20: =IF($G34=V$1,$D34,"") | W20: =CONCATENATE(H20," ",I20," ",J20," ",K20," ",L20," ",M20," ",N20," ",O20," ",P20," ",Q20," ",R20," ",S20," ",T20," ",U20," ",V20)
A21: =C21=D21 -> FALSE | B21: =B20+1 -> 20 | C21: Project Management Fundamental Terms | D21: Iron Triangle of Project Management | E21: =LEN(D21) -> 35 | F21: 1 | G21: =IF(F21=1,1,G20+1) -> 1 | H21: =IF($G21=H$1,$D21,"") -> Iron Triangle of Project Management | I21: =IF($G22=I$1,$D22,"") -> A triangle with the characteristics of time, cost, and scope. Time, cost, and scope each constitute one side of the triangle; if any side of the Iron Triangle is not in balance with the other sides, the project will suffer. The Iron Triangle of Project Management is also known as the Triple Constraints of Project Management, as all projects are constrained by time, cost, and scope. | J21: =IF($G23=J$1,$D23,"") | K21: =IF($G24=K$1,$D24,"") | L21: =IF($G25=L$1,$D25,"") | M21: =IF($G26=M$1,$D26,"") | N21: =IF($G27=N$1,$D27,"") | O21: =IF($G28=O$1,$D28,"") | P21: =IF($G29=P$1,$D29,"") | Q21: =IF($G30=Q$1,$D30,"") | R21: =IF($G31=R$1,$D31,"") | S21: =IF($G32=S$1,$D32,"") | T21: =IF($G33=T$1,$D33,"") | U21: =IF($G34=U$1,$D34,"") | V21: =IF($G35=V$1,$D35,"") | W21: =CONCATENATE(H21," ",I21," ",J21," ",K21," ",L21," ",M21," ",N21," ",O21," ",P21," ",Q21," ",R21," ",S21," ",T21," ",U21," ",V21) -> Iron Triangle of Project Management A triangle with the characteristics of time, cost, and scope. Time, cost, and scope each constitute one side of the triangle; if any side of the Iron Triangle is not in balance with the other sides, the project will suffer. The Iron Triangle of Project Management is also known as the Triple Constraints of Project Management, as all projects are constrained by time, cost, and scope.
A22: =C22=D22 -> FALSE | B22: =B21+1 -> 21 | C22: Project Management Fundamental Terms | D22: A triangle with the characteristics of time, cost, and scope. Time, cost, and scope each constitute one side of the triangle; if any side of the Iron Triangle is not in balance with the other sides, the project will suffer. The Iron Triangle of Project Management is also known as the Triple Constraints of Project Management, as all projects are constrained by time, cost, and scope. | E22: =LEN(D22) -> 384 | G22: =IF(F22=1,1,G21+1) -> 2 | H22: =IF($G22=H$1,$D22,"") | I22: =IF($G23=I$1,$D23,"") | J22: =IF($G24=J$1,$D24,"") | K22: =IF($G25=K$1,$D25,"") | L22: =IF($G26=L$1,$D26,"") | M22: =IF($G27=M$1,$D27,"") | N22: =IF($G28=N$1,$D28,"") | O22: =IF($G29=O$1,$D29,"") | P22: =IF($G30=P$1,$D30,"") | Q22: =IF($G31=Q$1,$D31,"") | R22: =IF($G32=R$1,$D32,"") | S22: =IF($G33=S$1,$D33,"") | T22: =IF($G34=T$1,$D34,"") | U22: =IF($G35=U$1,$D35,"") | V22: =IF($G36=V$1,$D36,"") | W22: =CONCATENATE(H22," ",I22," ",J22," ",K22," ",L22," ",M22," ",N22," ",O22," ",P22," ",Q22," ",R22," ",S22," ",T22," ",U22," ",V22)
A23: =C23=D23 -> FALSE | B23: =B22+1 -> 22 | C23: Project Management Fundamental Terms | D23: Physical environment | E23: =LEN(D23) -> 20 | F23: 1 | G23: =IF(F23=1,1,G22+1) -> 1 | H23: =IF($G23=H$1,$D23,"") -> Physical environment | I23: =IF($G24=I$1,$D24,"") -> The physical structure and surroundings that affect a project’s work. | J23: =IF($G25=J$1,$D25,"") | K23: =IF($G26=K$1,$D26,"") | L23: =IF($G27=L$1,$D27,"") | M23: =IF($G28=M$1,$D28,"") | N23: =IF($G29=N$1,$D29,"") | O23: =IF($G30=O$1,$D30,"") | P23: =IF($G31=P$1,$D31,"") | Q23: =IF($G32=Q$1,$D32,"") | R23: =IF($G33=R$1,$D33,"") | S23: =IF($G34=S$1,$D34,"") | T23: =IF($G35=T$1,$D35,"") | U23: =IF($G36=U$1,$D36,"") | V23: =IF($G37=V$1,$D37,"") | W23: =CONCATENATE(H23," ",I23," ",J23," ",K23," ",L23," ",M23," ",N23," ",O23," ",P23," ",Q23," ",R23," ",S23," ",T23," ",U23," ",V23) -> Physical environment The physical structure and surroundings that affect a project’s work.
A24: =C24=D24 -> FALSE | B24: =B23+1 -> 23 | C24: Project Management Fundamental Terms | D24: The physical structure and surroundings that affect a project’s work. | E24: =LEN(D24) -> 69 | G24: =IF(F24=1,1,G23+1) -> 2 | H24: =IF($G24=H$1,$D24,"") | I24: =IF($G25=I$1,$D25,"") | J24: =IF($G26=J$1,$D26,"") | K24: =IF($G27=K$1,$D27,"") | L24: =IF($G28=L$1,$D28,"") | M24: =IF($G29=M$1,$D29,"") | N24: =IF($G30=N$1,$D30,"") | O24: =IF($G31=O$1,$D31,"") | P24: =IF($G32=P$1,$D32,"") | Q24: =IF($G33=Q$1,$D33,"") | R24: =IF($G34=R$1,$D34,"") | S24: =IF($G35=S$1,$D35,"") | T24: =IF($G36=T$1,$D36,"") | U24: =IF($G37=U$1,$D37,"") | V24: =IF($G38=V$1,$D38,"") | W24: =CONCATENATE(H24," ",I24," ",J24," ",K24," ",L24," ",M24," ",N24," ",O24," ",P24," ",Q24," ",R24," ",S24," ",T24," ",U24," ",V24)
A25: =C25=D25 -> FALSE | B25: =B24+1 -> 24 | C25: Project Management Fundamental Terms | D25: Process groups | E25: =LEN(D25) -> 14 | F25: 1 | G25: =IF(F25=1,1,G24+1) -> 1 | H25: =IF($G25=H$1,$D25,"") -> Process groups | I25: =IF($G26=I$1,$D26,"") -> A collection of related processes in project management. There are five process groups and 49 project management processes. The five process groups are Initiating, Planning, Executing, Monitoring and Controlling, and Closing. | J25: =IF($G27=J$1,$D27,"") | K25: =IF($G28=K$1,$D28,"") | L25: =IF($G29=L$1,$D29,"") | M25: =IF($G30=M$1,$D30,"") | N25: =IF($G31=N$1,$D31,"") | O25: =IF($G32=O$1,$D32,"") | P25: =IF($G33=P$1,$D33,"") | Q25: =IF($G34=Q$1,$D34,"") | R25: =IF($G35=R$1,$D35,"") | S25: =IF($G36=S$1,$D36,"") | T25: =IF($G37=T$1,$D37,"") | U25: =IF($G38=U$1,$D38,"") | V25: =IF($G39=V$1,$D39,"") | W25: =CONCATENATE(H25," ",I25," ",J25," ",K25," ",L25," ",M25," ",N25," ",O25," ",P25," ",Q25," ",R25," ",S25," ",T25," ",U25," ",V25) -> Process groups A collection of related processes in project management. There are five process groups and 49 project management processes. The five process groups are Initiating, Planning, Executing, Monitoring and Controlling, and Closing.
A26: =C26=D26 -> FALSE | B26: =B25+1 -> 25 | C26: Project Management Fundamental Terms | D26: A collection of related processes in project management. There are five process groups and 49 project management processes. The five process groups are Initiating, Planning, Executing, Monitoring and Controlling, and Closing. | E26: =LEN(D26) -> 225 | G26: =IF(F26=1,1,G25+1) -> 2 | H26: =IF($G26=H$1,$D26,"") | I26: =IF($G27=I$1,$D27,"") | J26: =IF($G28=J$1,$D28,"") | K26: =IF($G29=K$1,$D29,"") | L26: =IF($G30=L$1,$D30,"") | M26: =IF($G31=M$1,$D31,"") | N26: =IF($G32=N$1,$D32,"") | O26: =IF($G33=O$1,$D33,"") | P26: =IF($G34=P$1,$D34,"") | Q26: =IF($G35=Q$1,$D35,"") | R26: =IF($G36=R$1,$D36,"") | S26: =IF($G37=S$1,$D37,"") | T26: =IF($G38=T$1,$D38,"") | U26: =IF($G39=U$1,$D39,"") | V26: =IF($G40=V$1,$D40,"") | W26: =CONCATENATE(H26," ",I26," ",J26," ",K26," ",L26," ",M26," ",N26," ",O26," ",P26," ",Q26," ",R26," ",S26," ",T26," ",U26," ",V26)
A27: =C27=D27 -> FALSE | B27: =B26+1 -> 26 | C27: Project Management Fundamental Terms | D27: Program | E27: =LEN(D27) -> 7 | F27: 1 | G27: =IF(F27=1,1,G26+1) -> 1 | H27: =IF($G27=H$1,$D27,"") -> Program | I27: =IF($G28=I$1,$D28,"") -> A collection of related projects working in unison toward a common deliverable. | J27: =IF($G29=J$1,$D29,"") | K27: =IF($G30=K$1,$D30,"") | L27: =IF($G31=L$1,$D31,"") | M27: =IF($G32=M$1,$D32,"") | N27: =IF($G33=N$1,$D33,"") | O27: =IF($G34=O$1,$D34,"") | P27: =IF($G35=P$1,$D35,"") | Q27: =IF($G36=Q$1,$D36,"") | R27: =IF($G37=R$1,$D37,"") | S27: =IF($G38=S$1,$D38,"") | T27: =IF($G39=T$1,$D39,"") | U27: =IF($G40=U$1,$D40,"") | V27: =IF($G41=V$1,$D41,"") | W27: =CONCATENATE(H27," ",I27," ",J27," ",K27," ",L27," ",M27," ",N27," ",O27," ",P27," ",Q27," ",R27," ",S27," ",T27," ",U27," ",V27) -> Program A collection of related projects working in unison toward a common deliverable.
A28: =C28=D28 -> FALSE | B28: =B27+1 -> 27 | C28: Project Management Fundamental Terms | D28: A collection of related projects working in unison toward a common deliverable. | E28: =LEN(D28) -> 79 | G28: =IF(F28=1,1,G27+1) -> 2 | H28: =IF($G28=H$1,$D28,"") | I28: =IF($G29=I$1,$D29,"") | J28: =IF($G30=J$1,$D30,"") | K28: =IF($G31=K$1,$D31,"") | L28: =IF($G32=L$1,$D32,"") | M28: =IF($G33=M$1,$D33,"") | N28: =IF($G34=N$1,$D34,"") | O28: =IF($G35=O$1,$D35,"") | P28: =IF($G36=P$1,$D36,"") | Q28: =IF($G37=Q$1,$D37,"") | R28: =IF($G38=R$1,$D38,"") | S28: =IF($G39=S$1,$D39,"") | T28: =IF($G40=T$1,$D40,"") | U28: =IF($G41=U$1,$D41,"") | V28: =IF($G42=V$1,$D42,"") | W28: =CONCATENATE(H28," ",I28," ",J28," ",K28," ",L28," ",M28," ",N28," ",O28," ",P28," ",Q28," ",R28," ",S28," ",T28," ",U28," ",V28)
A29: =C29=D29 -> FALSE | B29: =B28+1 -> 28 | C29: Project Management Fundamental Terms | D29: Progressive elaboration | E29: =LEN(D29) -> 23 | F29: 1 | G29: =IF(F29=1,1,G28+1) -> 1 | H29: =IF($G29=H$1,$D29,"") -> Progressive elaboration | I29: =IF($G30=I$1,$D30,"") -> The process of gathering project details. This process uses deductive reasoning, logic, and a series of information-gathering techniques to identify details about a project, product, or solution. | J29: =IF($G31=J$1,$D31,"") | K29: =IF($G32=K$1,$D32,"") | L29: =IF($G33=L$1,$D33,"") | M29: =IF($G34=M$1,$D34,"") | N29: =IF($G35=N$1,$D35,"") | O29: =IF($G36=O$1,$D36,"") | P29: =IF($G37=P$1,$D37,"") | Q29: =IF($G38=Q$1,$D38,"") | R29: =IF($G39=R$1,$D39,"") | S29: =IF($G40=S$1,$D40,"") | T29: =IF($G41=T$1,$D41,"") | U29: =IF($G42=U$1,$D42,"") | V29: =IF($G43=V$1,$D43,"") | W29: =CONCATENATE(H29," ",I29," ",J29," ",K29," ",L29," ",M29," ",N29," ",O29," ",P29," ",Q29," ",R29," ",S29," ",T29," ",U29," ",V29) -> Progressive elaboration The process of gathering project details. This process uses deductive reasoning, logic, and a series of information-gathering techniques to identify details about a project, product, or solution.
A30: =C30=D30 -> FALSE | B30: =B29+1 -> 29 | C30: Project Management Fundamental Terms | D30: The process of gathering project details. This process uses deductive reasoning, logic, and a series of information-gathering techniques to identify details about a project, product, or solution. | E30: =LEN(D30) -> 195 | G30: =IF(F30=1,1,G29+1) -> 2 | H30: =IF($G30=H$1,$D30,"") | I30: =IF($G31=I$1,$D31,"") | J30: =IF($G32=J$1,$D32,"") | K30: =IF($G33=K$1,$D33,"") | L30: =IF($G34=L$1,$D34,"") | M30: =IF($G35=M$1,$D35,"") | N30: =IF($G36=N$1,$D36,"") | O30: =IF($G37=O$1,$D37,"") | P30: =IF($G38=P$1,$D38,"") | Q30: =IF($G39=Q$1,$D39,"") | R30: =IF($G40=R$1,$D40,"") | S30: =IF($G41=S$1,$D41,"") | T30: =IF($G42=T$1,$D42,"") | U30: =IF($G43=U$1,$D43,"") | V30: =IF($G44=V$1,$D44,"") | W30: =CONCATENATE(H30," ",I30," ",J30," ",K30," ",L30," ",M30," ",N30," ",O30," ",P30," ",Q30," ",R30," ",S30," ",T30," ",U30," ",V30)
A31: =C31=D31 -> FALSE | B31: =B30+1 -> 30 | C31: Project Management Fundamental Terms | D31: Project | E31: =LEN(D31) -> 7 | F31: 1 | G31: =IF(F31=1,1,G30+1) -> 1 | H31: =IF($G31=H$1,$D31,"") -> Project | I31: =IF($G32=I$1,$D32,"") -> A temporary endeavor to create a unique product, service, or result. The end result of a project is also called a deliverable. | J31: =IF($G33=J$1,$D33,"") | K31: =IF($G34=K$1,$D34,"") | L31: =IF($G35=L$1,$D35,"") | M31: =IF($G36=M$1,$D36,"") | N31: =IF($G37=N$1,$D37,"") | O31: =IF($G38=O$1,$D38,"") | P31: =IF($G39=P$1,$D39,"") | Q31: =IF($G40=Q$1,$D40,"") | R31: =IF($G41=R$1,$D41,"") | S31: =IF($G42=S$1,$D42,"") | T31: =IF($G43=T$1,$D43,"") | U31: =IF($G44=U$1,$D44,"") | V31: =IF($G45=V$1,$D45,"") | W31: =CONCATENATE(H31," ",I31," ",J31," ",K31," ",L31," ",M31," ",N31," ",O31," ",P31," ",Q31," ",R31," ",S31," ",T31," ",U31," ",V31) -> Project A temporary endeavor to create a unique product, service, or result. The end result of a project is also called a deliverable.
A32: =C32=D32 -> FALSE | B32: =B31+1 -> 31 | C32: Project Management Fundamental Terms | D32: A temporary endeavor to create a unique product, service, or result. The end result of a project is also called a deliverable. | E32: =LEN(D32) -> 126 | G32: =IF(F32=1,1,G31+1) -> 2 | H32: =IF($G32=H$1,$D32,"") | I32: =IF($G33=I$1,$D33,"") | J32: =IF($G34=J$1,$D34,"") | K32: =IF($G35=K$1,$D35,"") | L32: =IF($G36=L$1,$D36,"") | M32: =IF($G37=M$1,$D37,"") | N32: =IF($G38=N$1,$D38,"") | O32: =IF($G39=O$1,$D39,"") | P32: =IF($G40=P$1,$D40,"") | Q32: =IF($G41=Q$1,$D41,"") | R32: =IF($G42=R$1,$D42,"") | S32: =IF($G43=S$1,$D43,"") | T32: =IF($G44=T$1,$D44,"") | U32: =IF($G45=U$1,$D45,"") | V32: =IF($G46=V$1,$D46,"") | W32: =CONCATENATE(H32," ",I32," ",J32," ",K32," ",L32," ",M32," ",N32," ",O32," ",P32," ",Q32," ",R32," ",S32," ",T32," ",U32," ",V32)
A33: =C33=D33 -> FALSE | B33: =B32+1 -> 32 | C33: Project Management Fundamental Terms | D33: Project benefits management plan | E33: =LEN(D33) -> 32 | F33: 1 | G33: =IF(F33=1,1,G32+1) -> 1 | H33: =IF($G33=H$1,$D33,"") -> Project benefits management plan | I33: =IF($G34=I$1,$D34,"") -> A documented created and maintained by the project sponsor and the project manager. The project benefits management plan defines what benefits the project will create, when the benefits will be realized, and how the benefits will be measured. | J33: =IF($G35=J$1,$D35,"") | K33: =IF($G36=K$1,$D36,"") | L33: =IF($G37=L$1,$D37,"") | M33: =IF($G38=M$1,$D38,"") | N33: =IF($G39=N$1,$D39,"") | O33: =IF($G40=O$1,$D40,"") | P33: =IF($G41=P$1,$D41,"") | Q33: =IF($G42=Q$1,$D42,"") | R33: =IF($G43=R$1,$D43,"") | S33: =IF($G44=S$1,$D44,"") | T33: =IF($G45=T$1,$D45,"") | U33: =IF($G46=U$1,$D46,"") | V33: =IF($G47=V$1,$D47,"") | W33: =CONCATENATE(H33," ",I33," ",J33," ",K33," ",L33," ",M33," ",N33," ",O33," ",P33," ",Q33," ",R33," ",S33," ",T33," ",U33," ",V33) -> Project benefits management plan A documented created and maintained by the project sponsor and the project manager. The project benefits management plan defines what benefits the project will create, when the benefits will be realized, and how the benefits will be measured.
A34: =C34=D34 -> FALSE | B34: =B33+1 -> 33 | C34: Project Management Fundamental Terms | D34: A documented created and maintained by the project sponsor and the project manager. The project benefits management plan defines what benefits the project will create, when the benefits will be realized, and how the benefits will be measured. | E34: =LEN(D34) -> 242 | G34: =IF(F34=1,1,G33+1) -> 2 | H34: =IF($G34=H$1,$D34,"") | I34: =IF($G35=I$1,$D35,"") | J34: =IF($G36=J$1,$D36,"") | K34: =IF($G37=K$1,$D37,"") | L34: =IF($G38=L$1,$D38,"") | M34: =IF($G39=M$1,$D39,"") | N34: =IF($G40=N$1,$D40,"") | O34: =IF($G41=O$1,$D41,"") | P34: =IF($G42=P$1,$D42,"") | Q34: =IF($G43=Q$1,$D43,"") | R34: =IF($G44=R$1,$D44,"") | S34: =IF($G45=S$1,$D45,"") | T34: =IF($G46=T$1,$D46,"") | U34: =IF($G47=U$1,$D47,"") | V34: =IF($G48=V$1,$D48,"") | W34: =CONCATENATE(H34," ",I34," ",J34," ",K34," ",L34," ",M34," ",N34," ",O34," ",P34," ",Q34," ",R34," ",S34," ",T34," ",U34," ",V34)
A35: =C35=D35 -> FALSE | B35: =B34+1 -> 34 | C35: Project Management Fundamental Terms | D35: Project business case | E35: =LEN(D35) -> 21 | F35: 1 | G35: =IF(F35=1,1,G34+1) -> 1 | H35: =IF($G35=H$1,$D35,"") -> Project business case | I35: =IF($G36=I$1,$D36,"") -> Created and maintained by the project sponsor and shows the financial validity of why a project is chartered and launched within the organization. Typically, the project business case is created before the launch of the project and may be used as a go/no-go decision point. | J35: =IF($G37=J$1,$D37,"") | K35: =IF($G38=K$1,$D38,"") | L35: =IF($G39=L$1,$D39,"") | M35: =IF($G40=M$1,$D40,"") | N35: =IF($G41=N$1,$D41,"") | O35: =IF($G42=O$1,$D42,"") | P35: =IF($G43=P$1,$D43,"") | Q35: =IF($G44=Q$1,$D44,"") | R35: =IF($G45=R$1,$D45,"") | S35: =IF($G46=S$1,$D46,"") | T35: =IF($G47=T$1,$D47,"") | U35: =IF($G48=U$1,$D48,"") | V35: =IF($G49=V$1,$D49,"") | W35: =CONCATENATE(H35," ",I35," ",J35," ",K35," ",L35," ",M35," ",N35," ",O35," ",P35," ",Q35," ",R35," ",S35," ",T35," ",U35," ",V35) -> Project business case Created and maintained by the project sponsor and shows the financial validity of why a project is chartered and launched within the organization. Typically, the project business case is created before the launch of the project and may be used as a go/no-go decision point.
A36: =C36=D36 -> FALSE | B36: =B35+1 -> 35 | C36: Project Management Fundamental Terms | D36: Created and maintained by the project sponsor and shows the financial validity of why a project is chartered and launched within the organization. Typically, the project business case is created before the launch of the project and may be used as a go/no-go decision point. | E36: =LEN(D36) -> 273 | G36: =IF(F36=1,1,G35+1) -> 2 | H36: =IF($G36=H$1,$D36,"") | I36: =IF($G37=I$1,$D37,"") | J36: =IF($G38=J$1,$D38,"") | K36: =IF($G39=K$1,$D39,"") | L36: =IF($G40=L$1,$D40,"") | M36: =IF($G41=M$1,$D41,"") | N36: =IF($G42=N$1,$D42,"") | O36: =IF($G43=O$1,$D43,"") | P36: =IF($G44=P$1,$D44,"") | Q36: =IF($G45=Q$1,$D45,"") | R36: =IF($G46=R$1,$D46,"") | S36: =IF($G47=S$1,$D47,"") | T36: =IF($G48=T$1,$D48,"") | U36: =IF($G49=U$1,$D49,"") | V36: =IF($G50=V$1,$D50,"") | W36: =CONCATENATE(H36," ",I36," ",J36," ",K36," ",L36," ",M36," ",N36," ",O36," ",P36," ",Q36," ",R36," ",S36," ",T36," ",U36," ",V36)
A37: =C37=D37 -> FALSE | B37: =B36+1 -> 36 | C37: Project Management Fundamental Terms | D37: Project environment | E37: =LEN(D37) -> 19 | F37: 1 | G37: =IF(F37=1,1,G36+1) -> 1 | H37: =IF($G37=H$1,$D37,"") -> Project environment | I37: =IF($G38=I$1,$D38,"") -> The location and culture of the environment where the project work will reside. The project environment includes the social, economic, and environmental variables the project must work with or around. | J37: =IF($G39=J$1,$D39,"") | K37: =IF($G40=K$1,$D40,"") | L37: =IF($G41=L$1,$D41,"") | M37: =IF($G42=M$1,$D42,"") | N37: =IF($G43=N$1,$D43,"") | O37: =IF($G44=O$1,$D44,"") | P37: =IF($G45=P$1,$D45,"") | Q37: =IF($G46=Q$1,$D46,"") | R37: =IF($G47=R$1,$D47,"") | S37: =IF($G48=S$1,$D48,"") | T37: =IF($G49=T$1,$D49,"") | U37: =IF($G50=U$1,$D50,"") | V37: =IF($G51=V$1,$D51,"") | W37: =CONCATENATE(H37," ",I37," ",J37," ",K37," ",L37," ",M37," ",N37," ",O37," ",P37," ",Q37," ",R37," ",S37," ",T37," ",U37," ",V37) -> Project environment The location and culture of the environment where the project work will reside. The project environment includes the social, economic, and environmental variables the project must work with or around.
A38: =C38=D38 -> FALSE | B38: =B37+1 -> 37 | C38: Project Management Fundamental Terms | D38: The location and culture of the environment where the project work will reside. The project environment includes the social, economic, and environmental variables the project must work with or around. | E38: =LEN(D38) -> 200 | G38: =IF(F38=1,1,G37+1) -> 2 | H38: =IF($G38=H$1,$D38,"") | I38: =IF($G39=I$1,$D39,"") | J38: =IF($G40=J$1,$D40,"") | K38: =IF($G41=K$1,$D41,"") | L38: =IF($G42=L$1,$D42,"") | M38: =IF($G43=M$1,$D43,"") | N38: =IF($G44=N$1,$D44,"") | O38: =IF($G45=O$1,$D45,"") | P38: =IF($G46=P$1,$D46,"") | Q38: =IF($G47=Q$1,$D47,"") | R38: =IF($G48=R$1,$D48,"") | S38: =IF($G49=S$1,$D49,"") | T38: =IF($G50=T$1,$D50,"") | U38: =IF($G51=U$1,$D51,"") | V38: =IF($G52=V$1,$D52,"") | W38: =CONCATENATE(H38," ",I38," ",J38," ",K38," ",L38," ",M38," ",N38," ",O38," ",P38," ",Q38," ",R38," ",S38," ",T38," ",U38," ",V38)
A39: =C39=D39 -> FALSE | B39: =B38+1 -> 38 | C39: Project Management Fundamental Terms | D39: Project Management Institute (PMI) | E39: =LEN(D39) -> 34 | F39: 1 | G39: =IF(F39=1,1,G38+1) -> 1 | H39: =IF($G39=H$1,$D39,"") -> Project Management Institute (PMI) | I39: =IF($G40=I$1,$D40,"") -> An organization of project management professionals from around the world, supporting and promoting the careers, values, and concerns of project managers. | J39: =IF($G41=J$1,$D41,"") | K39: =IF($G42=K$1,$D42,"") | L39: =IF($G43=L$1,$D43,"") | M39: =IF($G44=M$1,$D44,"") | N39: =IF($G45=N$1,$D45,"") | O39: =IF($G46=O$1,$D46,"") | P39: =IF($G47=P$1,$D47,"") | Q39: =IF($G48=Q$1,$D48,"") | R39: =IF($G49=R$1,$D49,"") | S39: =IF($G50=S$1,$D50,"") | T39: =IF($G51=T$1,$D51,"") | U39: =IF($G52=U$1,$D52,"") | V39: =IF($G53=V$1,$D53,"") | W39: =CONCATENATE(H39," ",I39," ",J39," ",K39," ",L39," ",M39," ",N39," ",O39," ",P39," ",Q39," ",R39," ",S39," ",T39," ",U39," ",V39) -> Project Management Institute (PMI) An organization of project management professionals from around the world, supporting and promoting the careers, values, and concerns of project managers.
A40: =C40=D40 -> FALSE | B40: =B39+1 -> 39 | C40: Project Management Fundamental Terms | D40: An organization of project management professionals from around the world, supporting and promoting the careers, values, and concerns of project managers. | E40: =LEN(D40) -> 154 | G40: =IF(F40=1,1,G39+1) -> 2 | H40: =IF($G40=H$1,$D40,"") | I40: =IF($G41=I$1,$D41,"") | J40: =IF($G42=J$1,$D42,"") | K40: =IF($G43=K$1,$D43,"") | L40: =IF($G44=L$1,$D44,"") | M40: =IF($G45=M$1,$D45,"") | N40: =IF($G46=N$1,$D46,"") | O40: =IF($G47=O$1,$D47,"") | P40: =IF($G48=P$1,$D48,"") | Q40: =IF($G49=Q$1,$D49,"") | R40: =IF($G50=R$1,$D50,"") | S40: =IF($G51=S$1,$D51,"") | T40: =IF($G52=T$1,$D52,"") | U40: =IF($G53=U$1,$D53,"") | V40: =IF($G54=V$1,$D54,"") | W40: =CONCATENATE(H40," ",I40," ",J40," ",K40," ",L40," ",M40," ",N40," ",O40," ",P40," ",Q40," ",R40," ",S40," ",T40," ",U40," ",V40)
A41: =C41=D41 -> FALSE | B41: =B40+1 -> 40 | C41: Project Management Fundamental Terms | D41: Project life cycle | E41: =LEN(D41) -> 18 | F41: 1 | G41: =IF(F41=1,1,G40+1) -> 1 | H41: =IF($G41=H$1,$D41,"") -> Project life cycle | I41: =IF($G42=I$1,$D42,"") -> The phases that make up the project. Project life cycles are unique to the type of work being performed and are not universal to all projects. | J41: =IF($G43=J$1,$D43,"") | K41: =IF($G44=K$1,$D44,"") | L41: =IF($G45=L$1,$D45,"") | M41: =IF($G46=M$1,$D46,"") | N41: =IF($G47=N$1,$D47,"") | O41: =IF($G48=O$1,$D48,"") | P41: =IF($G49=P$1,$D49,"") | Q41: =IF($G50=Q$1,$D50,"") | R41: =IF($G51=R$1,$D51,"") | S41: =IF($G52=S$1,$D52,"") | T41: =IF($G53=T$1,$D53,"") | U41: =IF($G54=U$1,$D54,"") | V41: =IF($G55=V$1,$D55,"") | W41: =CONCATENATE(H41," ",I41," ",J41," ",K41," ",L41," ",M41," ",N41," ",O41," ",P41," ",Q41," ",R41," ",S41," ",T41," ",U41," ",V41) -> Project life cycle The phases that make up the project. Project life cycles are unique to the type of work being performed and are not universal to all projects.
A42: =C42=D42 -> FALSE | B42: =B41+1 -> 41 | C42: Project Management Fundamental Terms | D42: The phases that make up the project. Project life cycles are unique to the type of work being performed and are not universal to all projects. | E42: =LEN(D42) -> 142 | G42: =IF(F42=1,1,G41+1) -> 2 | H42: =IF($G42=H$1,$D42,"") | I42: =IF($G43=I$1,$D43,"") | J42: =IF($G44=J$1,$D44,"") | K42: =IF($G45=K$1,$D45,"") | L42: =IF($G46=L$1,$D46,"") | M42: =IF($G47=M$1,$D47,"") | N42: =IF($G48=N$1,$D48,"") | O42: =IF($G49=O$1,$D49,"") | P42: =IF($G50=P$1,$D50,"") | Q42: =IF($G51=Q$1,$D51,"") | R42: =IF($G52=R$1,$D52,"") | S42: =IF($G53=S$1,$D53,"") | T42: =IF($G54=T$1,$D54,"") | U42: =IF($G55=U$1,$D55,"") | V42: =IF($G56=V$1,$D56,"") | W42: =CONCATENATE(H42," ",I42," ",J42," ",K42," ",L42," ",M42," ",N42," ",O42," ",P42," ",Q42," ",R42," ",S42," ",T42," ",U42," ",V42)
A43: =C43=D43 -> FALSE | B43: =B42+1 -> 42 | C43: Project Management Fundamental Terms | D43: Project management office (PMO) | E43: =LEN(D43) -> 31 | F43: 1 | G43: =IF(F43=1,1,G42+1) -> 1 | H43: =IF($G43=H$1,$D43,"") -> Project management office (PMO) | I43: =IF($G44=I$1,$D44,"") -> A central office that oversees all projects within an organization or within a functional department. A PMO supports the project manager through software, training, templates, policies, communication, dispute resolution, and other services. | J43: =IF($G45=J$1,$D45,"") | K43: =IF($G46=K$1,$D46,"") | L43: =IF($G47=L$1,$D47,"") | M43: =IF($G48=M$1,$D48,"") | N43: =IF($G49=N$1,$D49,"") | O43: =IF($G50=O$1,$D50,"") | P43: =IF($G51=P$1,$D51,"") | Q43: =IF($G52=Q$1,$D52,"") | R43: =IF($G53=R$1,$D53,"") | S43: =IF($G54=S$1,$D54,"") | T43: =IF($G55=T$1,$D55,"") | U43: =IF($G56=U$1,$D56,"") | V43: =IF($G57=V$1,$D57,"") | W43: =CONCATENATE(H43," ",I43," ",J43," ",K43," ",L43," ",M43," ",N43," ",O43," ",P43," ",Q43," ",R43," ",S43," ",T43," ",U43," ",V43) -> Project management office (PMO) A central office that oversees all projects within an organization or within a functional department. A PMO supports the project manager through software, training, templates, policies, communication, dispute resolution, and other services.
A44: =C44=D44 -> FALSE | B44: =B43+1 -> 43 | C44: Project Management Fundamental Terms | D44: A central office that oversees all projects within an organization or within a functional department. A PMO supports the project manager through software, training, templates, policies, communication, dispute resolution, and other services. | E44: =LEN(D44) -> 240 | G44: =IF(F44=1,1,G43+1) -> 2 | H44: =IF($G44=H$1,$D44,"") | I44: =IF($G45=I$1,$D45,"") | J44: =IF($G46=J$1,$D46,"") | K44: =IF($G47=K$1,$D47,"") | L44: =IF($G48=L$1,$D48,"") | M44: =IF($G49=M$1,$D49,"") | N44: =IF($G50=N$1,$D50,"") | O44: =IF($G51=O$1,$D51,"") | P44: =IF($G52=P$1,$D52,"") | Q44: =IF($G53=Q$1,$D53,"") | R44: =IF($G54=R$1,$D54,"") | S44: =IF($G55=S$1,$D55,"") | T44: =IF($G56=T$1,$D56,"") | U44: =IF($G57=U$1,$D57,"") | V44: =IF($G58=V$1,$D58,"") | W44: =CONCATENATE(H44," ",I44," ",J44," ",K44," ",L44," ",M44," ",N44," ",O44," ",P44," ",Q44," ",R44," ",S44," ",T44," ",U44," ",V44)
A45: =C45=D45 -> FALSE | B45: =B44+1 -> 44 | C45: Project Management Fundamental Terms | D45: Project Management Professional (PMP) | E45: =LEN(D45) -> 37 | F45: 1 | G45: =IF(F45=1,1,G44+1) -> 1 | H45: =IF($G45=H$1,$D45,"") -> Project Management Professional (PMP) | I45: =IF($G46=I$1,$D46,"") -> A person who has proven project management experience and has qualified for and then passed the PMP examination. | J45: =IF($G47=J$1,$D47,"") | K45: =IF($G48=K$1,$D48,"") | L45: =IF($G49=L$1,$D49,"") | M45: =IF($G50=M$1,$D50,"") | N45: =IF($G51=N$1,$D51,"") | O45: =IF($G52=O$1,$D52,"") | P45: =IF($G53=P$1,$D53,"") | Q45: =IF($G54=Q$1,$D54,"") | R45: =IF($G55=R$1,$D55,"") | S45: =IF($G56=S$1,$D56,"") | T45: =IF($G57=T$1,$D57,"") | U45: =IF($G58=U$1,$D58,"") | V45: =IF($G59=V$1,$D59,"") | W45: =CONCATENATE(H45," ",I45," ",J45," ",K45," ",L45," ",M45," ",N45," ",O45," ",P45," ",Q45," ",R45," ",S45," ",T45," ",U45," ",V45) -> Project Management Professional (PMP) A person who has proven project management experience and has qualified for and then passed the PMP examination.
A46: =C46=D46 -> FALSE | B46: =B45+1 -> 45 | C46: Project Management Fundamental Terms | D46: A person who has proven project management experience and has qualified for and then passed the PMP examination. | E46: =LEN(D46) -> 112 | G46: =IF(F46=1,1,G45+1) -> 2 | H46: =IF($G46=H$1,$D46,"") | I46: =IF($G47=I$1,$D47,"") | J46: =IF($G48=J$1,$D48,"") | K46: =IF($G49=K$1,$D49,"") | L46: =IF($G50=L$1,$D50,"") | M46: =IF($G51=M$1,$D51,"") | N46: =IF($G52=N$1,$D52,"") | O46: =IF($G53=O$1,$D53,"") | P46: =IF($G54=P$1,$D54,"") | Q46: =IF($G55=Q$1,$D55,"") | R46: =IF($G56=R$1,$D56,"") | S46: =IF($G57=S$1,$D57,"") | T46: =IF($G58=T$1,$D58,"") | U46: =IF($G59=U$1,$D59,"") | V46: =IF($G60=V$1,$D60,"") | W46: =CONCATENATE(H46," ",I46," ",J46," ",K46," ",L46," ",M46," ",N46," ",O46," ",P46," ",Q46," ",R46," ",S46," ",T46," ",U46," ",V46)
A47: =C47=D47 -> FALSE | B47: =B46+1 -> 46 | C47: Project Management Fundamental Terms | D47: Project portfolio management | E47: =LEN(D47) -> 28 | F47: 1 | G47: =IF(F47=1,1,G46+1) -> 1 | H47: =IF($G47=H$1,$D47,"") -> Project portfolio management | I47: =IF($G48=I$1,$D48,"") -> The management and selection of projects that support an organization’s vision and mission. It is the balance of project priority, risk, reward, and return on investment. This is a senior management process. | J47: =IF($G49=J$1,$D49,"") | K47: =IF($G50=K$1,$D50,"") | L47: =IF($G51=L$1,$D51,"") | M47: =IF($G52=M$1,$D52,"") | N47: =IF($G53=N$1,$D53,"") | O47: =IF($G54=O$1,$D54,"") | P47: =IF($G55=P$1,$D55,"") | Q47: =IF($G56=Q$1,$D56,"") | R47: =IF($G57=R$1,$D57,"") | S47: =IF($G58=S$1,$D58,"") | T47: =IF($G59=T$1,$D59,"") | U47: =IF($G60=U$1,$D60,"") | V47: =IF($G61=V$1,$D61,"") | W47: =CONCATENATE(H47," ",I47," ",J47," ",K47," ",L47," ",M47," ",N47," ",O47," ",P47," ",Q47," ",R47," ",S47," ",T47," ",U47," ",V47) -> Project portfolio management The management and selection of projects that support an organization’s vision and mission. It is the balance of project priority, risk, reward, and return on investment. This is a senior management process.
A48: =C48=D48 -> FALSE | B48: =B47+1 -> 47 | C48: Project Management Fundamental Terms | D48: The management and selection of projects that support an organization’s vision and mission. It is the balance of project priority, risk, reward, and return on investment. This is a senior management process. | E48: =LEN(D48) -> 207 | G48: =IF(F48=1,1,G47+1) -> 2 | H48: =IF($G48=H$1,$D48,"") | I48: =IF($G49=I$1,$D49,"") | J48: =IF($G50=J$1,$D50,"") | K48: =IF($G51=K$1,$D51,"") | L48: =IF($G52=L$1,$D52,"") | M48: =IF($G53=M$1,$D53,"") | N48: =IF($G54=N$1,$D54,"") | O48: =IF($G55=O$1,$D55,"") | P48: =IF($G56=P$1,$D56,"") | Q48: =IF($G57=Q$1,$D57,"") | R48: =IF($G58=R$1,$D58,"") | S48: =IF($G59=S$1,$D59,"") | T48: =IF($G60=T$1,$D60,"") | U48: =IF($G61=U$1,$D61,"") | V48: =IF($G62=V$1,$D62,"") | W48: =CONCATENATE(H48," ",I48," ",J48," ",K48," ",L48," ",M48," ",N48," ",O48," ",P48," ",Q48," ",R48," ",S48," ",T48," ",U48," ",V48)
A49: =C49=D49 -> FALSE | B49: =B48+1 -> 48 | C49: Project Management Fundamental Terms | D49: Subprojects | E49: =LEN(D49) -> 11 | F49: 1 | G49: =IF(F49=1,1,G48+1) -> 1 | H49: =IF($G49=H$1,$D49,"") -> Subprojects | I49: =IF($G50=I$1,$D50,"") -> A smaller project managed within a larger, parent project. Subprojects are often contracted work whose deliverable allows the larger project to progress. | J49: =IF($G51=J$1,$D51,"") -> Triple Constraints of Project Management | K49: =IF($G52=K$1,$D52,"") -> Also known as the Iron Triangle. This theory posits that time, cost, and scope are three constraints that every project has. | L49: =IF($G53=L$1,$D53,"") | M49: =IF($G54=M$1,$D54,"") | N49: =IF($G55=N$1,$D55,"") | O49: =IF($G56=O$1,$D56,"") | P49: =IF($G57=P$1,$D57,"") | Q49: =IF($G58=Q$1,$D58,"") | R49: =IF($G59=R$1,$D59,"") | S49: =IF($G60=S$1,$D60,"") | T49: =IF($G61=T$1,$D61,"") | U49: =IF($G62=U$1,$D62,"") | V49: =IF($G63=V$1,$D63,"") | W49: =CONCATENATE(H49," ",I49," ",J49," ",K49," ",L49," ",M49," ",N49," ",O49," ",P49," ",Q49," ",R49," ",S49," ",T49," ",U49," ",V49) -> Subprojects A smaller project managed within a larger, parent project. Subprojects are often contracted work whose deliverable allows the larger project to progress. Triple Constraints of Project Management Also known as the Iron Triangle. This theory posits that time, cost, and scope are three constraints that every project has.
A50: =C50=D50 -> FALSE | B50: =B49+1 -> 49 | C50: Project Management Fundamental Terms | D50: A smaller project managed within a larger, parent project. Subprojects are often contracted work whose deliverable allows the larger project to progress. | E50: =LEN(D50) -> 153 | G50: =IF(F50=1,1,G49+1) -> 2 | H50: =IF($G50=H$1,$D50,"") | I50: =IF($G51=I$1,$D51,"") | J50: =IF($G52=J$1,$D52,"") | K50: =IF($G53=K$1,$D53,"") | L50: =IF($G54=L$1,$D54,"") | M50: =IF($G55=M$1,$D55,"") | N50: =IF($G56=N$1,$D56,"") | O50: =IF($G57=O$1,$D57,"") | P50: =IF($G58=P$1,$D58,"") | Q50: =IF($G59=Q$1,$D59,"") | R50: =IF($G60=R$1,$D60,"") | S50: =IF($G61=S$1,$D61,"") | T50: =IF($G62=T$1,$D62,"") | U50: =IF($G63=U$1,$D63,"") | V50: =IF($G64=V$1,$D64,"") | W50: =CONCATENATE(H50," ",I50," ",J50," ",K50," ",L50," ",M50," ",N50," ",O50," ",P50," ",Q50," ",R50," ",S50," ",T50," ",U50," ",V50)
A51: =C51=D51 -> FALSE | B51: =B50+1 -> 50 | C51: Project Management Fundamental Terms | D51: Triple Constraints of Project Management | E51: =LEN(D51) -> 40 | G51: =IF(F51=1,1,G50+1) -> 3 | H51: =IF($G51=H$1,$D51,"") | I51: =IF($G52=I$1,$D52,"") | J51: =IF($G53=J$1,$D53,"") | K51: =IF($G54=K$1,$D54,"") | L51: =IF($G55=L$1,$D55,"") | M51: =IF($G56=M$1,$D56,"") | N51: =IF($G57=N$1,$D57,"") | O51: =IF($G58=O$1,$D58,"") | P51: =IF($G59=P$1,$D59,"") | Q51: =IF($G60=Q$1,$D60,"") | R51: =IF($G61=R$1,$D61,"") | S51: =IF($G62=S$1,$D62,"") | T51: =IF($G63=T$1,$D63,"") | U51: =IF($G64=U$1,$D64,"") | V51: =IF($G65=V$1,$D65,"") | W51: =CONCATENATE(H51," ",I51," ",J51," ",K51," ",L51," ",M51," ",N51," ",O51," ",P51," ",Q51," ",R51," ",S51," ",T51," ",U51," ",V51)
A52: =C52=D52 -> FALSE | B52: =B51+1 -> 51 | C52: Project Management Fundamental Terms | D52: Also known as the Iron Triangle. This theory posits that time, cost, and scope are three constraints that every project has. | E52: =LEN(D52) -> 124 | G52: =IF(F52=1,1,G51+1) -> 4 | H52: =IF($G52=H$1,$D52,"") | I52: =IF($G53=I$1,$D53,"") | J52: =IF($G54=J$1,$D54,"") | K52: =IF($G55=K$1,$D55,"") | L52: =IF($G56=L$1,$D56,"") | M52: =IF($G57=M$1,$D57,"") | N52: =IF($G58=N$1,$D58,"") | O52: =IF($G59=O$1,$D59,"") | P52: =IF($G60=P$1,$D60,"") | Q52: =IF($G61=Q$1,$D61,"") | R52: =IF($G62=R$1,$D62,"") | S52: =IF($G63=S$1,$D63,"") | T52: =IF($G64=T$1,$D64,"") | U52: =IF($G65=U$1,$D65,"") | V52: =IF($G66=V$1,$D66,"") | W52: =CONCATENATE(H52," ",I52," ",J52," ",K52," ",L52," ",M52," ",N52," ",O52," ",P52," ",Q52," ",R52," ",S52," ",T52," ",U52," ",V52)
A53: =C53=D53 -> FALSE | B53: =B52+1 -> 52 | C53: Project Management Fundamental Terms | D53: Work performance data | E53: =LEN(D53) -> 21 | F53: 1 | G53: =IF(F53=1,1,G52+1) -> 1 | H53: =IF($G53=H$1,$D53,"") -> Work performance data | I53: =IF($G54=I$1,$D54,"") -> Raw data, observations, and measurements about project components. Work performance data is gathered and stored in the project management information system. | J53: =IF($G55=J$1,$D55,"") | K53: =IF($G56=K$1,$D56,"") | L53: =IF($G57=L$1,$D57,"") | M53: =IF($G58=M$1,$D58,"") | N53: =IF($G59=N$1,$D59,"") | O53: =IF($G60=O$1,$D60,"") | P53: =IF($G61=P$1,$D61,"") | Q53: =IF($G62=Q$1,$D62,"") | R53: =IF($G63=R$1,$D63,"") | S53: =IF($G64=S$1,$D64,"") | T53: =IF($G65=T$1,$D65,"") | U53: =IF($G66=U$1,$D66,"") | V53: =IF($G67=V$1,$D67,"") | W53: =CONCATENATE(H53," ",I53," ",J53," ",K53," ",L53," ",M53," ",N53," ",O53," ",P53," ",Q53," ",R53," ",S53," ",T53," ",U53," ",V53) -> Work performance data Raw data, observations, and measurements about project components. Work performance data is gathered and stored in the project management information system.
A54: =C54=D54 -> FALSE | B54: =B53+1 -> 53 | C54: Project Management Fundamental Terms | D54: Raw data, observations, and measurements about project components. Work performance data is gathered and stored in the project management information system. | E54: =LEN(D54) -> 157 | G54: =IF(F54=1,1,G53+1) -> 2 | H54: =IF($G54=H$1,$D54,"") | I54: =IF($G55=I$1,$D55,"") | J54: =IF($G56=J$1,$D56,"") | K54: =IF($G57=K$1,$D57,"") | L54: =IF($G58=L$1,$D58,"") | M54: =IF($G59=M$1,$D59,"") | N54: =IF($G60=N$1,$D60,"") | O54: =IF($G61=O$1,$D61,"") | P54: =IF($G62=P$1,$D62,"") | Q54: =IF($G63=Q$1,$D63,"") | R54: =IF($G64=R$1,$D64,"") | S54: =IF($G65=S$1,$D65,"") | T54: =IF($G66=T$1,$D66,"") | U54: =IF($G67=U$1,$D67,"") | V54: =IF($G68=V$1,$D68,"") | W54: =CONCATENATE(H54," ",I54," ",J54," ",K54," ",L54," ",M54," ",N54," ",O54," ",P54," ",Q54," ",R54," ",S54," ",T54," ",U54," ",V54)
A55: =C55=D55 -> FALSE | B55: =B54+1 -> 54 | C55: Project Management Fundamental Terms | D55: Work performance information | E55: =LEN(D55) -> 28 | F55: 1 | G55: =IF(F55=1,1,G54+1) -> 1 | H55: =IF($G55=H$1,$D55,"") -> Work performance information | I55: =IF($G56=I$1,$D56,"") -> Work performance information is the processed and analyzed data that will help the project manager make project decisions. | J55: =IF($G57=J$1,$D57,"") | K55: =IF($G58=K$1,$D58,"") | L55: =IF($G59=L$1,$D59,"") | M55: =IF($G60=M$1,$D60,"") | N55: =IF($G61=N$1,$D61,"") | O55: =IF($G62=O$1,$D62,"") | P55: =IF($G63=P$1,$D63,"") | Q55: =IF($G64=Q$1,$D64,"") | R55: =IF($G65=R$1,$D65,"") | S55: =IF($G66=S$1,$D66,"") | T55: =IF($G67=T$1,$D67,"") | U55: =IF($G68=U$1,$D68,"") | V55: =IF($G69=V$1,$D69,"") | W55: =CONCATENATE(H55," ",I55," ",J55," ",K55," ",L55," ",M55," ",N55," ",O55," ",P55," ",Q55," ",R55," ",S55," ",T55," ",U55," ",V55) -> Work performance information Work performance information is the processed and analyzed data that will help the project manager make project decisions.
A56: =C56=D56 -> FALSE | B56: =B55+1 -> 55 | C56: Project Management Fundamental Terms | D56: Work performance information is the processed and analyzed data that will help the project manager make project decisions. | E56: =LEN(D56) -> 122 | G56: =IF(F56=1,1,G55+1) -> 2 | H56: =IF($G56=H$1,$D56,"") | I56: =IF($G57=I$1,$D57,"") | J56: =IF($G58=J$1,$D58,"") | K56: =IF($G59=K$1,$D59,"") | L56: =IF($G60=L$1,$D60,"") | M56: =IF($G61=M$1,$D61,"") | N56: =IF($G62=N$1,$D62,"") | O56: =IF($G63=O$1,$D63,"") | P56: =IF($G64=P$1,$D64,"") | Q56: =IF($G65=Q$1,$D65,"") | R56: =IF($G66=R$1,$D66,"") | S56: =IF($G67=S$1,$D67,"") | T56: =IF($G68=T$1,$D68,"") | U56: =IF($G69=U$1,$D69,"") | V56: =IF($G70=V$1,$D70,"") | W56: =CONCATENATE(H56," ",I56," ",J56," ",K56," ",L56," ",M56," ",N56," ",O56," ",P56," ",Q56," ",R56," ",S56," ",T56," ",U56," ",V56)
A57: =C57=D57 -> FALSE | B57: =B56+1 -> 56 | C57: Project Management Fundamental Terms | D57: Work performance reports | E57: =LEN(D57) -> 24 | F57: 1 | G57: =IF(F57=1,1,G56+1) -> 1 | H57: =IF($G57=H$1,$D57,"") -> Work performance reports | I57: =IF($G58=I$1,$D58,"") -> Work performance reports is the formatted communication of work performance information. Work performance reports communicate what’s happening in the project through status reports, memos, dashboards, or other modalities. | J57: =IF($G59=J$1,$D59,"") -> Hybrid structure An organization that creates a blend of the functional, matrix, and project-oriented structures. Multidivisional structure Describe organizations that have duplication of efforts within the organization, but not within each department or division of the organization. Project manager has little authority in this structure and the functional manager controls the project budget. Organic or simple Describes a loosely organized business or organization. There likely aren’t big formal departments and people work alongside one another regardless of roles and titles. The project manager likely has little control over the project resources and may not be called a project manager. Organizational process assets Organizational process assets include organizational processes, policies, procedures, and items from a corporate knowledge base. Organizational process assets are grouped into two categories to consider: processes, policies and procedures, and organizational knowledge bases. Organizational Knowledge Repositories Organizational knowledge repositories are the databases, files, and historical information that you can use to help better plan and manage your projects. This is an organizational process asset that is created internally to your organization through the ongoing work of operations and other projects. | K57: =IF($G60=K$1,$D60,"") -> Organizational System A system can create things by working with multiple components that the individual components could not create if they worked alone. The structure of the organization and the governance framework creates constraints that affect how the project manager makes decisions within the project. The organizational system directly affects how the project manager utilizes their power, influence, leadership, and even political capital, to get things done in the environment. Project management office (PMO) A business unit that centralizes the operations and procedures of all projects within the organization. The PMO can be supportive, controlling, or directive. Project-oriented structure An organization that assigns a project team to one project for the duration of the project life cycle. The project manager has high-to-almost-complete project power. Strong matrix structure An organization where organizational resources are pooled into one project team, but the functional managers have less project power than the project manager. Virtual organization Uses a network structure to communicate and interact with other groups and departments. A point of contact exists for each department and these department point of contact receive and send all messages for the department. Weak matrix structure An organization where organizational resources are pooled into one project team, but the functional managers have more project power than the project manager. | L57: =IF($G61=L$1,$D61,"") | M57: =IF($G62=M$1,$D62,"") | N57: =IF($G63=N$1,$D63,"") | O57: =IF($G64=O$1,$D64,"") | P57: =IF($G65=P$1,$D65,"") | Q57: =IF($G66=Q$1,$D66,"") | R57: =IF($G67=R$1,$D67,"") | S57: =IF($G68=S$1,$D68,"") | T57: =IF($G69=T$1,$D69,"") | U57: =IF($G70=U$1,$D70,"") | V57: =IF($G71=V$1,$D71,"") | W57: =CONCATENATE(H57," ",I57," ",J57," ",K57," ",L57," ",M57," ",N57," ",O57," ",P57," ",Q57," ",R57," ",S57," ",T57," ",U57," ",V57) -> Work performance reports Work performance reports is the formatted communication of work performance information. Work performance reports communicate what’s happening in the project through status reports, memos, dashboards, or other modalities. Hybrid structure An organization that creates a blend of the functional, matrix, and project-oriented structures. Multidivisional structure Describe organizations that have duplication of efforts within the organization, but not within each department or division of the organization. Project manager has little authority in this structure and the functional manager controls the project budget. Organic or simple Describes a loosely organized business or organization. There likely aren’t big formal departments and people work alongside one another regardless of roles and titles. The project manager likely has little control over the project resources and may not be called a project manager. Organizational process assets Organizational process assets include organizational processes, policies, procedures, and items from a corporate knowledge base. Organizational process assets are grouped into two categories to consider: processes, policies and procedures, and organizational knowledge bases. Organizational Knowledge Repositories Organizational knowledge repositories are the databases, files, and historical information that you can use to help better plan and manage your projects. This is an organizational process asset that is created internally to your organization through the ongoing work of operations and other projects. Organizational System A system can create things by working with multiple components that the individual components could not create if they worked alone. The structure of the organization and the governance framework creates constraints that affect how the project manager makes decisions within the project. The organizational system directly affects how the project manager utilizes their power, influence, leadership, and even political capital, to get things done in the environment. Project management office (PMO) A business unit that centralizes the operations and procedures of all projects within the organization. The PMO can be supportive, controlling, or directive. Project-oriented structure An organization that assigns a project team to one project for the duration of the project life cycle. The project manager has high-to-almost-complete project power. Strong matrix structure An organization where organizational resources are pooled into one project team, but the functional managers have less project power than the project manager. Virtual organization Uses a network structure to communicate and interact with other groups and departments. A point of contact exists for each department and these department point of contact receive and send all messages for the department. Weak matrix structure An organization where organizational resources are pooled into one project team, but the functional managers have more project power than the project manager.
A58: =C58=D58 -> FALSE | B58: =B57+1 -> 57 | C58: Project Management Fundamental Terms | D58: Work performance reports is the formatted communication of work performance information. Work performance reports communicate what’s happening in the project through status reports, memos, dashboards, or other modalities. | E58: =LEN(D58) -> 221 | G58: =IF(F58=1,1,G57+1) -> 2 | H58: =IF($G58=H$1,$D58,"") | I58: =IF($G59=I$1,$D59,"") | J58: =IF($G60=J$1,$D60,"") | K58: =IF($G61=K$1,$D61,"") | L58: =IF($G62=L$1,$D62,"") | M58: =IF($G63=M$1,$D63,"") | N58: =IF($G64=N$1,$D64,"") | O58: =IF($G65=O$1,$D65,"") | P58: =IF($G66=P$1,$D66,"") | Q58: =IF($G67=Q$1,$D67,"") | R58: =IF($G68=R$1,$D68,"") | S58: =IF($G69=S$1,$D69,"") | T58: =IF($G70=T$1,$D70,"") | U58: =IF($G71=U$1,$D71,"") | V58: =IF($G72=V$1,$D72,"") | W58: =CONCATENATE(H58," ",I58," ",J58," ",K58," ",L58," ",M58," ",N58," ",O58," ",P58," ",Q58," ",R58," ",S58," ",T58," ",U58," ",V58)
A59: =C59=D59 -> FALSE | B59: =B58+1 -> 58 | C59: Project Management Fundamental Terms | D59: Hybrid structure An organization that creates a blend of the functional, matrix, and project-oriented structures. Multidivisional structure Describe organizations that have duplication of efforts within the organization, but not within each department or division of the organization. Project manager has little authority in this structure and the functional manager controls the project budget. Organic or simple Describes a loosely organized business or organization. There likely aren’t big formal departments and people work alongside one another regardless of roles and titles. The project manager likely has little control over the project resources and may not be called a project manager. Organizational process assets Organizational process assets include organizational processes, policies, procedures, and items from a corporate knowledge base. Organizational process assets are grouped into two categories to consider: processes, policies and procedures, and organizational knowledge bases. Organizational Knowledge Repositories Organizational knowledge repositories are the databases, files, and historical information that you can use to help better plan and manage your projects. This is an organizational process asset that is created internally to your organization through the ongoing work of operations and other projects. | E59: =LEN(D59) -> 1341 | G59: =IF(F59=1,1,G58+1) -> 3 | H59: =IF($G59=H$1,$D59,"") | I59: =IF($G60=I$1,$D60,"") | J59: =IF($G61=J$1,$D61,"") | K59: =IF($G62=K$1,$D62,"") | L59: =IF($G63=L$1,$D63,"") | M59: =IF($G64=M$1,$D64,"") | N59: =IF($G65=N$1,$D65,"") | O59: =IF($G66=O$1,$D66,"") | P59: =IF($G67=P$1,$D67,"") | Q59: =IF($G68=Q$1,$D68,"") | R59: =IF($G69=R$1,$D69,"") | S59: =IF($G70=S$1,$D70,"") | T59: =IF($G71=T$1,$D71,"") | U59: =IF($G72=U$1,$D72,"") | V59: =IF($G73=V$1,$D73,"") | W59: =CONCATENATE(H59," ",I59," ",J59," ",K59," ",L59," ",M59," ",N59," ",O59," ",P59," ",Q59," ",R59," ",S59," ",T59," ",U59," ",V59)
A60: =C60=D60 -> FALSE | B60: =B59+1 -> 59 | C60: Project Management Fundamental Terms | D60: Organizational System A system can create things by working with multiple components that the individual components could not create if they worked alone. The structure of the organization and the governance framework creates constraints that affect how the project manager makes decisions within the project. The organizational system directly affects how the project manager utilizes their power, influence, leadership, and even political capital, to get things done in the environment. Project management office (PMO) A business unit that centralizes the operations and procedures of all projects within the organization. The PMO can be supportive, controlling, or directive. Project-oriented structure An organization that assigns a project team to one project for the duration of the project life cycle. The project manager has high-to-almost-complete project power. Strong matrix structure An organization where organizational resources are pooled into one project team, but the functional managers have less project power than the project manager. Virtual organization Uses a network structure to communicate and interact with other groups and departments. A point of contact exists for each department and these department point of contact receive and send all messages for the department. Weak matrix structure An organization where organizational resources are pooled into one project team, but the functional managers have more project power than the project manager. | E60: =LEN(D60) -> 1478 | G60: =IF(F60=1,1,G59+1) -> 4 | H60: =IF($G60=H$1,$D60,"") | I60: =IF($G61=I$1,$D61,"") | J60: =IF($G62=J$1,$D62,"") | K60: =IF($G63=K$1,$D63,"") | L60: =IF($G64=L$1,$D64,"") | M60: =IF($G65=M$1,$D65,"") | N60: =IF($G66=N$1,$D66,"") | O60: =IF($G67=O$1,$D67,"") | P60: =IF($G68=P$1,$D68,"") | Q60: =IF($G69=Q$1,$D69,"") | R60: =IF($G70=R$1,$D70,"") | S60: =IF($G71=S$1,$D71,"") | T60: =IF($G72=T$1,$D72,"") | U60: =IF($G73=U$1,$D73,"") | V60: =IF($G74=V$1,$D74,"") | W60: =CONCATENATE(H60," ",I60," ",J60," ",K60," ",L60," ",M60," ",N60," ",O60," ",P60," ",Q60," ",R60," ",S60," ",T60," ",U60," ",V60)
A61: =C61=D61 -> FALSE | B61: =B60+1 -> 60 | C61: Project Manager Role | D61: active listening | E61: =LEN(D61) -> 16 | F61: 1 | G61: =IF(F61=1,1,G60+1) -> 1 | H61: =IF($G61=H$1,$D61,"") -> active listening | I61: =IF($G62=I$1,$D62,"") -> The message receiver restates what’s | J61: =IF($G63=J$1,$D63,"") -> been said to fully understand and confirm | K61: =IF($G64=K$1,$D64,"") -> the message and it provides an | L61: =IF($G65=L$1,$D65,"") -> opportunity for the sender to clarify the | M61: =IF($G66=M$1,$D66,"") -> message if needed. | N61: =IF($G67=N$1,$D67,"") | O61: =IF($G68=O$1,$D68,"") | P61: =IF($G69=P$1,$D69,"") | Q61: =IF($G70=Q$1,$D70,"") | R61: =IF($G71=R$1,$D71,"") | S61: =IF($G72=S$1,$D72,"") | T61: =IF($G73=T$1,$D73,"") | U61: =IF($G74=U$1,$D74,"") | V61: =IF($G75=V$1,$D75,"") | W61: =CONCATENATE(H61," ",I61," ",J61," ",K61," ",L61," ",M61," ",N61," ",O61," ",P61," ",Q61," ",R61," ",S61," ",T61," ",U61," ",V61) -> active listening The message receiver restates what’s been said to fully understand and confirm the message and it provides an opportunity for the sender to clarify the message if needed.
A62: =C62=D62 -> FALSE | B62: =B61+1 -> 61 | C62: Project Manager Role | D62: The message receiver restates what’s | E62: =LEN(D62) -> 36 | G62: =IF(F62=1,1,G61+1) -> 2 | H62: =IF($G62=H$1,$D62,"") | I62: =IF($G63=I$1,$D63,"") | J62: =IF($G64=J$1,$D64,"") | K62: =IF($G65=K$1,$D65,"") | L62: =IF($G66=L$1,$D66,"") | M62: =IF($G67=M$1,$D67,"") | N62: =IF($G68=N$1,$D68,"") | O62: =IF($G69=O$1,$D69,"") | P62: =IF($G70=P$1,$D70,"") | Q62: =IF($G71=Q$1,$D71,"") | R62: =IF($G72=R$1,$D72,"") | S62: =IF($G73=S$1,$D73,"") | T62: =IF($G74=T$1,$D74,"") | U62: =IF($G75=U$1,$D75,"") | V62: =IF($G76=V$1,$D76,"") | W62: =CONCATENATE(H62," ",I62," ",J62," ",K62," ",L62," ",M62," ",N62," ",O62," ",P62," ",Q62," ",R62," ",S62," ",T62," ",U62," ",V62)
A63: =C63=D63 -> FALSE | B63: =B62+1 -> 62 | C63: Project Manager Role | D63: been said to fully understand and confirm | E63: =LEN(D63) -> 41 | G63: =IF(F63=1,1,G62+1) -> 3 | H63: =IF($G63=H$1,$D63,"") | I63: =IF($G64=I$1,$D64,"") | J63: =IF($G65=J$1,$D65,"") | K63: =IF($G66=K$1,$D66,"") | L63: =IF($G67=L$1,$D67,"") | M63: =IF($G68=M$1,$D68,"") | N63: =IF($G69=N$1,$D69,"") | O63: =IF($G70=O$1,$D70,"") | P63: =IF($G71=P$1,$D71,"") | Q63: =IF($G72=Q$1,$D72,"") | R63: =IF($G73=R$1,$D73,"") | S63: =IF($G74=S$1,$D74,"") | T63: =IF($G75=T$1,$D75,"") | U63: =IF($G76=U$1,$D76,"") | V63: =IF($G77=V$1,$D77,"") | W63: =CONCATENATE(H63," ",I63," ",J63," ",K63," ",L63," ",M63," ",N63," ",O63," ",P63," ",Q63," ",R63," ",S63," ",T63," ",U63," ",V63)
A64: =C64=D64 -> FALSE | B64: =B63+1 -> 63 | C64: Project Manager Role | D64: the message and it provides an | E64: =LEN(D64) -> 30 | G64: =IF(F64=1,1,G63+1) -> 4 | H64: =IF($G64=H$1,$D64,"") | I64: =IF($G65=I$1,$D65,"") | J64: =IF($G66=J$1,$D66,"") | K64: =IF($G67=K$1,$D67,"") | L64: =IF($G68=L$1,$D68,"") | M64: =IF($G69=M$1,$D69,"") | N64: =IF($G70=N$1,$D70,"") | O64: =IF($G71=O$1,$D71,"") | P64: =IF($G72=P$1,$D72,"") | Q64: =IF($G73=Q$1,$D73,"") | R64: =IF($G74=R$1,$D74,"") | S64: =IF($G75=S$1,$D75,"") | T64: =IF($G76=T$1,$D76,"") | U64: =IF($G77=U$1,$D77,"") | V64: =IF($G78=V$1,$D78,"") | W64: =CONCATENATE(H64," ",I64," ",J64," ",K64," ",L64," ",M64," ",N64," ",O64," ",P64," ",Q64," ",R64," ",S64," ",T64," ",U64," ",V64)
A65: =C65=D65 -> FALSE | B65: =B64+1 -> 64 | C65: Project Manager Role | D65: opportunity for the sender to clarify the | E65: =LEN(D65) -> 41 | G65: =IF(F65=1,1,G64+1) -> 5 | H65: =IF($G65=H$1,$D65,"") | I65: =IF($G66=I$1,$D66,"") | J65: =IF($G67=J$1,$D67,"") | K65: =IF($G68=K$1,$D68,"") | L65: =IF($G69=L$1,$D69,"") | M65: =IF($G70=M$1,$D70,"") | N65: =IF($G71=N$1,$D71,"") | O65: =IF($G72=O$1,$D72,"") | P65: =IF($G73=P$1,$D73,"") | Q65: =IF($G74=Q$1,$D74,"") | R65: =IF($G75=R$1,$D75,"") | S65: =IF($G76=S$1,$D76,"") | T65: =IF($G77=T$1,$D77,"") | U65: =IF($G78=U$1,$D78,"") | V65: =IF($G79=V$1,$D79,"") | W65: =CONCATENATE(H65," ",I65," ",J65," ",K65," ",L65," ",M65," ",N65," ",O65," ",P65," ",Q65," ",R65," ",S65," ",T65," ",U65," ",V65)
A66: =C66=D66 -> FALSE | B66: =B65+1 -> 65 | C66: Project Manager Role | D66: message if needed. | E66: =LEN(D66) -> 18 | G66: =IF(F66=1,1,G65+1) -> 6 | H66: =IF($G66=H$1,$D66,"") | I66: =IF($G67=I$1,$D67,"") | J66: =IF($G68=J$1,$D68,"") | K66: =IF($G69=K$1,$D69,"") | L66: =IF($G70=L$1,$D70,"") | M66: =IF($G71=M$1,$D71,"") | N66: =IF($G72=N$1,$D72,"") | O66: =IF($G73=O$1,$D73,"") | P66: =IF($G74=P$1,$D74,"") | Q66: =IF($G75=Q$1,$D75,"") | R66: =IF($G76=R$1,$D76,"") | S66: =IF($G77=S$1,$D77,"") | T66: =IF($G78=T$1,$D78,"") | U66: =IF($G79=U$1,$D79,"") | V66: =IF($G80=V$1,$D80,"") | W66: =CONCATENATE(H66," ",I66," ",J66," ",K66," ",L66," ",M66," ",N66," ",O66," ",P66," ",Q66," ",R66," ",S66," ",T66," ",U66," ",V66)
A67: =C67=D67 -> FALSE | B67: =B66+1 -> 66 | C67: Project Manager Role | D67: active problem solving | E67: =LEN(D67) -> 22 | F67: 1 | G67: =IF(F67=1,1,G66+1) -> 1 | H67: =IF($G67=H$1,$D67,"") -> active problem solving | I67: =IF($G68=I$1,$D68,"") -> Active problem solving begins with | J67: =IF($G69=J$1,$D69,"") -> problem definition. Problem definition is | K67: =IF($G70=K$1,$D70,"") -> the ability to discern between the cause | L67: =IF($G71=L$1,$D71,"") -> and effect of the problem. Root-cause | M67: =IF($G72=M$1,$D72,"") -> analysis looks beyond the immediate | N67: =IF($G73=N$1,$D73,"") -> symptoms to the cause of the | O67: =IF($G74=O$1,$D74,"") -> symptoms—which then affords | P67: =IF($G75=P$1,$D75,"") -> opportunities for solutions. | Q67: =IF($G76=Q$1,$D76,"") | R67: =IF($G77=R$1,$D77,"") | S67: =IF($G78=S$1,$D78,"") | T67: =IF($G79=T$1,$D79,"") | U67: =IF($G80=U$1,$D80,"") | V67: =IF($G81=V$1,$D81,"") | W67: =CONCATENATE(H67," ",I67," ",J67," ",K67," ",L67," ",M67," ",N67," ",O67," ",P67," ",Q67," ",R67," ",S67," ",T67," ",U67," ",V67) -> active problem solving Active problem solving begins with problem definition. Problem definition is the ability to discern between the cause and effect of the problem. Root-cause analysis looks beyond the immediate symptoms to the cause of the symptoms—which then affords opportunities for solutions.
A68: =C68=D68 -> FALSE | B68: =B67+1 -> 67 | C68: Project Manager Role | D68: Active problem solving begins with | E68: =LEN(D68) -> 34 | G68: =IF(F68=1,1,G67+1) -> 2 | H68: =IF($G68=H$1,$D68,"") | I68: =IF($G69=I$1,$D69,"") | J68: =IF($G70=J$1,$D70,"") | K68: =IF($G71=K$1,$D71,"") | L68: =IF($G72=L$1,$D72,"") | M68: =IF($G73=M$1,$D73,"") | N68: =IF($G74=N$1,$D74,"") | O68: =IF($G75=O$1,$D75,"") | P68: =IF($G76=P$1,$D76,"") | Q68: =IF($G77=Q$1,$D77,"") | R68: =IF($G78=R$1,$D78,"") | S68: =IF($G79=S$1,$D79,"") | T68: =IF($G80=T$1,$D80,"") | U68: =IF($G81=U$1,$D81,"") | V68: =IF($G82=V$1,$D82,"") | W68: =CONCATENATE(H68," ",I68," ",J68," ",K68," ",L68," ",M68," ",N68," ",O68," ",P68," ",Q68," ",R68," ",S68," ",T68," ",U68," ",V68)
A69: =C69=D69 -> FALSE | B69: =B68+1 -> 68 | C69: Project Manager Role | D69: problem definition. Problem definition is | E69: =LEN(D69) -> 41 | G69: =IF(F69=1,1,G68+1) -> 3 | H69: =IF($G69=H$1,$D69,"") | I69: =IF($G70=I$1,$D70,"") | J69: =IF($G71=J$1,$D71,"") | K69: =IF($G72=K$1,$D72,"") | L69: =IF($G73=L$1,$D73,"") | M69: =IF($G74=M$1,$D74,"") | N69: =IF($G75=N$1,$D75,"") | O69: =IF($G76=O$1,$D76,"") | P69: =IF($G77=P$1,$D77,"") | Q69: =IF($G78=Q$1,$D78,"") | R69: =IF($G79=R$1,$D79,"") | S69: =IF($G80=S$1,$D80,"") | T69: =IF($G81=T$1,$D81,"") | U69: =IF($G82=U$1,$D82,"") | V69: =IF($G83=V$1,$D83,"") | W69: =CONCATENATE(H69," ",I69," ",J69," ",K69," ",L69," ",M69," ",N69," ",O69," ",P69," ",Q69," ",R69," ",S69," ",T69," ",U69," ",V69)
A70: =C70=D70 -> FALSE | B70: =B69+1 -> 69 | C70: Project Manager Role | D70: the ability to discern between the cause | E70: =LEN(D70) -> 40 | G70: =IF(F70=1,1,G69+1) -> 4 | H70: =IF($G70=H$1,$D70,"") | I70: =IF($G71=I$1,$D71,"") | J70: =IF($G72=J$1,$D72,"") | K70: =IF($G73=K$1,$D73,"") | L70: =IF($G74=L$1,$D74,"") | M70: =IF($G75=M$1,$D75,"") | N70: =IF($G76=N$1,$D76,"") | O70: =IF($G77=O$1,$D77,"") | P70: =IF($G78=P$1,$D78,"") | Q70: =IF($G79=Q$1,$D79,"") | R70: =IF($G80=R$1,$D80,"") | S70: =IF($G81=S$1,$D81,"") | T70: =IF($G82=T$1,$D82,"") | U70: =IF($G83=U$1,$D83,"") | V70: =IF($G84=V$1,$D84,"") | W70: =CONCATENATE(H70," ",I70," ",J70," ",K70," ",L70," ",M70," ",N70," ",O70," ",P70," ",Q70," ",R70," ",S70," ",T70," ",U70," ",V70)
A71: =C71=D71 -> FALSE | B71: =B70+1 -> 70 | C71: Project Manager Role | D71: and effect of the problem. Root-cause | E71: =LEN(D71) -> 37 | G71: =IF(F71=1,1,G70+1) -> 5 | H71: =IF($G71=H$1,$D71,"") | I71: =IF($G72=I$1,$D72,"") | J71: =IF($G73=J$1,$D73,"") | K71: =IF($G74=K$1,$D74,"") | L71: =IF($G75=L$1,$D75,"") | M71: =IF($G76=M$1,$D76,"") | N71: =IF($G77=N$1,$D77,"") | O71: =IF($G78=O$1,$D78,"") | P71: =IF($G79=P$1,$D79,"") | Q71: =IF($G80=Q$1,$D80,"") | R71: =IF($G81=R$1,$D81,"") | S71: =IF($G82=S$1,$D82,"") | T71: =IF($G83=T$1,$D83,"") | U71: =IF($G84=U$1,$D84,"") | V71: =IF($G85=V$1,$D85,"") | W71: =CONCATENATE(H71," ",I71," ",J71," ",K71," ",L71," ",M71," ",N71," ",O71," ",P71," ",Q71," ",R71," ",S71," ",T71," ",U71," ",V71)
A72: =C72=D72 -> FALSE | B72: =B71+1 -> 71 | C72: Project Manager Role | D72: analysis looks beyond the immediate | E72: =LEN(D72) -> 35 | G72: =IF(F72=1,1,G71+1) -> 6 | H72: =IF($G72=H$1,$D72,"") | I72: =IF($G73=I$1,$D73,"") | J72: =IF($G74=J$1,$D74,"") | K72: =IF($G75=K$1,$D75,"") | L72: =IF($G76=L$1,$D76,"") | M72: =IF($G77=M$1,$D77,"") | N72: =IF($G78=N$1,$D78,"") | O72: =IF($G79=O$1,$D79,"") | P72: =IF($G80=P$1,$D80,"") | Q72: =IF($G81=Q$1,$D81,"") | R72: =IF($G82=R$1,$D82,"") | S72: =IF($G83=S$1,$D83,"") | T72: =IF($G84=T$1,$D84,"") | U72: =IF($G85=U$1,$D85,"") | V72: =IF($G86=V$1,$D86,"") | W72: =CONCATENATE(H72," ",I72," ",J72," ",K72," ",L72," ",M72," ",N72," ",O72," ",P72," ",Q72," ",R72," ",S72," ",T72," ",U72," ",V72)
A73: =C73=D73 -> FALSE | B73: =B72+1 -> 72 | C73: Project Manager Role | D73: symptoms to the cause of the | E73: =LEN(D73) -> 28 | G73: =IF(F73=1,1,G72+1) -> 7 | H73: =IF($G73=H$1,$D73,"") | I73: =IF($G74=I$1,$D74,"") | J73: =IF($G75=J$1,$D75,"") | K73: =IF($G76=K$1,$D76,"") | L73: =IF($G77=L$1,$D77,"") | M73: =IF($G78=M$1,$D78,"") | N73: =IF($G79=N$1,$D79,"") | O73: =IF($G80=O$1,$D80,"") | P73: =IF($G81=P$1,$D81,"") | Q73: =IF($G82=Q$1,$D82,"") | R73: =IF($G83=R$1,$D83,"") | S73: =IF($G84=S$1,$D84,"") | T73: =IF($G85=T$1,$D85,"") | U73: =IF($G86=U$1,$D86,"") | V73: =IF($G87=V$1,$D87,"") | W73: =CONCATENATE(H73," ",I73," ",J73," ",K73," ",L73," ",M73," ",N73," ",O73," ",P73," ",Q73," ",R73," ",S73," ",T73," ",U73," ",V73)
A74: =C74=D74 -> FALSE | B74: =B73+1 -> 73 | C74: Project Manager Role | D74: symptoms—which then affords | E74: =LEN(D74) -> 27 | G74: =IF(F74=1,1,G73+1) -> 8 | H74: =IF($G74=H$1,$D74,"") | I74: =IF($G75=I$1,$D75,"") | J74: =IF($G76=J$1,$D76,"") | K74: =IF($G77=K$1,$D77,"") | L74: =IF($G78=L$1,$D78,"") | M74: =IF($G79=M$1,$D79,"") | N74: =IF($G80=N$1,$D80,"") | O74: =IF($G81=O$1,$D81,"") | P74: =IF($G82=P$1,$D82,"") | Q74: =IF($G83=Q$1,$D83,"") | R74: =IF($G84=R$1,$D84,"") | S74: =IF($G85=S$1,$D85,"") | T74: =IF($G86=T$1,$D86,"") | U74: =IF($G87=U$1,$D87,"") | V74: =IF($G88=V$1,$D88,"") | W74: =CONCATENATE(H74," ",I74," ",J74," ",K74," ",L74," ",M74," ",N74," ",O74," ",P74," ",Q74," ",R74," ",S74," ",T74," ",U74," ",V74)
A75: =C75=D75 -> FALSE | B75: =B74+1 -> 74 | C75: Project Manager Role | D75: opportunities for solutions. | E75: =LEN(D75) -> 28 | G75: =IF(F75=1,1,G74+1) -> 9 | H75: =IF($G75=H$1,$D75,"") | I75: =IF($G76=I$1,$D76,"") | J75: =IF($G77=J$1,$D77,"") | K75: =IF($G78=K$1,$D78,"") | L75: =IF($G79=L$1,$D79,"") | M75: =IF($G80=M$1,$D80,"") | N75: =IF($G81=N$1,$D81,"") | O75: =IF($G82=O$1,$D82,"") | P75: =IF($G83=P$1,$D83,"") | Q75: =IF($G84=Q$1,$D84,"") | R75: =IF($G85=R$1,$D85,"") | S75: =IF($G86=S$1,$D86,"") | T75: =IF($G87=T$1,$D87,"") | U75: =IF($G88=U$1,$D88,"") | V75: =IF($G89=V$1,$D89,"") | W75: =CONCATENATE(H75," ",I75," ",J75," ",K75," ",L75," ",M75," ",N75," ",O75," ",P75," ",Q75," ",R75," ",S75," ",T75," ",U75," ",V75)
A76: =C76=D76 -> FALSE | B76: =B75+1 -> 75 | C76: Project Manager Role | D76: avoiding power | E76: =LEN(D76) -> 14 | F76: 1 | G76: =IF(F76=1,1,G75+1) -> 1 | H76: =IF($G76=H$1,$D76,"") -> avoiding power | I76: =IF($G77=I$1,$D77,"") -> The project manager refuses to act, get | J76: =IF($G78=J$1,$D78,"") -> involved, or make decisions. | K76: =IF($G79=K$1,$D79,"") | L76: =IF($G80=L$1,$D80,"") | M76: =IF($G81=M$1,$D81,"") | N76: =IF($G82=N$1,$D82,"") | O76: =IF($G83=O$1,$D83,"") | P76: =IF($G84=P$1,$D84,"") | Q76: =IF($G85=Q$1,$D85,"") | R76: =IF($G86=R$1,$D86,"") | S76: =IF($G87=S$1,$D87,"") | T76: =IF($G88=T$1,$D88,"") | U76: =IF($G89=U$1,$D89,"") | V76: =IF($G90=V$1,$D90,"") | W76: =CONCATENATE(H76," ",I76," ",J76," ",K76," ",L76," ",M76," ",N76," ",O76," ",P76," ",Q76," ",R76," ",S76," ",T76," ",U76," ",V76) -> avoiding power The project manager refuses to act, get involved, or make decisions.
A77: =C77=D77 -> FALSE | B77: =B76+1 -> 76 | C77: Project Manager Role | D77: The project manager refuses to act, get | E77: =LEN(D77) -> 39 | G77: =IF(F77=1,1,G76+1) -> 2 | H77: =IF($G77=H$1,$D77,"") | I77: =IF($G78=I$1,$D78,"") | J77: =IF($G79=J$1,$D79,"") | K77: =IF($G80=K$1,$D80,"") | L77: =IF($G81=L$1,$D81,"") | M77: =IF($G82=M$1,$D82,"") | N77: =IF($G83=N$1,$D83,"") | O77: =IF($G84=O$1,$D84,"") | P77: =IF($G85=P$1,$D85,"") | Q77: =IF($G86=Q$1,$D86,"") | R77: =IF($G87=R$1,$D87,"") | S77: =IF($G88=S$1,$D88,"") | T77: =IF($G89=T$1,$D89,"") | U77: =IF($G90=U$1,$D90,"") | V77: =IF($G91=V$1,$D91,"") | W77: =CONCATENATE(H77," ",I77," ",J77," ",K77," ",L77," ",M77," ",N77," ",O77," ",P77," ",Q77," ",R77," ",S77," ",T77," ",U77," ",V77)
A78: =C78=D78 -> FALSE | B78: =B77+1 -> 77 | C78: Project Manager Role | D78: involved, or make decisions. | E78: =LEN(D78) -> 28 | G78: =IF(F78=1,1,G77+1) -> 3 | H78: =IF($G78=H$1,$D78,"") | I78: =IF($G79=I$1,$D79,"") | J78: =IF($G80=J$1,$D80,"") | K78: =IF($G81=K$1,$D81,"") | L78: =IF($G82=L$1,$D82,"") | M78: =IF($G83=M$1,$D83,"") | N78: =IF($G84=N$1,$D84,"") | O78: =IF($G85=O$1,$D85,"") | P78: =IF($G86=P$1,$D86,"") | Q78: =IF($G87=Q$1,$D87,"") | R78: =IF($G88=R$1,$D88,"") | S78: =IF($G89=S$1,$D89,"") | T78: =IF($G90=T$1,$D90,"") | U78: =IF($G91=U$1,$D91,"") | V78: =IF($G92=V$1,$D92,"") | W78: =CONCATENATE(H78," ",I78," ",J78," ",K78," ",L78," ",M78," ",N78," ",O78," ",P78," ",Q78," ",R78," ",S78," ",T78," ",U78," ",V78)
A79: =C79=D79 -> FALSE | B79: =B78+1 -> 78 | C79: Project Manager Role | D79: charismatic leadership | E79: =LEN(D79) -> 22 | F79: 1 | G79: =IF(F79=1,1,G78+1) -> 1 | H79: =IF($G79=H$1,$D79,"") -> charismatic leadership | I79: =IF($G80=I$1,$D80,"") -> The leader is motivating, has highenergy, | J79: =IF($G81=J$1,$D81,"") -> and inspires the team through | K79: =IF($G82=K$1,$D82,"") -> strong convictions about what’s possible | L79: =IF($G83=L$1,$D83,"") -> and what the team can achieve. Positive | M79: =IF($G84=M$1,$D84,"") -> thinking and a can-do mentality are | N79: =IF($G85=N$1,$D85,"") -> characteristics of a charismatic leader. | O79: =IF($G86=O$1,$D86,"") | P79: =IF($G87=P$1,$D87,"") | Q79: =IF($G88=Q$1,$D88,"") | R79: =IF($G89=R$1,$D89,"") | S79: =IF($G90=S$1,$D90,"") | T79: =IF($G91=T$1,$D91,"") | U79: =IF($G92=U$1,$D92,"") | V79: =IF($G93=V$1,$D93,"") | W79: =CONCATENATE(H79," ",I79," ",J79," ",K79," ",L79," ",M79," ",N79," ",O79," ",P79," ",Q79," ",R79," ",S79," ",T79," ",U79," ",V79) -> charismatic leadership The leader is motivating, has highenergy, and inspires the team through strong convictions about what’s possible and what the team can achieve. Positive thinking and a can-do mentality are characteristics of a charismatic leader.
A80: =C80=D80 -> FALSE | B80: =B79+1 -> 79 | C80: Project Manager Role | D80: The leader is motivating, has highenergy, | E80: =LEN(D80) -> 41 | G80: =IF(F80=1,1,G79+1) -> 2 | H80: =IF($G80=H$1,$D80,"") | I80: =IF($G81=I$1,$D81,"") | J80: =IF($G82=J$1,$D82,"") | K80: =IF($G83=K$1,$D83,"") | L80: =IF($G84=L$1,$D84,"") | M80: =IF($G85=M$1,$D85,"") | N80: =IF($G86=N$1,$D86,"") | O80: =IF($G87=O$1,$D87,"") | P80: =IF($G88=P$1,$D88,"") | Q80: =IF($G89=Q$1,$D89,"") | R80: =IF($G90=R$1,$D90,"") | S80: =IF($G91=S$1,$D91,"") | T80: =IF($G92=T$1,$D92,"") | U80: =IF($G93=U$1,$D93,"") | V80: =IF($G94=V$1,$D94,"") | W80: =CONCATENATE(H80," ",I80," ",J80," ",K80," ",L80," ",M80," ",N80," ",O80," ",P80," ",Q80," ",R80," ",S80," ",T80," ",U80," ",V80)
A81: =C81=D81 -> FALSE | B81: =B80+1 -> 80 | C81: Project Manager Role | D81: and inspires the team through | E81: =LEN(D81) -> 29 | G81: =IF(F81=1,1,G80+1) -> 3 | H81: =IF($G81=H$1,$D81,"") | I81: =IF($G82=I$1,$D82,"") | J81: =IF($G83=J$1,$D83,"") | K81: =IF($G84=K$1,$D84,"") | L81: =IF($G85=L$1,$D85,"") | M81: =IF($G86=M$1,$D86,"") | N81: =IF($G87=N$1,$D87,"") | O81: =IF($G88=O$1,$D88,"") | P81: =IF($G89=P$1,$D89,"") | Q81: =IF($G90=Q$1,$D90,"") | R81: =IF($G91=R$1,$D91,"") | S81: =IF($G92=S$1,$D92,"") | T81: =IF($G93=T$1,$D93,"") | U81: =IF($G94=U$1,$D94,"") | V81: =IF($G95=V$1,$D95,"") | W81: =CONCATENATE(H81," ",I81," ",J81," ",K81," ",L81," ",M81," ",N81," ",O81," ",P81," ",Q81," ",R81," ",S81," ",T81," ",U81," ",V81)
A82: =C82=D82 -> FALSE | B82: =B81+1 -> 81 | C82: Project Manager Role | D82: strong convictions about what’s possible | E82: =LEN(D82) -> 40 | G82: =IF(F82=1,1,G81+1) -> 4 | H82: =IF($G82=H$1,$D82,"") | I82: =IF($G83=I$1,$D83,"") | J82: =IF($G84=J$1,$D84,"") | K82: =IF($G85=K$1,$D85,"") | L82: =IF($G86=L$1,$D86,"") | M82: =IF($G87=M$1,$D87,"") | N82: =IF($G88=N$1,$D88,"") | O82: =IF($G89=O$1,$D89,"") | P82: =IF($G90=P$1,$D90,"") | Q82: =IF($G91=Q$1,$D91,"") | R82: =IF($G92=R$1,$D92,"") | S82: =IF($G93=S$1,$D93,"") | T82: =IF($G94=T$1,$D94,"") | U82: =IF($G95=U$1,$D95,"") | V82: =IF($G96=V$1,$D96,"") | W82: =CONCATENATE(H82," ",I82," ",J82," ",K82," ",L82," ",M82," ",N82," ",O82," ",P82," ",Q82," ",R82," ",S82," ",T82," ",U82," ",V82)
A83: =C83=D83 -> FALSE | B83: =B82+1 -> 82 | C83: Project Manager Role | D83: and what the team can achieve. Positive | E83: =LEN(D83) -> 39 | G83: =IF(F83=1,1,G82+1) -> 5 | H83: =IF($G83=H$1,$D83,"") | I83: =IF($G84=I$1,$D84,"") | J83: =IF($G85=J$1,$D85,"") | K83: =IF($G86=K$1,$D86,"") | L83: =IF($G87=L$1,$D87,"") | M83: =IF($G88=M$1,$D88,"") | N83: =IF($G89=N$1,$D89,"") | O83: =IF($G90=O$1,$D90,"") | P83: =IF($G91=P$1,$D91,"") | Q83: =IF($G92=Q$1,$D92,"") | R83: =IF($G93=R$1,$D93,"") | S83: =IF($G94=S$1,$D94,"") | T83: =IF($G95=T$1,$D95,"") | U83: =IF($G96=U$1,$D96,"") | V83: =IF($G97=V$1,$D97,"") | W83: =CONCATENATE(H83," ",I83," ",J83," ",K83," ",L83," ",M83," ",N83," ",O83," ",P83," ",Q83," ",R83," ",S83," ",T83," ",U83," ",V83)
A84: =C84=D84 -> FALSE | B84: =B83+1 -> 83 | C84: Project Manager Role | D84: thinking and a can-do mentality are | E84: =LEN(D84) -> 35 | G84: =IF(F84=1,1,G83+1) -> 6 | H84: =IF($G84=H$1,$D84,"") | I84: =IF($G85=I$1,$D85,"") | J84: =IF($G86=J$1,$D86,"") | K84: =IF($G87=K$1,$D87,"") | L84: =IF($G88=L$1,$D88,"") | M84: =IF($G89=M$1,$D89,"") | N84: =IF($G90=N$1,$D90,"") | O84: =IF($G91=O$1,$D91,"") | P84: =IF($G92=P$1,$D92,"") | Q84: =IF($G93=Q$1,$D93,"") | R84: =IF($G94=R$1,$D94,"") | S84: =IF($G95=S$1,$D95,"") | T84: =IF($G96=T$1,$D96,"") | U84: =IF($G97=U$1,$D97,"") | V84: =IF($G98=V$1,$D98,"") | W84: =CONCATENATE(H84," ",I84," ",J84," ",K84," ",L84," ",M84," ",N84," ",O84," ",P84," ",Q84," ",R84," ",S84," ",T84," ",U84," ",V84)
A85: =C85=D85 -> FALSE | B85: =B84+1 -> 84 | C85: Project Manager Role | D85: characteristics of a charismatic leader. | E85: =LEN(D85) -> 40 | G85: =IF(F85=1,1,G84+1) -> 7 | H85: =IF($G85=H$1,$D85,"") | I85: =IF($G86=I$1,$D86,"") | J85: =IF($G87=J$1,$D87,"") | K85: =IF($G88=K$1,$D88,"") | L85: =IF($G89=L$1,$D89,"") | M85: =IF($G90=M$1,$D90,"") | N85: =IF($G91=N$1,$D91,"") | O85: =IF($G92=O$1,$D92,"") | P85: =IF($G93=P$1,$D93,"") | Q85: =IF($G94=Q$1,$D94,"") | R85: =IF($G95=R$1,$D95,"") | S85: =IF($G96=S$1,$D96,"") | T85: =IF($G97=T$1,$D97,"") | U85: =IF($G98=U$1,$D98,"") | V85: =IF($G99=V$1,$D99,"") | W85: =CONCATENATE(H85," ",I85," ",J85," ",K85," ",L85," ",M85," ",N85," ",O85," ",P85," ",Q85," ",R85," ",S85," ",T85," ",U85," ",V85)
A86: =C86=D86 -> FALSE | B86: =B85+1 -> 85 | C86: Project Manager Role | D86: expert power | E86: =LEN(D86) -> 12 | F86: 1 | G86: =IF(F86=1,1,G85+1) -> 1 | H86: =IF($G86=H$1,$D86,"") -> expert power | I86: =IF($G87=I$1,$D87,"") -> The project manager has deep skills and | J86: =IF($G88=J$1,$D88,"") -> experience in a discipline (for example, | K86: =IF($G89=K$1,$D89,"") -> years of working in IT helps an IT project | L86: =IF($G90=L$1,$D90,"") -> manager better manage IT projects). | M86: =IF($G91=M$1,$D91,"") -> ingratiating power | N86: =IF($G92=N$1,$D92,"") -> The project manager aims to gain favor | O86: =IF($G93=O$1,$D93,"") -> with the project team and stakeholders | P86: =IF($G94=P$1,$D94,"") -> through flattery. | Q86: =IF($G95=Q$1,$D95,"") | R86: =IF($G96=R$1,$D96,"") | S86: =IF($G97=S$1,$D97,"") | T86: =IF($G98=T$1,$D98,"") | U86: =IF($G99=U$1,$D99,"") | V86: =IF($G100=V$1,$D100,"") | W86: =CONCATENATE(H86," ",I86," ",J86," ",K86," ",L86," ",M86," ",N86," ",O86," ",P86," ",Q86," ",R86," ",S86," ",T86," ",U86," ",V86) -> expert power The project manager has deep skills and experience in a discipline (for example, years of working in IT helps an IT project manager better manage IT projects). ingratiating power The project manager aims to gain favor with the project team and stakeholders through flattery.
A87: =C87=D87 -> FALSE | B87: =B86+1 -> 86 | C87: Project Manager Role | D87: The project manager has deep skills and | E87: =LEN(D87) -> 39 | G87: =IF(F87=1,1,G86+1) -> 2 | H87: =IF($G87=H$1,$D87,"") | I87: =IF($G88=I$1,$D88,"") | J87: =IF($G89=J$1,$D89,"") | K87: =IF($G90=K$1,$D90,"") | L87: =IF($G91=L$1,$D91,"") | M87: =IF($G92=M$1,$D92,"") | N87: =IF($G93=N$1,$D93,"") | O87: =IF($G94=O$1,$D94,"") | P87: =IF($G95=P$1,$D95,"") | Q87: =IF($G96=Q$1,$D96,"") | R87: =IF($G97=R$1,$D97,"") | S87: =IF($G98=S$1,$D98,"") | T87: =IF($G99=T$1,$D99,"") | U87: =IF($G100=U$1,$D100,"") | V87: =IF($G101=V$1,$D101,"") | W87: =CONCATENATE(H87," ",I87," ",J87," ",K87," ",L87," ",M87," ",N87," ",O87," ",P87," ",Q87," ",R87," ",S87," ",T87," ",U87," ",V87)
A88: =C88=D88 -> FALSE | B88: =B87+1 -> 87 | C88: Project Manager Role | D88: experience in a discipline (for example, | E88: =LEN(D88) -> 40 | G88: =IF(F88=1,1,G87+1) -> 3 | H88: =IF($G88=H$1,$D88,"") | I88: =IF($G89=I$1,$D89,"") | J88: =IF($G90=J$1,$D90,"") | K88: =IF($G91=K$1,$D91,"") | L88: =IF($G92=L$1,$D92,"") | M88: =IF($G93=M$1,$D93,"") | N88: =IF($G94=N$1,$D94,"") | O88: =IF($G95=O$1,$D95,"") | P88: =IF($G96=P$1,$D96,"") | Q88: =IF($G97=Q$1,$D97,"") | R88: =IF($G98=R$1,$D98,"") | S88: =IF($G99=S$1,$D99,"") | T88: =IF($G100=T$1,$D100,"") | U88: =IF($G101=U$1,$D101,"") | V88: =IF($G102=V$1,$D102,"") | W88: =CONCATENATE(H88," ",I88," ",J88," ",K88," ",L88," ",M88," ",N88," ",O88," ",P88," ",Q88," ",R88," ",S88," ",T88," ",U88," ",V88)
A89: =C89=D89 -> FALSE | B89: =B88+1 -> 88 | C89: Project Manager Role | D89: years of working in IT helps an IT project | E89: =LEN(D89) -> 42 | G89: =IF(F89=1,1,G88+1) -> 4 | H89: =IF($G89=H$1,$D89,"") | I89: =IF($G90=I$1,$D90,"") | J89: =IF($G91=J$1,$D91,"") | K89: =IF($G92=K$1,$D92,"") | L89: =IF($G93=L$1,$D93,"") | M89: =IF($G94=M$1,$D94,"") | N89: =IF($G95=N$1,$D95,"") | O89: =IF($G96=O$1,$D96,"") | P89: =IF($G97=P$1,$D97,"") | Q89: =IF($G98=Q$1,$D98,"") | R89: =IF($G99=R$1,$D99,"") | S89: =IF($G100=S$1,$D100,"") | T89: =IF($G101=T$1,$D101,"") | U89: =IF($G102=U$1,$D102,"") | V89: =IF($G103=V$1,$D103,"") | W89: =CONCATENATE(H89," ",I89," ",J89," ",K89," ",L89," ",M89," ",N89," ",O89," ",P89," ",Q89," ",R89," ",S89," ",T89," ",U89," ",V89)
A90: =C90=D90 -> FALSE | B90: =B89+1 -> 89 | C90: Project Manager Role | D90: manager better manage IT projects). | E90: =LEN(D90) -> 35 | G90: =IF(F90=1,1,G89+1) -> 5 | H90: =IF($G90=H$1,$D90,"") | I90: =IF($G91=I$1,$D91,"") | J90: =IF($G92=J$1,$D92,"") | K90: =IF($G93=K$1,$D93,"") | L90: =IF($G94=L$1,$D94,"") | M90: =IF($G95=M$1,$D95,"") | N90: =IF($G96=N$1,$D96,"") | O90: =IF($G97=O$1,$D97,"") | P90: =IF($G98=P$1,$D98,"") | Q90: =IF($G99=Q$1,$D99,"") | R90: =IF($G100=R$1,$D100,"") | S90: =IF($G101=S$1,$D101,"") | T90: =IF($G102=T$1,$D102,"") | U90: =IF($G103=U$1,$D103,"") | V90: =IF($G104=V$1,$D104,"") | W90: =CONCATENATE(H90," ",I90," ",J90," ",K90," ",L90," ",M90," ",N90," ",O90," ",P90," ",Q90," ",R90," ",S90," ",T90," ",U90," ",V90)
A91: =C91=D91 -> FALSE | B91: =B90+1 -> 90 | C91: Project Manager Role | D91: ingratiating power | E91: =LEN(D91) -> 18 | G91: =IF(F91=1,1,G90+1) -> 6 | H91: =IF($G91=H$1,$D91,"") | I91: =IF($G92=I$1,$D92,"") | J91: =IF($G93=J$1,$D93,"") | K91: =IF($G94=K$1,$D94,"") | L91: =IF($G95=L$1,$D95,"") | M91: =IF($G96=M$1,$D96,"") | N91: =IF($G97=N$1,$D97,"") | O91: =IF($G98=O$1,$D98,"") | P91: =IF($G99=P$1,$D99,"") | Q91: =IF($G100=Q$1,$D100,"") | R91: =IF($G101=R$1,$D101,"") | S91: =IF($G102=S$1,$D102,"") | T91: =IF($G103=T$1,$D103,"") | U91: =IF($G104=U$1,$D104,"") | V91: =IF($G105=V$1,$D105,"") | W91: =CONCATENATE(H91," ",I91," ",J91," ",K91," ",L91," ",M91," ",N91," ",O91," ",P91," ",Q91," ",R91," ",S91," ",T91," ",U91," ",V91)
A92: =C92=D92 -> FALSE | B92: =B91+1 -> 91 | C92: Project Manager Role | D92: The project manager aims to gain favor | E92: =LEN(D92) -> 38 | G92: =IF(F92=1,1,G91+1) -> 7 | H92: =IF($G92=H$1,$D92,"") | I92: =IF($G93=I$1,$D93,"") | J92: =IF($G94=J$1,$D94,"") | K92: =IF($G95=K$1,$D95,"") | L92: =IF($G96=L$1,$D96,"") | M92: =IF($G97=M$1,$D97,"") | N92: =IF($G98=N$1,$D98,"") | O92: =IF($G99=O$1,$D99,"") | P92: =IF($G100=P$1,$D100,"") | Q92: =IF($G101=Q$1,$D101,"") | R92: =IF($G102=R$1,$D102,"") | S92: =IF($G103=S$1,$D103,"") | T92: =IF($G104=T$1,$D104,"") | U92: =IF($G105=U$1,$D105,"") | V92: =IF($G106=V$1,$D106,"") | W92: =CONCATENATE(H92," ",I92," ",J92," ",K92," ",L92," ",M92," ",N92," ",O92," ",P92," ",Q92," ",R92," ",S92," ",T92," ",U92," ",V92)
A93: =C93=D93 -> FALSE | B93: =B92+1 -> 92 | C93: Project Manager Role | D93: with the project team and stakeholders | E93: =LEN(D93) -> 38 | G93: =IF(F93=1,1,G92+1) -> 8 | H93: =IF($G93=H$1,$D93,"") | I93: =IF($G94=I$1,$D94,"") | J93: =IF($G95=J$1,$D95,"") | K93: =IF($G96=K$1,$D96,"") | L93: =IF($G97=L$1,$D97,"") | M93: =IF($G98=M$1,$D98,"") | N93: =IF($G99=N$1,$D99,"") | O93: =IF($G100=O$1,$D100,"") | P93: =IF($G101=P$1,$D101,"") | Q93: =IF($G102=Q$1,$D102,"") | R93: =IF($G103=R$1,$D103,"") | S93: =IF($G104=S$1,$D104,"") | T93: =IF($G105=T$1,$D105,"") | U93: =IF($G106=U$1,$D106,"") | V93: =IF($G107=V$1,$D107,"") | W93: =CONCATENATE(H93," ",I93," ",J93," ",K93," ",L93," ",M93," ",N93," ",O93," ",P93," ",Q93," ",R93," ",S93," ",T93," ",U93," ",V93)
A94: =C94=D94 -> FALSE | B94: =B93+1 -> 93 | C94: Project Manager Role | D94: through flattery. | E94: =LEN(D94) -> 17 | G94: =IF(F94=1,1,G93+1) -> 9 | H94: =IF($G94=H$1,$D94,"") | I94: =IF($G95=I$1,$D95,"") | J94: =IF($G96=J$1,$D96,"") | K94: =IF($G97=K$1,$D97,"") | L94: =IF($G98=L$1,$D98,"") | M94: =IF($G99=M$1,$D99,"") | N94: =IF($G100=N$1,$D100,"") | O94: =IF($G101=O$1,$D101,"") | P94: =IF($G102=P$1,$D102,"") | Q94: =IF($G103=Q$1,$D103,"") | R94: =IF($G104=R$1,$D104,"") | S94: =IF($G105=S$1,$D105,"") | T94: =IF($G106=T$1,$D106,"") | U94: =IF($G107=U$1,$D107,"") | V94: =IF($G108=V$1,$D108,"") | W94: =CONCATENATE(H94," ",I94," ",J94," ",K94," ",L94," ",M94," ",N94," ",O94," ",P94," ",Q94," ",R94," ",S94," ",T94," ",U94," ",V94)
A95: =C95=D95 -> FALSE | B95: =B94+1 -> 94 | C95: Project Manager Role | D95: informational power | E95: =LEN(D95) -> 19 | F95: 1 | G95: =IF(F95=1,1,G94+1) -> 1 | H95: =IF($G95=H$1,$D95,"") -> informational power | I95: =IF($G96=I$1,$D96,"") -> The individual has power and control of | J95: =IF($G97=J$1,$D97,"") -> the data gathering and distribution of | K95: =IF($G98=K$1,$D98,"") -> information. | L95: =IF($G99=L$1,$D99,"") -> interactional leadership The leader is a hybrid of transactional, transformational, and charismatic leaders. The interactional leader wants the team to act, is excited and inspired about the project work, yet still holds the team accountable for their results. guilt-based power The project manager can make the team and stakeholders feel guilty to gain compliance in the project. leadership Leadership is about aligning, motivating, and inspiring the project team members to do the right thing, build trust, think creatively, and to challenge the status quo. laissez-faire leadership The leader takes a “hands-off” approach to the project. This means the project team makes decisions, takes initiative in the actions, and creates goals. While this approach can provide autonomy, it can make the leader appear absent when it comes to project decisions. management Management utilizes positional power to maintain, administrate, control, and focus on getting things done without challenging the status quo of the project and organization. media selection Based on the audience and the message being sent, the media should be in alignment with the message. meeting management Meetings are forms of communication. How the meeting is led, managed, and controlled all influence the message being delivered. Agendas, minutes, and order are mandatory for effective communications within a meeting. personal or charismatic power The project manager has a warm personality that others like. | M95: =IF($G100=M$1,$D100,"") -> presentation | N95: =IF($G101=N$1,$D101,"") -> In formal presentations, the presenter’s | O95: =IF($G102=O$1,$D102,"") -> oral and body language, visual aids, and | P95: =IF($G103=P$1,$D103,"") -> handouts all influence the message being | Q95: =IF($G104=Q$1,$D104,"") -> delivered. | R95: =IF($G105=R$1,$D105,"") | S95: =IF($G106=S$1,$D106,"") | T95: =IF($G107=T$1,$D107,"") | U95: =IF($G108=U$1,$D108,"") | V95: =IF($G109=V$1,$D109,"") | W95: =CONCATENATE(H95," ",I95," ",J95," ",K95," ",L95," ",M95," ",N95," ",O95," ",P95," ",Q95," ",R95," ",S95," ",T95," ",U95," ",V95) -> informational power The individual has power and control of the data gathering and distribution of information. interactional leadership The leader is a hybrid of transactional, transformational, and charismatic leaders. The interactional leader wants the team to act, is excited and inspired about the project work, yet still holds the team accountable for their results. guilt-based power The project manager can make the team and stakeholders feel guilty to gain compliance in the project. leadership Leadership is about aligning, motivating, and inspiring the project team members to do the right thing, build trust, think creatively, and to challenge the status quo. laissez-faire leadership The leader takes a “hands-off” approach to the project. This means the project team makes decisions, takes initiative in the actions, and creates goals. While this approach can provide autonomy, it can make the leader appear absent when it comes to project decisions. management Management utilizes positional power to maintain, administrate, control, and focus on getting things done without challenging the status quo of the project and organization. media selection Based on the audience and the message being sent, the media should be in alignment with the message. meeting management Meetings are forms of communication. How the meeting is led, managed, and controlled all influence the message being delivered. Agendas, minutes, and order are mandatory for effective communications within a meeting. personal or charismatic power The project manager has a warm personality that others like. presentation In formal presentations, the presenter’s oral and body language, visual aids, and handouts all influence the message being delivered.
A96: =C96=D96 -> FALSE | B96: =B95+1 -> 95 | C96: Project Manager Role | D96: The individual has power and control of | E96: =LEN(D96) -> 39 | G96: =IF(F96=1,1,G95+1) -> 2 | H96: =IF($G96=H$1,$D96,"") | I96: =IF($G97=I$1,$D97,"") | J96: =IF($G98=J$1,$D98,"") | K96: =IF($G99=K$1,$D99,"") | L96: =IF($G100=L$1,$D100,"") | M96: =IF($G101=M$1,$D101,"") | N96: =IF($G102=N$1,$D102,"") | O96: =IF($G103=O$1,$D103,"") | P96: =IF($G104=P$1,$D104,"") | Q96: =IF($G105=Q$1,$D105,"") | R96: =IF($G106=R$1,$D106,"") | S96: =IF($G107=S$1,$D107,"") | T96: =IF($G108=T$1,$D108,"") | U96: =IF($G109=U$1,$D109,"") | V96: =IF($G110=V$1,$D110,"") | W96: =CONCATENATE(H96," ",I96," ",J96," ",K96," ",L96," ",M96," ",N96," ",O96," ",P96," ",Q96," ",R96," ",S96," ",T96," ",U96," ",V96)
A97: =C97=D97 -> FALSE | B97: =B96+1 -> 96 | C97: Project Manager Role | D97: the data gathering and distribution of | E97: =LEN(D97) -> 38 | G97: =IF(F97=1,1,G96+1) -> 3 | H97: =IF($G97=H$1,$D97,"") | I97: =IF($G98=I$1,$D98,"") | J97: =IF($G99=J$1,$D99,"") | K97: =IF($G100=K$1,$D100,"") | L97: =IF($G101=L$1,$D101,"") | M97: =IF($G102=M$1,$D102,"") | N97: =IF($G103=N$1,$D103,"") | O97: =IF($G104=O$1,$D104,"") | P97: =IF($G105=P$1,$D105,"") | Q97: =IF($G106=Q$1,$D106,"") | R97: =IF($G107=R$1,$D107,"") | S97: =IF($G108=S$1,$D108,"") | T97: =IF($G109=T$1,$D109,"") | U97: =IF($G110=U$1,$D110,"") | V97: =IF($G111=V$1,$D111,"") | W97: =CONCATENATE(H97," ",I97," ",J97," ",K97," ",L97," ",M97," ",N97," ",O97," ",P97," ",Q97," ",R97," ",S97," ",T97," ",U97," ",V97)
A98: =C98=D98 -> FALSE | B98: =B97+1 -> 97 | C98: Project Manager Role | D98: information. | E98: =LEN(D98) -> 12 | G98: =IF(F98=1,1,G97+1) -> 4 | H98: =IF($G98=H$1,$D98,"") | I98: =IF($G99=I$1,$D99,"") | J98: =IF($G100=J$1,$D100,"") | K98: =IF($G101=K$1,$D101,"") | L98: =IF($G102=L$1,$D102,"") | M98: =IF($G103=M$1,$D103,"") | N98: =IF($G104=N$1,$D104,"") | O98: =IF($G105=O$1,$D105,"") | P98: =IF($G106=P$1,$D106,"") | Q98: =IF($G107=Q$1,$D107,"") | R98: =IF($G108=R$1,$D108,"") | S98: =IF($G109=S$1,$D109,"") | T98: =IF($G110=T$1,$D110,"") | U98: =IF($G111=U$1,$D111,"") | V98: =IF($G112=V$1,$D112,"") | W98: =CONCATENATE(H98," ",I98," ",J98," ",K98," ",L98," ",M98," ",N98," ",O98," ",P98," ",Q98," ",R98," ",S98," ",T98," ",U98," ",V98)
A99: =C99=D99 -> FALSE | B99: =B98+1 -> 98 | C99: Project Manager Role | D99: interactional leadership The leader is a hybrid of transactional, transformational, and charismatic leaders. The interactional leader wants the team to act, is excited and inspired about the project work, yet still holds the team accountable for their results. guilt-based power The project manager can make the team and stakeholders feel guilty to gain compliance in the project. leadership Leadership is about aligning, motivating, and inspiring the project team members to do the right thing, build trust, think creatively, and to challenge the status quo. laissez-faire leadership The leader takes a “hands-off” approach to the project. This means the project team makes decisions, takes initiative in the actions, and creates goals. While this approach can provide autonomy, it can make the leader appear absent when it comes to project decisions. management Management utilizes positional power to maintain, administrate, control, and focus on getting things done without challenging the status quo of the project and organization. media selection Based on the audience and the message being sent, the media should be in alignment with the message. meeting management Meetings are forms of communication. How the meeting is led, managed, and controlled all influence the message being delivered. Agendas, minutes, and order are mandatory for effective communications within a meeting. personal or charismatic power The project manager has a warm personality that others like. | E99: =LEN(D99) -> 1481 | G99: =IF(F99=1,1,G98+1) -> 5 | H99: =IF($G99=H$1,$D99,"") | I99: =IF($G100=I$1,$D100,"") | J99: =IF($G101=J$1,$D101,"") | K99: =IF($G102=K$1,$D102,"") | L99: =IF($G103=L$1,$D103,"") | M99: =IF($G104=M$1,$D104,"") | N99: =IF($G105=N$1,$D105,"") | O99: =IF($G106=O$1,$D106,"") | P99: =IF($G107=P$1,$D107,"") | Q99: =IF($G108=Q$1,$D108,"") | R99: =IF($G109=R$1,$D109,"") | S99: =IF($G110=S$1,$D110,"") | T99: =IF($G111=T$1,$D111,"") | U99: =IF($G112=U$1,$D112,"") | V99: =IF($G113=V$1,$D113,"") | W99: =CONCATENATE(H99," ",I99," ",J99," ",K99," ",L99," ",M99," ",N99," ",O99," ",P99," ",Q99," ",R99," ",S99," ",T99," ",U99," ",V99)
A100: =C100=D100 -> FALSE | B100: =B99+1 -> 99 | C100: Project Manager Role | D100: presentation | E100: =LEN(D100) -> 12 | G100: =IF(F100=1,1,G99+1) -> 6 | H100: =IF($G100=H$1,$D100,"") | I100: =IF($G101=I$1,$D101,"") | J100: =IF($G102=J$1,$D102,"") | K100: =IF($G103=K$1,$D103,"") | L100: =IF($G104=L$1,$D104,"") | M100: =IF($G105=M$1,$D105,"") | N100: =IF($G106=N$1,$D106,"") | O100: =IF($G107=O$1,$D107,"") | P100: =IF($G108=P$1,$D108,"") | Q100: =IF($G109=Q$1,$D109,"") | R100: =IF($G110=R$1,$D110,"") | S100: =IF($G111=S$1,$D111,"") | T100: =IF($G112=T$1,$D112,"") | U100: =IF($G113=U$1,$D113,"") | V100: =IF($G114=V$1,$D114,"") | W100: =CONCATENATE(H100," ",I100," ",J100," ",K100," ",L100," ",M100," ",N100," ",O100," ",P100," ",Q100," ",R100," ",S100," ",T100," ",U100," ",V100)
...

Sheet Summary
A3: Row Labels | B3: Count of Term
A4: Project Communications Management Terms | B4: 26
A5: Project Integration Management Terms | B5: 40
A6: Project Management Fundamental Terms | B6: 26
A7: Project Manager Role | B7: 13
A8: Project Quality Management Terms | B8: 30
A9: Project Resources Management Terms | B9: 28
A10: Project Risk Management Terms | B10: 72
A11: Project Scope Management Terms | B11: 84
A12: Project Stakeholder Management Terms | B12: 16
A13: Grand Total | B13: 335

Sheet All
B2: 🧠 Core Domains (PMI Talent Triangle) | C2: 📚 PMBOK® Guide Knowledge Areas | D2: 📈 Performance Domains (PMBOK® 7th Edition) | E2: 🧩 Key Concepts to Master | F2: 📝 Exam Strategy
B3: 1. People – Leadership, team performance, conflict resolution, motivation | C3: These are traditional areas from earlier PMBOK editions, still relevant: | D3: These are broader areas of focus in modern PMP: | E3: Tailoring – Adapting methods to fit the project | F3: Situational Questions – Apply concepts to real scenarios
B4: 2. Process – Project management practices, tools, and techniques | C4: 1. Integration Management | D4: 1. Team | E4: Delivery Approaches – Predictive, Agile, Hybrid, etc. | F4: Agile & Hybrid Focus – Increasing emphasis on adaptive methods
B5: 3. Business Environment – Strategic alignment, compliance, value delivery | C5: 2. Scope Management | D5: 2. Stakeholders | E5: Principles – 12 guiding principles from PMBOK® 7 | F5: Ethics & Professional Conduct – PMI Code of Ethics
C6: 3. Schedule Management | D6: 3. Life Cycle & Development Approach | E6: Math & Formulas – Earned Value, PERT, ROI, etc.
C7: 4. Cost Management | D7: 4. Planning | E7: Scenarios – Real-world application of concepts
C8: 5. Quality Management | D8: 5. Project Work | E8: Manager Role – Leadership, decision-making, ethics
C9: 6. Resource Management | D9: 6. Delivery | E9: Fundamentals – Definitions, roles, processes
C10: 7. Communications Management | D10: 7. Measurement
C11: 8. Risk Management | D11: 8. Uncertainty
C12: 9. Procurement Management
C13: 10. Stakeholder Management

Sheet PMBOK
F1: APPENDIX X1
B2: THE STANDARD FOR PROJECT MANAGEMENT | D2: A GUIDE TO THE PROJECT MANAGEMENT | F2: CONTRIBUTORS AND REVIEWERS OF
B3: 1 INTRODUCTION...................................................................................3 | D3: BODY OF KNOWLEDGE (PMBOK® GUIDE) | F3: THE STANDARD FOR PROJECT MANAGEMENT AND
B4: 1.1 Purpose of The Standard for Project Management......................3 | D4: 1. INTRODUCTION..................................................................................3 | F4: A GUIDE TO THE PROJECT MANAGEMENT BODY
B5: 1.2 Key Terms and Concepts.............................................................4 | D5: 1.1 Structure of the PMBOK® Guide................................................3 | F5: OF KNOWLEDGE – SEVENTH EDITION...............................................197
B6: 1.3 Audience for this Standard..........................................................5 | D6: 1.2 Relationship of the PMBOK® Guide | F6: X1.1 Contributors........................................................................197
B7: 2 A SYSTEM FOR VALUE DELIVERY........................................................7 | D7: and The Standard for Project Management................................4 | F7: X1.2 PMI Staff.............................................................................206
B8: 2.1 Creating Value.............................................................................7 | D8: 1.3 Changes to the PMBOK® Guide.................................................6 | F8: APPENDIX X2
B9: 2.1.1 Value Delivery Components...............................................8 | D9: 1.4 Relationship to PMIstandards+..................................................6 | F9: SPONSOR.............................................................................................207
B10: 2.1.2 Information Flow.............................................................11 | D10: 2. PROJECT PERFORMANCE DOMAINS..................................................7 | F10: X2.1 Introduction........................................................................207
B11: 2.2 Organizational Governance Systems.........................................12 | D11: 2.1 Stakeholder Performance Domain.............................................8 | F11: X2.2 The Sponsor Role................................................................207
B12: 2.3 Functions Associated with Projects...........................................12 | D12: 2.1.1 Stakeholder Engagement...............................................10 | F12: X2.3 Lack of Engagement............................................................208
B13: 2.3.1 Provide Oversight and Coordination................................13 | D13: 2.1.2 Interactions with Other Performance Domains...............14 | F13: X2.4 Sponsor Behaviors...............................................................209
... B38: References.......................................................................................60 | D38: 2.4.3 Project Team Composition and Structure........................63 | F38: X5.3 Research for The Standard for Project Management...........228
D39: 2.4.4 Communication..............................................................64 | F39: X5.4 Standard Development Process...........................................229
B40: List of Figures and Tables | D40: 2.4.5 Physical Resources.........................................................65 | F40: X5.5 Validating the Standard.......................................................230
B41: THE STANDARD FOR PROJECT MANAGEMENT | D41: 2.4.6 Procurement..................................................................65 | F41: X5.6 Summary.............................................................................232
B42: Figure 2-1. Example of a System for Value Delivery............................9 | D42: 2.4.7 Changes.........................................................................66 | F42: GLOSSARY...........................................................................................233
B43: Figure 2-2. Components of a Sample System for Value Delivery.......10 | D43: 2.4.8 Metrics...........................................................................66 | F43: 1. Inclusions and Exclusions...........................................................233
B44: Figure 2-3. Example of Information Flow..........................................11 | D44: 2.4.9 Alignment......................................................................67 | F44: 2. Common Acronyms...................................................................234
B45: Figure 2-4. Sample Product Life Cycle...............................................19 | D45: 2.4.10 Interactions with Other Performance Domains...............67 | F45: 3. Definitions.................................................................................235
B46: Figure 3-1. Overlap of Project Management | D46: 2.4.11 Checking Results............................................................68 | F46: INDEX..................................................................................................255
B47: and General Management Principles...............................22 | D47: 2.5 Project Work Performance Domain...........................................69
B48: Figure 3-2. Be a Diligent, Respectful, and Caring Steward................24 | D48: 2.5.1 Project Processes...........................................................71
B49: Figure 3-3. Create a Collaborative Project Team Environment...........28 | D49: 2.5.2 Balancing Competing Constraints...................................72
B50: Figure 3-4. Effectively Engage with Stakeholders.............................31 | D50: 2.5.3 Maintaining Project Team Focus.....................................73
B51: Figure 3-5. Focus on Value................................................................34 | D51: 2.5.4 Project Communications and Engagement.....................73
B52: Figure 3-6. Recognize, Evaluate, and Respond | D52: 2.5.5 Managing Physical Resources.........................................73
B53: to System Interactions.....................................................37 | D53: 2.5.6 Working with Procurements...........................................74
B54: Figure 3-7. Demonstrate Leadership Behaviors.................................40 | D54: 2.5.7 Monitoring New Work and Changes...............................76
B55: Figure 3-8. Tailor Based on Context..................................................44 | D55: 2.5.8 Learning throughout the Project....................................77
B56: Figure 3-9. Build Quality into Processes and Deliverables.................47 | D56: 2.5.9 Interactions with Other Performance Domains...............78
B57: Figure 3-10. Navigate Complexity.......................................................50 | D57: 2.5.10 Checking Results............................................................79
B58: Figure 3-11. Optimize Risk Responses.................................................53 | D58: 2.6 Delivery Performance Domain...................................................80
... B61: the Envisioned Future State............................................58 | D61: 2.6.3 Quality...........................................................................87
D62: 2.6.4 Suboptimal Outcomes....................................................91
D63: 2.6.5 Interactions with Other Performance Domains...............91
D64: 2.6.6 Checking Results............................................................92
D65: 2.7 Measurement Performance Domain...........................................93
D66: 2.7.1 Establishing Effective Measures.....................................95
D67: 2.7.2 What to Measure...........................................................98
D68: 2.7.3 Presenting Information................................................106
D69: 2.7.4 Measurement Pitfalls....................................................111
D70: 2.7.5 Troubleshooting Performance......................................113
D71: 2.7.6 Growing and Improving...............................................114
D72: 2.7.7 Interactions with Other Performance Domains.............114
D73: 2.7.8 Checking Results..........................................................115
... D219: Programs, and Products................................................224

Sheet Sheet9
H2: Module | I2: Pmism's
C3: 📊 Example PMBOK-Aligned Traits to Assess | F3: Approximately 70–80% of the PMP exam questions are scenario-based | H3: STAKEHOLDER MANAGEMENT | I3: While PMs may have experience and want to maintain project momentum, the team that will execute the work has the best understanding of what's actually required to complete it.
C4: PMBOK Principle | D4: Psychometric Focus | H4: STAKEHOLDER MANAGEMENT | I4: New organizational changes, role changes, or people joining/leaving during a project require immediate stakeholder analysis updates.
C5: Stewardship | D5: Ethics, responsibility, integrity | H5: STAKEHOLDER MANAGEMENT | I5: When stakeholder engagement drops using one communication method, the solution isn't to intensify that same method but to diversify communication channels.
C6: Team | D6: Collaboration, emotional intelligence | F6: These questions test your ability to apply principles, performance domains, and decision-making in real-world project situations. | H6: STAKEHOLDER MANAGEMENT | I6: Emotional intelligence involves reading between the lines of what stakeholders say and observing changes in behavior, tone, and engagement.
C7: Value | D7: Strategic thinking, customer focus | F7: The remaining questions are typically knowledge-based, definition-focused, or interpretive (e.g., identifying the best tool or technique). | H7: STAKEHOLDER MANAGEMENT | I7: Anyone whose work, processes, or outcomes are affected by the project should be considered a stakeholder and managed accordingly.
C8: Systems Thinking | D8: Analytical thinking, holistic view | H8: STAKEHOLDER MANAGEMENT | I8: Customer requests, even those that seem disruptive or late in the project, should first be evaluated for their business value and strategic importance.
C9: Leadership | D9: Influence, decision-making, vision | H9: CHANGE MANAGEMENT | I9: In agile methodology, changes are managed through backlog prioritization rather than formal change control processes.
C10: Tailoring | D10: Flexibility, contextual judgment | H10: CHANGE MANAGEMENT | I10: Even when changes come from high-authority stakeholders (like sponsors) or seem obviously necessary (like regulatory compliance), the formal change control process must be followed.
C11: Quality | D11: Attention to detail, standards adherence | H11: CHANGE MANAGEMENT | I11: What seems "easy" often has hidden complexities or downstream effects that only become apparent through systematic analysis.
H12: DECISION MAKING & PROBLEM SOLVING | I12: Emergency situations create pressure to "do something quickly," but this is precisely when planning becomes most critical.
H13: DECISION MAKING & PROBLEM SOLVING | I13: Even when PMs feel confident in their analysis, the project team's expertise and hands-on experience often reveal critical insights that aren't apparent from high-level planning.
H14: DECISION MAKING & PROBLEM SOLVING | I14: Value-driven decision making requires considering both immediate and long-term impacts on all stakeholders.
H15: DECISION MAKING & PROBLEM SOLVING | I15: Conflicts that appear to be about specific issues are often symptoms of deeper problems like communication gaps, role confusion, competing priorities, or unmet needs.
H16: DECISION MAKING & PROBLEM SOLVING | I16: When issues are found, it is important to first add to the issue log.
H17: DECISION MAKING & PROBLEM SOLVING | I17: Demonstrating leadership doesn't mean making decisions independently when specialized knowledge is required.
H18: DECISION MAKING & PROBLEM SOLVING | I18: Taking time to gather information, even when clients demand immediate responses, leads to more effective and appropriate solutions than reactive decisions.
H19: DECISION MAKING & PROBLEM SOLVING | I19: Tangible outputs like prototypes, MVPs, or working components provide concrete evidence that the project is progressing and that the final deliverable will meet expectations.
H20: DECISION MAKING & PROBLEM SOLVING | I20: Taking ownership of problem resolution demonstrates leadership and prevents unnecessary escalation fatigue.
H21: TEAM LEADERSHIP & COLLABORATION | I21: When teams struggle, the servant leader's role is to create conditions for learning, growth, and success rather than taking over or bringing in external solutions.
H22: TEAM LEADERSHIP & COLLABORATION | I22: Project managers must think beyond individual functional areas and focus on how all pieces fit together.
H23: TEAM LEADERSHIP & COLLABORATION | I23: While PMs may have experience and want to maintain project momentum, the team that will execute the work has the best understanding of what's actually required to complete it.
... H53: EXAM STRATEGY & DECISION GUIDELINES | I53: Not every project situation has one obviously correct solution. In these cases, make your best choice based on sound PM principles and don't second-guess yourself endlessly.

Sheet Answers WHY
A4: Term | B4: Answer
A5: Add it to the product backlog | B5: When a customer would like to add a change to an agile project, they simply added to the product backlog. That new feature will then be prioritized based on its value in the product backlog.
A6: Add the feature as an exclusion to the scope statement | B6: A project scope statement not only contains the project’s deliverables but also the exclusions, which are features the project will not accomplish. Mark should not add the feature due to the company’s inability to install it.
A7: Add the security system to the datacenter | B7: You should not add changes to a project management plan without it being first approved
A8: Analogous estimates | B8: Analogous estimates are based on historical information to estimate the cost of each activity.
A9: Approve the changes himself | B9: On a very small project, the project manager may ask the sponsor to approve or deny changes. The project manager’s main job is to document and assess changes to the project.
A10: Approve the changes himself with the help of the project team | B10: On a very small project, the project manager may ask the sponsor to approve or deny changes. The project manager’s main job is to document and assess changes to the project.
A11: Assumption log | B11: The assumption log will only document assumptions that are made on a project
A12: Assumptions analysis | B12: Assumptions analysis involves analyzing assumptions
A13: Bottom-up estimation | B13: The tools of bottom-up estimation and parametric estimation are not used to determine a budget
A14: Bottom-up | B14: Bottom-up involves breaking down the work and then adding it back up.
A15: Change request | B15: A change request is only issued when parts of the project management plan or document must be updated.
... A32: Create WBS | B32: Creating WBS and defining scope will come before defining activities.
B33: The create WBS process is generally done after the scope statement has been created, as it will decompose the deliverables in the scope statement
B34: The create WBS process is generally done after the scope statement has been created, as it will decompose the deliverables in the scope statement. You cannot define activities or sequence activities until the WBS is complete, as you will need to know work packages to create the activities.
A35: Critical path method | B35: The critical path method is about creating a network diagram and finding the critical path.
A36: Define activities | B36: You cannot define activities or sequence activities until the WBS is complete, as you will need to know work packages to create the activities
A37: Define Scope | B37: Creating WBS and defining scope will come before defining activities.
A38: Develop project charter | B38: Develop project charter is used to get the project authorized
A39: Develop project management plan | B39: Work performance data is an output of the integration process of direct and manage project work.
A40: Direct and manage project work | B40: Once a change has been approved, it is then moved to the direct and manage project work process for implementation
A41: Direct and manage project work | B41: Once a change has been approved, it is time to execute the change, which is done in the executing process of direct and manage project work
B42: Work performance data is an output of the integration process of direct and manage project work.
A43: Don’t worry too much about the specifics it’s more important to get the relative prioritization correct | B43: When using any prioritization technique, it is important the customer understands not to worry too much about the specifics of the technique but rather to prioritize the features based on relative value.
A44: Downwards | B44: Downward influence is for those below you such as team members.
A45: Emotional intelligence | B45: Emotional intelligence is defined as the ability to identify, assess, and influence emotions of ourselves and others around us.
A46: Encryption | B46: Encryption is not a tool in the PMBOK.
A47: Establish a change control board for the project | B47: Since this is a large project that will affect a large population, it would be best to establish a change control board for the project to have the changes reviewed and approved. On a very small project, the project manager may ask the sponsor to approve or deny changes. The project manager’s main job is to document and assess changes to the project.
A48: Estimate activity resources | B48: The process of estimate activity resources will output the resource breakdown structure, which is a hierarchal breakdown of resources by their categories and types. No other choice will output this project document.
A49: Executing | B49: During the executing process group, the project manager will assess the team’s performance and try to improve it through the process of developing and managing the team.
B50: In the executing process group, the team completes the deliverables.
A51: Expert judgment | B51: An expert may help in determining the costs, but not to aggregate them.
A52: Fast tracking | B52: Fast tracking is when you run activities in parallel. Adding leads to activities will overlap activities
A53: Fishbone analysis | B53: A Fishbone analysis is done during the generate insight step in a retrospective to show the reasons for why something failed.
A54: Fishbone diagram | B54: A fishbone diagram is used to help identify potential causes of defects
A55: Float | B55: Slack and floats refer to the same thing: the amount of time you can delay an activity without delaying the project.
A56: Flowchart | B56: A flowchart is a tool that is used to help visually display a process. It can show decision points, loops, or paths.
A57: Forcing | B57: forcing is when one side completely wins and the other side completely loses.
A58: Forming | B58: The team is currently in the forming stage and will move next to the storming stage. The stages are forming, storming, norming, performing and adjourning.
A59: Free float | B59: Free float is the amount of time you can delay an activity without delaying the next activity
A60: Funding limit reconciliation | B60: Funding limit reconciliation is done when there are limited funds to spend on the project and work may need to be rescheduled
A61: Gantt chart | B61: All other choices would give you a detailed view of the project schedule and work.
A62: Histogram | B62: histogram, such as a Pareto chart, is a bar chart that shows the frequency of things.
... A70: Initiating | B70: The process of identifying stakeholders is part of the initiating process group
B71: The process of identifying stakeholders is part of the initiating process group.
A72: Inspection leads to less prevention | B72: Prevention leads to less inspection.
A73: Inspections | B73: and inspections are used to see if a deliverable has met its requirements.
A74: Issue log | B74: The issue log is used to keep track of all issues in the project. The delay of a server will mean the project might be delayed, so it should be entered into the issue log immediately. After that the project manager might implement a change request to extend the schedule baseline and update the project management plan
A75: Issue log | B75: and the issue log will have a list of issues that are currently taking place on a project.
A76: Kanban development | B76: Kanban development involves the use of a signboard that is used to help track the work in progress and limit the work in progress.
A77: Lag | B77: Lag is the amount of time you need to delay an activity before the next activity starts.
A78: Lessons learned register | B78: The lessons learned register is used to keep track of all new knowledge gained during the project.
A79: Manage procurement | B79: Manage procurement is not a PMBOK process.
A80: Maslow’s hierarchy of needs | B80: Maslow’s hierarchy of needs specifies what a company must have in order for employees to stay motivated.
A81: Meet with the team to determine where money can be saved on the project | B81: You cannot meet with the team to reduce cost if you don’t know the requirements.
A82: Metaphors | B82: A metaphor is using XP to explain designs and create a shared vision between customers and the development team.
A83: Monitor and control project work | B83: monitoring and controlling processes that will be used to measure the work against the project management plan.
A84: Monitoring and controlling | B84: During the monitoring and controlling processes, the deliverables are accepted by the stakeholders.
B85: The output for monitoring and controlling would be the accepted deliverables and the work performance reports.
A86: Mutually exclusive | B86: mutually exclusive is a term that is used when two events cannot happen at the same time.
A87: Network diagram | B87: All other choices would give you a detailed view of the project schedule and work.
A88: Outwards | B88: Outwards influence is for those who are external, such as vendors.
A89: Overall project risks | B89: Risk generally falls into two levels on a project: individual project risks and overall project risks. All other terms are not different types of risks.
A90: Pair programming | B90: Pair programming is defined as when one programmer writes the code and another inspects the code as it’s being written. This leads to the code being inspected in seconds.
A91: Parametric estimates | B91: Parametric estimates are a type of mathematical estimates done to estimate the cost of each activity.
A92: Parametric estimation | B92: The tools of bottom-up estimation and parametric estimation are not used to determine a budget
A93: Perform integrated change control | B93: Perform integrated change control is done to assess and approve a change request.
A94: Plan procurement management | B94: Plan procurement management is done to select what needs to be procured and how to conduct the procurement
A95: Plan risk management | B95: Plan risk management is done to create the risk management plan, which will document how to conduct all the risk management processes.
A96: Problem solving | B96: Problem-solving is the best way, but that would require both sides to come up with a solution in which they both win.
A97: Process tailoring | B97: Process tailoring is done to amend the agile methodology to better fit the project environment.
... A104: Requirements documentation | B104: The project management plan, accepted deliverables, and requirements documentation are not outputs of the control quality process.
B105: The project scope statement, scope baseline, and requirements documentation will not include where requirements came from.
B106: The requirements documentation lists requirements provided by customers that they would like to be done.
B107: The requirements documentation would be the output of the process of collect requirements, not a tool.
B108: The scope statement, requirements traceability matrix, and requirements documentation are generally written before vendors are invited to learn about the project.
A109: Requirements traceability Matrix | B109: The requirements traceability matrix will trace the requirements back to their origins. The project scope statement, scope baseline, and requirements documentation will not include where requirements came from.
B110: The scope statement, requirements traceability matrix, and requirements documentation are generally written before vendors are invited to learn about the project.
A111: Resource breakdown structure | B111: The resource breakdown structure is a breakdown of the resources by categories or types
A112: Resubmit the change request for additional consideration | B112: The Change Control Board has already denied the change, so there is no need to perform additional analyses or resubmit it.
A113: Retrospective | B113: A retrospective is done after each iteration so the team can reflect and plan improvements for the next iteration.
A114: Rolling wave planning | B114: Rolling wave planning is when planning is done at multiple points in time as data becomes available.
A115: Scope Baseline | B115: The project scope statement, scope baseline, and requirements documentation will not include where requirements came from.
A116: Scope statement | B116: The scope statement, requirements traceability matrix, and requirements documentation are generally written before vendors are invited to learn about the project.
A117: Screening system | B117: Screening and weighing systems are done to help select sellers.
A118: Sequence activities | B118: You cannot define activities or sequence activities until the WBS is complete, as you will need to know work packages to create the activities
A119: Sequence Activity | B119: After the team has created the activity list in the process of define activity, the next process should be sequencing the activities. This should be done before the team develops a schedule
A120: Slack | B120: Slack and floats refer to the same thing: the amount of time you can delay an activity without delaying the project.
A121: Smoothing | B121: Smoothing is when the problem is pushed aside
A122: Sprint review | B122: During a sprint review, the customers review the partially finished product and give the team their feedback
... A132: Update change log | B132: Update project management plan and change log are not processes
B133: Update project management plan and change log are not processes.
A134: Update project management plan | B134: Update project management plan and change log are not processes
B135: Update project management plan and change log are not processes.
A136: Update the change log | B136: Once a change is approved or denied, the project manager should update the change log to list the status of the change. If a change is approved, the project management should be updated.
A137: Validate scope | B137: Validate scope is a process where stakeholders formally accept the project deliverables
A138: Verify scope | B138: Verify scope is done when all the deliverables are completed and require stakeholders’ acceptance.
A139: WBS | B139: All other choices would give you a detailed view of the project schedule and work.
A140: Weighing system | B140: Screening and weighing systems are done to help select sellers.
A141: Work breakdown structure | B141: The work breakdown structure does not show work by time.
...

Sheet Others
C2: PMBOK 7 | D2: PMBOK 8 | F2: Project Management Plan | G2: Project Documents | H2: Project Documents | J2: Interpersonal and Team Skills | K2: EEF | L2: OPA | M2: Expert Judgement | N2: Issue Log | O2: Change Requests | P2: Knoweledge Management | Q2: Data Analysis | R2: Decesion making | S2: Data gathering | T2: Data representation | U2: Product analysis | V2: PMIS | Z2: In | AA2: Related | AD2: 🧭 PMBOK 7 Performance Domains vs PMBOK 6 Processes
B3: 1 | C3: Be a diligent, respectuful and caring steward | D3: Adopt a holistic view | F3: Scope | G3: Activity Attributes | H3: Quality control measurements | J3: Active listening | K3: Org structure | L3: Org policies, procedures, processes | M3: Tech know how | N3: Issue type | O3: CA | P3: networking | Q3: Alternatives analysis | R3: Voting | S3: brainstorming | T3: Affinity diagrams | U3: Product nreakdown | X3: Assumption Log | Z3: LOGS AND REGISTERS | AA3: Assumption log | AD3: PMBOK 7 Domain | AE3: Relevant PMBOK 6 Processes
B4: 2 | C4: create a colaborative project enviorment | D4: focus on value | F4: Requirements | G4: Activity list | H4: Quality metrics | J4: Facilitation | K4: Infrastructure | L4: Issue and defect management procedures, databases | M4: Cost and budget management | N4: , who raised, | O4: PA | P4: Comunities of practice | Q4: Cost benefit | R4: Autocratic | S4: Interviews | T4: Mind mapping | U4: Requirement analysis | AA4: Backlog | AD4: Stakeholder | AE4: - Identify Stakeholders
B5: 3 | C5: effectively engage with stakeholders | D5: embed quality into processes and deliverables | F5: Schedule | G5: Assumptions log | H5: Quality Report | J5: Leadership | K5: Stakehlder Risk Thresholds | L5: Performance management database | M5: legal and procurement | N5: when raised, | O5: Defect Repair | P5: Meetings | Q5: Earned value | R5: Multicriteria | S5: Focus groups | U5: Systems analysis | AA5: Change log | AE5: - Plan Stakeholder Engagement
B6: 4 | C6: focus on value | D6: be an accountable leader | F6: Cost | G6: Basis of estimates | H6: Requirements documentation | J6: Networking | K6: legal restricitons | L6: change control and Risk Procreure | M6: legislation and regulations | N6: Priority, | O6: Updates | P6: Work shadow/Reverse shadow | Q6: RCA | S6: Questionaire and surveys | U6: Systems engineering | AA6: Issue log | AE6: - Manage Stakeholder Engagement
B7: 5 | C7: regognize, evaluate and respond to system interactions | D7: integrate sustanability within all project areas | F7: Quality | G7: Change log | H7: Requirements tracibility matrix | J7: Political Awareness | K7: Govt or industry standards | L7: Proj information form previous projects | M7: Org governance | N7: Who assigned, | O7: Identify configuration item | P7: Discussion forums | Q7: Trend alaysis | S7: benchmarking | U7: Value analysis | AA7: Lessons learned register | AE7: - Monitor Stakeholder Engagement
B8: 6 | C8: demonstrate leadership behaviours | D8: build an empowered culture | F8: Resource | G8: Cost estimates | H8: Resource breakdown structure | J8: Nominal group Technique | K8: contracting or purchaisng requirements | M8: Earned value analysis | N8: ETA, | O8: Record and configuration | P8: Knoweledge sharing events | Q8: Variance | U8: Value engineering | AA8: Risk-adjusted backlog | AD8: Team | AE8: - Plan Resource Management
B9: 7 | C9: tailor based on context | F9: Communications | G9: Cost Forecasts | H9: Resource calenders | J9: Observation/Conversation | M9: interpretation | N9: Status and resolution | O9: perform confirmaiton audit | P9: Workshops | Q9: document analysis | U9: Planning Package | AA9: Risk register | AE9: - Estimate Activity Resources
B10: 8 | C10: build quality into processes and deliverables | F10: Risk | G10: Duration estimates | H10: Resource requirements | J10: Facilitation | M10: trend analysis | P10: Story telling | Q10: regression | U10: WBS Dictionary | X10: Compromize | Y10: 4.2.7.1 | Z10: Conflict Model | AA10: Confronting/problem solving | AE10: - Acquire Resources
B11: 9 | C11: navigate complexity | F11: Procurement | G11: Issue log | H11: Risk Register | J11: JAD | M11: Risk management | P11: Creative ideas | AA11: Collaborating | AE11: - Develop Team
B12: 10 | C12: Optimize Risk responses | F12: Stakeholder | G12: Lessons learnt register | H12: Risk Report | J12: QFD | M12: Contract management | P12: management techniques | AA12: Compromising | AE12: - Manage Team
B13: 11 | C13: embrace adaptability and resiliance | F13: Change Management | G13: Milestone list | H13: Schedule data | J13: user stories | M13: Requirements elicitation | P13: knweledge fairs | AA13: Smoothing/accommodating | AD13: Development Approach & Life Cycle | AE13: - Develop Project Charter
B14: 12 | C14: enable change to achieve the envisooned future state | F14: Configuration | G14: Physical resource assignments | H14: Schedule forecasts | M14: Diagramming techniques | P14: trainings | AA14: Forcing | AE14: - Develop Project Management Plan
F15: Scope baseline | G15: Project calenders | H15: Stakeholder Resigter | AA15: Withdrawal/avoiding | AE15: - Define Activities
F16: Schedule baseline | G16: Project communications | H16: Team Charter | AE16: - Sequence Activities
C17: 7664363734 | F17: Cost Baseline | G17: Project Schedule | H17: Test and evaluation documents | AD17: Planning | AE17: - All planning processes across knowledge areas (Scope, Schedule, Cost, Quality, Risk, etc.)
F18: Performance measurement baseline | G18: Project schedule network diagram | AD18: Project Work | AE18: - Direct and Manage Project Work
F19: Project lifecycle description | G19: Project scope stament | AE19: - Manage Project Knowledge
F20: Development approach | G20: Project team assignments | AD20: Delivery | AE20: - Validate Scope
AE21: - Control Quality
AE22: - Manage Quality
AD23: Measurement | AE23: - Monitor and Control Project Work
AE24: - Perform Integrated Change Control
AE25: - Control Scope
AE26: - Control Schedule
AE27: - Control Costs
AD28: Uncertainty | AE28: - Plan Risk Management
AE29: - Identify Risks
AE30: - Perform Qualitative Risk Analysis
AE31: - Perform Quantitative Risk Analysis
AE32: - Plan Risk Responses
AE33: - Monitor Risks
AD34: Communication | AE34: - Plan Communications Management
AE35: - Manage Communications
AE36: - Monitor Communications
AD37: Procurement | AE37: - Plan Procurement Management
AE38: - Conduct Procurements
AE39: - Control Procurements

Sheet Tests
E1: {=SUMPRODUCT(--(LEN(E2:E397)>0))} -> 4 | F1: {=SUMPRODUCT(--(LEN(F2:F397)>0))} -> 2 | G1: {=SUMPRODUCT(--(LEN(G2:G397)>0))} -> 13 | H1: {=SUMPRODUCT(--(LEN(H2:H397)>0))} -> 6 | I1: {=SUMPRODUCT(--(LEN(I2:I397)>0))} -> 11
C2: Term | D2: Answer | E2: ITTO | F2: PMBOK | G2: Rita | H2: Terms | I2: Terms 2
B3: =TRIM(D3) | C3: A way to categorize the risks | E3: {=IFERROR( _xlfn.LET( _xlpm.searchText, Tests!$C3, _xlpm.dataRange, ITTO!$B$3:$F$300, _xlpm.headers, ITTO!$B$2:$F$2, _xlpm.matchMatrix, ISNUMBER(SEARCH(_xlpm.searchText, _xlpm.dataRange)), _xlpm.colMatch, _xlfn.XMATCH(TRUE, _xlfn.BYCOL(_xlpm.matchMatrix, _xlfn.LAMBDA(_xlpm.col, OR(_xlpm.col)))), INDEX(_xlpm.headers, _xlpm.colMatch) ), "" )} | F3: {=IFERROR(_xlfn.LET(_xlpm.searchText, Tests!$C3,_xlpm.dataRange, PMBOK!$B$3:$F$300,_xlpm.headers, PMBOK!$B$2:$F$2,_xlpm.matchMatrix, ISNUMBER(SEARCH(_xlpm.searchText, _xlpm.dataRange)),_xlpm.colMatch, _xlfn.XMATCH(TRUE, _xlfn.BYCOL(_xlpm.matchMatrix, _xlfn.LAMBDA(_xlpm.col, OR(_xlpm.col)))),INDEX(_xlpm.headers, _xlpm.colMatch)),"")} | G3: {=IFERROR(_xlfn.LET(_xlpm.searchText, Tests!$C3,_xlpm.dataRange, 'Rita Quick test'!$B$3:$P$57,_xlpm.headers, 'Rita Quick test'!$B$2:$P$2,_xlpm.matchMatrix, ISNUMBER(SEARCH(_xlpm.searchText, _xlpm.dataRange)),_xlpm.colMatch, _xlfn.XMATCH(TRUE, _xlfn.BYCOL(_xlpm.matchMatrix, _xlfn.LAMBDA(_xlpm.col, OR(_xlpm.col)))),INDEX(_xlpm.headers, _xlpm.colMatch)),"")} | H3: =IFERROR(VLOOKUP("*" & C3 & "*",Terms!D:E,2,FALSE),"") | I3: =IFERROR(VLOOKUP("*" & C3 & "*",'Terms 2'!B:D,3,FALSE),"")
B4: =TRIM(D4) | C4: Acceptance testing | E4: {=IFERROR( _xlfn.LET( _xlpm.searchText, Tests!$C4, _xlpm.dataRange, ITTO!$B$3:$F$300, _xlpm.headers, ITTO!$B$2:$F$2, _xlpm.matchMatrix, ISNUMBER(SEARCH(_xlpm.searchText, _xlpm.dataRange)), _xlpm.colMatch, _xlfn.XMATCH(TRUE, _xlfn.BYCOL(_xlpm.matchMatrix, _xlfn.LAMBDA(_xlpm.col, OR(_xlpm.col)))), INDEX(_xlpm.headers, _xlpm.colMatch) ), "" )} | F4: {=IFERROR(_xlfn.LET(_xlpm.searchText, Tests!$C4,_xlpm.dataRange, PMBOK!$B$3:$F$300,_xlpm.headers, PMBOK!$B$2:$F$2,_xlpm.matchMatrix, ISNUMBER(SEARCH(_xlpm.searchText, _xlpm.dataRange)),_xlpm.colMatch, _xlfn.XMATCH(TRUE, _xlfn.BYCOL(_xlpm.matchMatrix, _xlfn.LAMBDA(_xlpm.col, OR(_xlpm.col)))),INDEX(_xlpm.headers, _xlpm.colMatch)),"")} | G4: {=IFERROR(_xlfn.LET(_xlpm.searchText, Tests!$C4,_xlpm.dataRange, 'Rita Quick test'!$B$3:$P$57,_xlpm.headers, 'Rita Quick test'!$B$2:$P$2,_xlpm.matchMatrix, ISNUMBER(SEARCH(_xlpm.searchText, _xlpm.dataRange)),_xlpm.colMatch, _xlfn.XMATCH(TRUE, _xlfn.BYCOL(_xlpm.matchMatrix, _xlfn.LAMBDA(_xlpm.col, OR(_xlpm.col)))),INDEX(_xlpm.headers, _xlpm.colMatch)),"")} | H4: =IFERROR(VLOOKUP("*" & C4 & "*",Terms!D:E,2,FALSE),"") | I4: =IFERROR(VLOOKUP("*" & C4 & "*",'Terms 2'!B:D,3,FALSE),"")
B5: =TRIM(D5) | C5: Accepted deliverables | E5: {=IFERROR( _xlfn.LET( _xlpm.searchText, Tests!$C5, _xlpm.dataRange, ITTO!$B$3:$F$300, _xlpm.headers, ITTO!$B$2:$F$2, _xlpm.matchMatrix, ISNUMBER(SEARCH(_xlpm.searchText, _xlpm.dataRange)), _xlpm.colMatch, _xlfn.XMATCH(TRUE, _xlfn.BYCOL(_xlpm.matchMatrix, _xlfn.LAMBDA(_xlpm.col, OR(_xlpm.col)))), INDEX(_xlpm.headers, _xlpm.colMatch) ), "" )} | F5: {=IFERROR(_xlfn.LET(_xlpm.searchText, Tests!$C5,_xlpm.dataRange, PMBOK!$B$3:$F$300,_xlpm.headers, PMBOK!$B$2:$F$2,_xlpm.matchMatrix, ISNUMBER(SEARCH(_xlpm.searchText, _xlpm.dataRange)),_xlpm.colMatch, _xlfn.XMATCH(TRUE, _xlfn.BYCOL(_xlpm.matchMatrix, _xlfn.LAMBDA(_xlpm.col, OR(_xlpm.col)))),INDEX(_xlpm.headers, _xlpm.colMatch)),"")} | G5: {=IFERROR(_xlfn.LET(_xlpm.searchText, Tests!$C5,_xlpm.dataRange, 'Rita Quick test'!$B$3:$P$57,_xlpm.headers, 'Rita Quick test'!$B$2:$P$2,_xlpm.matchMatrix, ISNUMBER(SEARCH(_xlpm.searchText, _xlpm.dataRange)),_xlpm.colMatch, _xlfn.XMATCH(TRUE, _xlfn.BYCOL(_xlpm.matchMatrix, _xlfn.LAMBDA(_xlpm.col, OR(_xlpm.col)))),INDEX(_xlpm.headers, _xlpm.colMatch)),"")} | H5: =IFERROR(VLOOKUP("*" & C5 & "*",Terms!D:E,2,FALSE),"") | I5: =IFERROR(VLOOKUP("*" & C5 & "*",'Terms 2'!B:D,3,FALSE),"")
B6: =TRIM(D6) | C6: Access controls | E6: {=IFERROR( _xlfn.LET( _xlpm.searchText, Tests!$C6, _xlpm.dataRange, ITTO!$B$3:$F$300, _xlpm.headers, ITTO!$B$2:$F$2, _xlpm.matchMatrix, ISNUMBER(SEARCH(_xlpm.searchText, _xlpm.dataRange)), _xlpm.colMatch, _xlfn.XMATCH(TRUE, _xlfn.BYCOL(_xlpm.matchMatrix, _xlfn.LAMBDA(_xlpm.col, OR(_xlpm.col)))), INDEX(_xlpm.headers, _xlpm.colMatch) ), "" )} | F6: {=IFERROR(_xlfn.LET(_xlpm.searchText, Tests!$C6,_xlpm.dataRange, PMBOK!$B$3:$F$300,_xlpm.headers, PMBOK!$B$2:$F$2,_xlpm.matchMatrix, ISNUMBER(SEARCH(_xlpm.searchText, _xlpm.dataRange)),_xlpm.colMatch, _xlfn.XMATCH(TRUE, _xlfn.BYCOL(_xlpm.matchMatrix, _xlfn.LAMBDA(_xlpm.col, OR(_xlpm.col)))),INDEX(_xlpm.headers, _xlpm.colMatch)),"")} | G6: {=IFERROR(_xlfn.LET(_xlpm.searchText, Tests!$C6,_xlpm.dataRange, 'Rita Quick test'!$B$3:$P$57,_xlpm.headers, 'Rita Quick test'!$B$2:$P$2,_xlpm.matchMatrix, ISNUMBER(SEARCH(_xlpm.searchText, _xlpm.dataRange)),_xlpm.colMatch, _xlfn.XMATCH(TRUE, _xlfn.BYCOL(_xlpm.matchMatrix, _xlfn.LAMBDA(_xlpm.col, OR(_xlpm.col)))),INDEX(_xlpm.headers, _xlpm.colMatch)),"")} | H6: =IFERROR(VLOOKUP("*" & C6 & "*",Terms!D:E,2,FALSE),"") | I6: =IFERROR(VLOOKUP("*" & C6 & "*",'Terms 2'!B:D,3,FALSE),"")
B7: =TRIM(D7) | C7: Accommodating | E7: {=IFERROR( _xlfn.LET( _xlpm.searchText, Tests!$C7, _xlpm.dataRange, ITTO!$B$3:$F$300, _xlpm.headers, ITTO!$B$2:$F$2, _xlpm.matchMatrix, ISNUMBER(SEARCH(_xlpm.searchText, _xlpm.dataRange)), _xlpm.colMatch, _xlfn.XMATCH(TRUE, _xlfn.BYCOL(_xlpm.matchMatrix, _xlfn.LAMBDA(_xlpm.col, OR(_xlpm.col)))), INDEX(_xlpm.headers, _xlpm.colMatch) ), "" )} | F7: {=IFERROR(_xlfn.LET(_xlpm.searchText, Tests!$C7,_xlpm.dataRange, PMBOK!$B$3:$F$300,_xlpm.headers, PMBOK!$B$2:$F$2,_xlpm.matchMatrix, ISNUMBER(SEARCH(_xlpm.searchText, _xlpm.dataRange)),_xlpm.colMatch, _xlfn.XMATCH(TRUE, _xlfn.BYCOL(_xlpm.matchMatrix, _xlfn.LAMBDA(_xlpm.col, OR(_xlpm.col)))),INDEX(_xlpm.headers, _xlpm.colMatch)),"")} | G7: {=IFERROR(_xlfn.LET(_xlpm.searchText, Tests!$C7,_xlpm.dataRange, 'Rita Quick test'!$B$3:$P$57,_xlpm.headers, 'Rita Quick test'!$B$2:$P$2,_xlpm.matchMatrix, ISNUMBER(SEARCH(_xlpm.searchText, _xlpm.dataRange)),_xlpm.colMatch, _xlfn.XMATCH(TRUE, _xlfn.BYCOL(_xlpm.matchMatrix, _xlfn.LAMBDA(_xlpm.col, OR(_xlpm.col)))),INDEX(_xlpm.headers, _xlpm.colMatch)),"")} | H7: =IFERROR(VLOOKUP("*" & C7 & "*",Terms!D:E,2,FALSE),"") | I7: =IFERROR(VLOOKUP("*" & C7 & "*",'Terms 2'!B:D,3,FALSE),"")
B8: =TRIM(D8) | C8: Active listening | E8: {=IFERROR( _xlfn.LET( _xlpm.searchText, Tests!$C8, _xlpm.dataRange, ITTO!$B$3:$F$300, _xlpm.headers, ITTO!$B$2:$F$2, _xlpm.matchMatrix, ISNUMBER(SEARCH(_xlpm.searchText, _xlpm.dataRange)), _xlpm.colMatch, _xlfn.XMATCH(TRUE, _xlfn.BYCOL(_xlpm.matchMatrix, _xlfn.LAMBDA(_xlpm.col, OR(_xlpm.col)))), INDEX(_xlpm.headers, _xlpm.colMatch) ), "" )} | F8: {=IFERROR(_xlfn.LET(_xlpm.searchText, Tests!$C8,_xlpm.dataRange, PMBOK!$B$3:$F$300,_xlpm.headers, PMBOK!$B$2:$F$2,_xlpm.matchMatrix, ISNUMBER(SEARCH(_xlpm.searchText, _xlpm.dataRange)),_xlpm.colMatch, _xlfn.XMATCH(TRUE, _xlfn.BYCOL(_xlpm.matchMatrix, _xlfn.LAMBDA(_xlpm.col, OR(_xlpm.col)))),INDEX(_xlpm.headers, _xlpm.colMatch)),"")} | G8: {=IFERROR(_xlfn.LET(_xlpm.searchText, Tests!$C8,_xlpm.dataRange, 'Rita Quick test'!$B$3:$P$57,_xlpm.headers, 'Rita Quick test'!$B$2:$P$2,_xlpm.matchMatrix, ISNUMBER(SEARCH(_xlpm.searchText, _xlpm.dataRange)),_xlpm.colMatch, _xlfn.XMATCH(TRUE, _xlfn.BYCOL(_xlpm.matchMatrix, _xlfn.LAMBDA(_xlpm.col, OR(_xlpm.col)))),INDEX(_xlpm.headers, _xlpm.colMatch)),"")} -> Leadership Skills | H8: =IFERROR(VLOOKUP("*" & C8 & "*",Terms!D:E,2,FALSE),"") -> Active listening The receiver confirms that the message is being received through feedback, questions, prompts for clarity, and other signs of confirmation. | I8: =IFERROR(VLOOKUP("*" & C8 & "*",'Terms 2'!B:D,3,FALSE),"")
B9: =TRIM(D9) -> When a customer would like to add a change to an agile project, they simply added to the product backlog. That new feature will then be prioritized based on its value in the product backlog. | C9: Add it to the product backlog | D9: When a customer would like to add a change to an agile project, they simply added to the product backlog. That new feature will then be prioritized based on its value in the product backlog. | E9: {=IFERROR( _xlfn.LET( _xlpm.searchText, Tests!$C9, _xlpm.dataRange, ITTO!$B$3:$F$300, _xlpm.headers, ITTO!$B$2:$F$2, _xlpm.matchMatrix, ISNUMBER(SEARCH(_xlpm.searchText, _xlpm.dataRange)), _xlpm.colMatch, _xlfn.XMATCH(TRUE, _xlfn.BYCOL(_xlpm.matchMatrix, _xlfn.LAMBDA(_xlpm.col, OR(_xlpm.col)))), INDEX(_xlpm.headers, _xlpm.colMatch) ), "" )} | F9: {=IFERROR(_xlfn.LET(_xlpm.searchText, Tests!$C9,_xlpm.dataRange, PMBOK!$B$3:$F$300,_xlpm.headers, PMBOK!$B$2:$F$2,_xlpm.matchMatrix, ISNUMBER(SEARCH(_xlpm.searchText, _xlpm.dataRange)),_xlpm.colMatch, _xlfn.XMATCH(TRUE, _xlfn.BYCOL(_xlpm.matchMatrix, _xlfn.LAMBDA(_xlpm.col, OR(_xlpm.col)))),INDEX(_xlpm.headers, _xlpm.colMatch)),"")} | G9: {=IFERROR(_xlfn.LET(_xlpm.searchText, Tests!$C9,_xlpm.dataRange, 'Rita Quick test'!$B$3:$P$57,_xlpm.headers, 'Rita Quick test'!$B$2:$P$2,_xlpm.matchMatrix, ISNUMBER(SEARCH(_xlpm.searchText, _xlpm.dataRange)),_xlpm.colMatch, _xlfn.XMATCH(TRUE, _xlfn.BYCOL(_xlpm.matchMatrix, _xlfn.LAMBDA(_xlpm.col, OR(_xlpm.col)))),INDEX(_xlpm.headers, _xlpm.colMatch)),"")} | H9: =IFERROR(VLOOKUP("*" & C9 & "*",Terms!D:E,2,FALSE),"") | I9: =IFERROR(VLOOKUP("*" & C9 & "*",'Terms 2'!B:D,3,FALSE),"")
B10: =TRIM(D10) | C10: Add the feature and hope the sponsor approves the budget | E10: {=IFERROR( _xlfn.LET( _xlpm.searchText, Tests!$C10, _xlpm.dataRange, ITTO!$B$3:$F$300, _xlpm.headers, ITTO!$B$2:$F$2, _xlpm.matchMatrix, ISNUMBER(SEARCH(_xlpm.searchText, _xlpm.dataRange)), _xlpm.colMatch, _xlfn.XMATCH(TRUE, _xlfn.BYCOL(_xlpm.matchMatrix, _xlfn.LAMBDA(_xlpm.col, OR(_xlpm.col)))), INDEX(_xlpm.headers, _xlpm.colMatch) ), "" )} | F10: {=IFERROR(_xlfn.LET(_xlpm.searchText, Tests!$C10,_xlpm.dataRange, PMBOK!$B$3:$F$300,_xlpm.headers, PMBOK!$B$2:$F$2,_xlpm.matchMatrix, ISNUMBER(SEARCH(_xlpm.searchText, _xlpm.dataRange)),_xlpm.colMatch, _xlfn.XMATCH(TRUE, _xlfn.BYCOL(_xlpm.matchMatrix, _xlfn.LAMBDA(_xlpm.col, OR(_xlpm.col)))),INDEX(_xlpm.headers, _xlpm.colMatch)),"")} | G10: {=IFERROR(_xlfn.LET(_xlpm.searchText, Tests!$C10,_xlpm.dataRange, 'Rita Quick test'!$B$3:$P$57,_xlpm.headers, 'Rita Quick test'!$B$2:$P$2,_xlpm.matchMatrix, ISNUMBER(SEARCH(_xlpm.searchText, _xlpm.dataRange)),_xlpm.colMatch, _xlfn.XMATCH(TRUE, _xlfn.BYCOL(_xlpm.matchMatrix, _xlfn.LAMBDA(_xlpm.col, OR(_xlpm.col)))),INDEX(_xlpm.headers, _xlpm.colMatch)),"")} | H10: =IFERROR(VLOOKUP("*" & C10 & "*",Terms!D:E,2,FALSE),"") | I10: =IFERROR(VLOOKUP("*" & C10 & "*",'Terms 2'!B:D,3,FALSE),"")
B11: =TRIM(D11) -> A project scope statement not only contains the project’s deliverables but also the exclusions, which are features the project will not accomplish. Mark should not add the feature due to the company’s inability to install it. | C11: Add the feature as an exclusion to the scope statement | D11: A project scope statement not only contains the project’s deliverables but also the exclusions, which are features the project will not accomplish. Mark should not add the feature due to the company’s inability to install it. | E11: {=IFERROR( _xlfn.LET( _xlpm.searchText, Tests!$C11, _xlpm.dataRange, ITTO!$B$3:$F$300, _xlpm.headers, ITTO!$B$2:$F$2, _xlpm.matchMatrix, ISNUMBER(SEARCH(_xlpm.searchText, _xlpm.dataRange)), _xlpm.colMatch, _xlfn.XMATCH(TRUE, _xlfn.BYCOL(_xlpm.matchMatrix, _xlfn.LAMBDA(_xlpm.col, OR(_xlpm.col)))), INDEX(_xlpm.headers, _xlpm.colMatch) ), "" )} | F11: {=IFERROR(_xlfn.LET(_xlpm.searchText, Tests!$C11,_xlpm.dataRange, PMBOK!$B$3:$F$300,_xlpm.headers, PMBOK!$B$2:$F$2,_xlpm.matchMatrix, ISNUMBER(SEARCH(_xlpm.searchText, _xlpm.dataRange)),_xlpm.colMatch, _xlfn.XMATCH(TRUE, _xlfn.BYCOL(_xlpm.matchMatrix, _xlfn.LAMBDA(_xlpm.col, OR(_xlpm.col)))),INDEX(_xlpm.headers, _xlpm.colMatch)),"")} | G11: {=IFERROR(_xlfn.LET(_xlpm.searchText, Tests!$C11,_xlpm.dataRange, 'Rita Quick test'!$B$3:$P$57,_xlpm.headers, 'Rita Quick test'!$B$2:$P$2,_xlpm.matchMatrix, ISNUMBER(SEARCH(_xlpm.searchText, _xlpm.dataRange)),_xlpm.colMatch, _xlfn.XMATCH(TRUE, _xlfn.BYCOL(_xlpm.matchMatrix, _xlfn.LAMBDA(_xlpm.col, OR(_xlpm.col)))),INDEX(_xlpm.headers, _xlpm.colMatch)),"")} | H11: =IFERROR(VLOOKUP("*" & C11 & "*",Terms!D:E,2,FALSE),"") | I11: =IFERROR(VLOOKUP("*" & C11 & "*",'Terms 2'!B:D,3,FALSE),"")
B12: =TRIM(D12) -> You should not add changes to a project management plan without it being first approved | C12: Add the security system to the datacenter | D12: You should not add changes to a project management plan without it being first approved | E12: {=IFERROR( _xlfn.LET( _xlpm.searchText, Tests!$C12, _xlpm.dataRange, ITTO!$B$3:$F$300, _xlpm.headers, ITTO!$B$2:$F$2, _xlpm.matchMatrix, ISNUMBER(SEARCH(_xlpm.searchText, _xlpm.dataRange)), _xlpm.colMatch, _xlfn.XMATCH(TRUE, _xlfn.BYCOL(_xlpm.matchMatrix, _xlfn.LAMBDA(_xlpm.col, OR(_xlpm.col)))), INDEX(_xlpm.headers, _xlpm.colMatch) ), "" )} | F12: {=IFERROR(_xlfn.LET(_xlpm.searchText, Tests!$C12,_xlpm.dataRange, PMBOK!$B$3:$F$300,_xlpm.headers, PMBOK!$B$2:$F$2,_xlpm.matchMatrix, ISNUMBER(SEARCH(_xlpm.searchText, _xlpm.dataRange)),_xlpm.colMatch, _xlfn.XMATCH(TRUE, _xlfn.BYCOL(_xlpm.matchMatrix, _xlfn.LAMBDA(_xlpm.col, OR(_xlpm.col)))),INDEX(_xlpm.headers, _xlpm.colMatch)),"")} | G12: {=IFERROR(_xlfn.LET(_xlpm.searchText, Tests!$C12,_xlpm.dataRange, 'Rita Quick test'!$B$3:$P$57,_xlpm.headers, 'Rita Quick test'!$B$2:$P$2,_xlpm.matchMatrix, ISNUMBER(SEARCH(_xlpm.searchText, _xlpm.dataRange)),_xlpm.colMatch, _xlfn.XMATCH(TRUE, _xlfn.BYCOL(_xlpm.matchMatrix, _xlfn.LAMBDA(_xlpm.col, OR(_xlpm.col)))),INDEX(_xlpm.headers, _xlpm.colMatch)),"")} | H12: =IFERROR(VLOOKUP("*" & C12 & "*",Terms!D:E,2,FALSE),"") | I12: =IFERROR(VLOOKUP("*" & C12 & "*",'Terms 2'!B:D,3,FALSE),"")
B13: =TRIM(D13) | C13: Adding leads to activities | E13: {=IFERROR( _xlfn.LET( _xlpm.searchText, Tests!$C13, _xlpm.dataRange, ITTO!$B$3:$F$300, _xlpm.headers, ITTO!$B$2:$F$2, _xlpm.matchMatrix, ISNUMBER(SEARCH(_xlpm.searchText, _xlpm.dataRange)), _xlpm.colMatch, _xlfn.XMATCH(TRUE, _xlfn.BYCOL(_xlpm.matchMatrix, _xlfn.LAMBDA(_xlpm.col, OR(_xlpm.col)))), INDEX(_xlpm.headers, _xlpm.colMatch) ), "" )} | F13: {=IFERROR(_xlfn.LET(_xlpm.searchText, Tests!$C13,_xlpm.dataRange, PMBOK!$B$3:$F$300,_xlpm.headers, PMBOK!$B$2:$F$2,_xlpm.matchMatrix, ISNUMBER(SEARCH(_xlpm.searchText, _xlpm.dataRange)),_xlpm.colMatch, _xlfn.XMATCH(TRUE, _xlfn.BYCOL(_xlpm.matchMatrix, _xlfn.LAMBDA(_xlpm.col, OR(_xlpm.col)))),INDEX(_xlpm.headers, _xlpm.colMatch)),"")} | G13: {=IFERROR(_xlfn.LET(_xlpm.searchText, Tests!$C13,_xlpm.dataRange, 'Rita Quick test'!$B$3:$P$57,_xlpm.headers, 'Rita Quick test'!$B$2:$P$2,_xlpm.matchMatrix, ISNUMBER(SEARCH(_xlpm.searchText, _xlpm.dataRange)),_xlpm.colMatch, _xlfn.XMATCH(TRUE, _xlfn.BYCOL(_xlpm.matchMatrix, _xlfn.LAMBDA(_xlpm.col, OR(_xlpm.col)))),INDEX(_xlpm.headers, _xlpm.colMatch)),"")} | H13: =IFERROR(VLOOKUP("*" & C13 & "*",Terms!D:E,2,FALSE),"") | I13: =IFERROR(VLOOKUP("*" & C13 & "*",'Terms 2'!B:D,3,FALSE),"")
B14: =TRIM(D14) -> An affinity diagram is used to group large numbers of ideas to be analyzed. | C14: Affinity diagram | D14: An affinity diagram is used to group large numbers of ideas to be analyzed. | E14: {=IFERROR( _xlfn.LET( _xlpm.searchText, Tests!$C14, _xlpm.dataRange, ITTO!$B$3:$F$300, _xlpm.headers, ITTO!$B$2:$F$2, _xlpm.matchMatrix, ISNUMBER(SEARCH(_xlpm.searchText, _xlpm.dataRange)), _xlpm.colMatch, _xlfn.XMATCH(TRUE, _xlfn.BYCOL(_xlpm.matchMatrix, _xlfn.LAMBDA(_xlpm.col, OR(_xlpm.col)))), INDEX(_xlpm.headers, _xlpm.colMatch) ), "" )} | F14: {=IFERROR(_xlfn.LET(_xlpm.searchText, Tests!$C14,_xlpm.dataRange, PMBOK!$B$3:$F$300,_xlpm.headers, PMBOK!$B$2:$F$2,_xlpm.matchMatrix, ISNUMBER(SEARCH(_xlpm.searchText, _xlpm.dataRange)),_xlpm.colMatch, _xlfn.XMATCH(TRUE, _xlfn.BYCOL(_xlpm.matchMatrix, _xlfn.LAMBDA(_xlpm.col, OR(_xlpm.col)))),INDEX(_xlpm.headers, _xlpm.colMatch)),"")} | G14: {=IFERROR(_xlfn.LET(_xlpm.searchText, Tests!$C14,_xlpm.dataRange, 'Rita Quick test'!$B$3:$P$57,_xlpm.headers, 'Rita Quick test'!$B$2:$P$2,_xlpm.matchMatrix, ISNUMBER(SEARCH(_xlpm.searchText, _xlpm.dataRange)),_xlpm.colMatch, _xlfn.XMATCH(TRUE, _xlfn.BYCOL(_xlpm.matchMatrix, _xlfn.LAMBDA(_xlpm.col, OR(_xlpm.col)))),INDEX(_xlpm.headers, _xlpm.colMatch)),"")} -> Scope | H14: =IFERROR(VLOOKUP("*" & C14 & "*",Terms!D:E,2,FALSE),"") -> Affinity diagram This diagram breaks down ideas, solutions, causes, and project components and groups them together with other similar ideas and components. | I14: =IFERROR(VLOOKUP("*" & C14 & "*",'Terms 2'!B:D,3,FALSE),"") -> A diagram that shows large numbers of ideas classified into groups for review and analysis
B15: =TRIM(D15) | C15: Agile project planning | E15: {=IFERROR( _xlfn.LET( _xlpm.searchText, Tests!$C15, _xlpm.dataRange, ITTO!$B$3:$F$300, _xlpm.headers, ITTO!$B$2:$F$2, _xlpm.matchMatrix, ISNUMBER(SEARCH(_xlpm.searchText, _xlpm.dataRange)), _xlpm.colMatch, _xlfn.XMATCH(TRUE, _xlfn.BYCOL(_xlpm.matchMatrix, _xlfn.LAMBDA(_xlpm.col, OR(_xlpm.col)))), INDEX(_xlpm.headers, _xlpm.colMatch) ), "" )} | F15: {=IFERROR(_xlfn.LET(_xlpm.searchText, Tests!$C15,_xlpm.dataRange, PMBOK!$B$3:$F$300,_xlpm.headers, PMBOK!$B$2:$F$2,_xlpm.matchMatrix, ISNUMBER(SEARCH(_xlpm.searchText, _xlpm.dataRange)),_xlpm.colMatch, _xlfn.XMATCH(TRUE, _xlfn.BYCOL(_xlpm.matchMatrix, _xlfn.LAMBDA(_xlpm.col, OR(_xlpm.col)))),INDEX(_xlpm.headers, _xlpm.colMatch)),"")} | G15: {=IFERROR(_xlfn.LET(_xlpm.searchText, Tests!$C15,_xlpm.dataRange, 'Rita Quick test'!$B$3:$P$57,_xlpm.headers, 'Rita Quick test'!$B$2:$P$2,_xlpm.matchMatrix, ISNUMBER(SEARCH(_xlpm.searchText, _xlpm.dataRange)),_xlpm.colMatch, _xlfn.XMATCH(TRUE, _xlfn.BYCOL(_xlpm.matchMatrix, _xlfn.LAMBDA(_xlpm.col, OR(_xlpm.col)))),INDEX(_xlpm.headers, _xlpm.colMatch)),"")} | H15: =IFERROR(VLOOKUP("*" & C15 & "*",Terms!D:E,2,FALSE),"") | I15: =IFERROR(VLOOKUP("*" & C15 & "*",'Terms 2'!B:D,3,FALSE),"")
B16: =TRIM(D16) -> Analogous estimates are based on historical information to estimate the cost of each activity. | C16: Analogous estimates | D16: Analogous estimates are based on historical information to estimate the cost of each activity. | E16: {=IFERROR( _xlfn.LET( _xlpm.searchText, Tests!$C16, _xlpm.dataRange, ITTO!$B$3:$F$300, _xlpm.headers, ITTO!$B$2:$F$2, _xlpm.matchMatrix, ISNUMBER(SEARCH(_xlpm.searchText, _xlpm.dataRange)), _xlpm.colMatch, _xlfn.XMATCH(TRUE, _xlfn.BYCOL(_xlpm.matchMatrix, _xlfn.LAMBDA(_xlpm.col, OR(_xlpm.col)))), INDEX(_xlpm.headers, _xlpm.colMatch) ), "" )} | F16: {=IFERROR(_xlfn.LET(_xlpm.searchText, Tests!$C16,_xlpm.dataRange, PMBOK!$B$3:$F$300,_xlpm.headers, PMBOK!$B$2:$F$2,_xlpm.matchMatrix, ISNUMBER(SEARCH(_xlpm.searchText, _xlpm.dataRange)),_xlpm.colMatch, _xlfn.XMATCH(TRUE, _xlfn.BYCOL(_xlpm.matchMatrix, _xlfn.LAMBDA(_xlpm.col, OR(_xlpm.col)))),INDEX(_xlpm.headers, _xlpm.colMatch)),"")} | G16: {=IFERROR(_xlfn.LET(_xlpm.searchText, Tests!$C16,_xlpm.dataRange, 'Rita Quick test'!$B$3:$P$57,_xlpm.headers, 'Rita Quick test'!$B$2:$P$2,_xlpm.matchMatrix, ISNUMBER(SEARCH(_xlpm.searchText, _xlpm.dataRange)),_xlpm.colMatch, _xlfn.XMATCH(TRUE, _xlfn.BYCOL(_xlpm.matchMatrix, _xlfn.LAMBDA(_xlpm.col, OR(_xlpm.col)))),INDEX(_xlpm.headers, _xlpm.colMatch)),"")} | H16: =IFERROR(VLOOKUP("*" & C16 & "*",Terms!D:E,2,FALSE),"") | I16: =IFERROR(VLOOKUP("*" & C16 & "*",'Terms 2'!B:D,3,FALSE),"")
B17: =TRIM(D17) -> Top-down and analogous are the same and are high-level estimates based on historical data. | C17: Analogous | D17: Top-down and analogous are the same and are high-level estimates based on historical data. | E17: {=IFERROR( _xlfn.LET( _xlpm.searchText, Tests!$C17, _xlpm.dataRange, ITTO!$B$3:$F$300, _xlpm.headers, ITTO!$B$2:$F$2, _xlpm.matchMatrix, ISNUMBER(SEARCH(_xlpm.searchText, _xlpm.dataRange)), _xlpm.colMatch, _xlfn.XMATCH(TRUE, _xlfn.BYCOL(_xlpm.matchMatrix, _xlfn.LAMBDA(_xlpm.col, OR(_xlpm.col)))), INDEX(_xlpm.headers, _xlpm.colMatch) ), "" )} | F17: {=IFERROR(_xlfn.LET(_xlpm.searchText, Tests!$C17,_xlpm.dataRange, PMBOK!$B$3:$F$300,_xlpm.headers, PMBOK!$B$2:$F$2,_xlpm.matchMatrix, ISNUMBER(SEARCH(_xlpm.searchText, _xlpm.dataRange)),_xlpm.colMatch, _xlfn.XMATCH(TRUE, _xlfn.BYCOL(_xlpm.matchMatrix, _xlfn.LAMBDA(_xlpm.col, OR(_xlpm.col)))),INDEX(_xlpm.headers, _xlpm.colMatch)),"")} | G17: {=IFERROR(_xlfn.LET(_xlpm.searchText, Tests!$C17,_xlpm.dataRange, 'Rita Quick test'!$B$3:$P$57,_xlpm.headers, 'Rita Quick test'!$B$2:$P$2,_xlpm.matchMatrix, ISNUMBER(SEARCH(_xlpm.searchText, _xlpm.dataRange)),_xlpm.colMatch, _xlfn.XMATCH(TRUE, _xlfn.BYCOL(_xlpm.matchMatrix, _xlfn.LAMBDA(_xlpm.col, OR(_xlpm.col)))),INDEX(_xlpm.headers, _xlpm.colMatch)),"")} | H17: =IFERROR(VLOOKUP("*" & C17 & "*",Terms!D:E,2,FALSE),"") | I17: =IFERROR(VLOOKUP("*" & C17 & "*",'Terms 2'!B:D,3,FALSE),"")
B18: =TRIM(D18) -> On a very small project, the project manager may ask the sponsor to approve or deny changes. The project manager’s main job is to document and assess changes to the project. | C18: Approve the changes himself | D18: On a very small project, the project manager may ask the sponsor to approve or deny changes. The project manager’s main job is to document and assess changes to the project. | E18: {=IFERROR( _xlfn.LET( _xlpm.searchText, Tests!$C18, _xlpm.dataRange, ITTO!$B$3:$F$300, _xlpm.headers, ITTO!$B$2:$F$2, _xlpm.matchMatrix, ISNUMBER(SEARCH(_xlpm.searchText, _xlpm.dataRange)), _xlpm.colMatch, _xlfn.XMATCH(TRUE, _xlfn.BYCOL(_xlpm.matchMatrix, _xlfn.LAMBDA(_xlpm.col, OR(_xlpm.col)))), INDEX(_xlpm.headers, _xlpm.colMatch) ), "" )} | F18: {=IFERROR(_xlfn.LET(_xlpm.searchText, Tests!$C18,_xlpm.dataRange, PMBOK!$B$3:$F$300,_xlpm.headers, PMBOK!$B$2:$F$2,_xlpm.matchMatrix, ISNUMBER(SEARCH(_xlpm.searchText, _xlpm.dataRange)),_xlpm.colMatch, _xlfn.XMATCH(TRUE, _xlfn.BYCOL(_xlpm.matchMatrix, _xlfn.LAMBDA(_xlpm.col, OR(_xlpm.col)))),INDEX(_xlpm.headers, _xlpm.colMatch)),"")} | G18: {=IFERROR(_xlfn.LET(_xlpm.searchText, Tests!$C18,_xlpm.dataRange, 'Rita Quick test'!$B$3:$P$57,_xlpm.headers, 'Rita Quick test'!$B$2:$P$2,_xlpm.matchMatrix, ISNUMBER(SEARCH(_xlpm.searchText, _xlpm.dataRange)),_xlpm.colMatch, _xlfn.XMATCH(TRUE, _xlfn.BYCOL(_xlpm.matchMatrix, _xlfn.LAMBDA(_xlpm.col, OR(_xlpm.col)))),INDEX(_xlpm.headers, _xlpm.colMatch)),"")} | H18: =IFERROR(VLOOKUP("*" & C18 & "*",Terms!D:E,2,FALSE),"") | I18: =IFERROR(VLOOKUP("*" & C18 & "*",'Terms 2'!B:D,3,FALSE),"")
B19: =TRIM(D19) | C19: Approve the changes himself | E19: {=IFERROR( _xlfn.LET( _xlpm.searchText, Tests!$C19, _xlpm.dataRange, ITTO!$B$3:$F$300, _xlpm.headers, ITTO!$B$2:$F$2, _xlpm.matchMatrix, ISNUMBER(SEARCH(_xlpm.searchText, _xlpm.dataRange)), _xlpm.colMatch, _xlfn.XMATCH(TRUE, _xlfn.BYCOL(_xlpm.matchMatrix, _xlfn.LAMBDA(_xlpm.col, OR(_xlpm.col)))), INDEX(_xlpm.headers, _xlpm.colMatch) ), "" )} | F19: {=IFERROR(_xlfn.LET(_xlpm.searchText, Tests!$C19,_xlpm.dataRange, PMBOK!$B$3:$F$300,_xlpm.headers, PMBOK!$B$2:$F$2,_xlpm.matchMatrix, ISNUMBER(SEARCH(_xlpm.searchText, _xlpm.dataRange)),_xlpm.colMatch, _xlfn.XMATCH(TRUE, _xlfn.BYCOL(_xlpm.matchMatrix, _xlfn.LAMBDA(_xlpm.col, OR(_xlpm.col)))),INDEX(_xlpm.headers, _xlpm.colMatch)),"")} | G19: {=IFERROR(_xlfn.LET(_xlpm.searchText, Tests!$C19,_xlpm.dataRange, 'Rita Quick test'!$B$3:$P$57,_xlpm.headers, 'Rita Quick test'!$B$2:$P$2,_xlpm.matchMatrix, ISNUMBER(SEARCH(_xlpm.searchText, _xlpm.dataRange)),_xlpm.colMatch, _xlfn.XMATCH(TRUE, _xlfn.BYCOL(_xlpm.matchMatrix, _xlfn.LAMBDA(_xlpm.col, OR(_xlpm.col)))),INDEX(_xlpm.headers, _xlpm.colMatch)),"")} | H19: =IFERROR(VLOOKUP("*" & C19 & "*",Terms!D:E,2,FALSE),"") | I19: =IFERROR(VLOOKUP("*" & C19 & "*",'Terms 2'!B:D,3,FALSE),"")
B20: =TRIM(D20) -> On a very small project, the project manager may ask the sponsor to approve or deny changes. The project manager’s main job is to document and assess changes to the project. | C20: Approve the changes himself with the help of the project team | D20: On a very small project, the project manager may ask the sponsor to approve or deny changes. The project manager’s main job is to document and assess changes to the project. | E20: {=IFERROR( _xlfn.LET( _xlpm.searchText, Tests!$C20, _xlpm.dataRange, ITTO!$B$3:$F$300, _xlpm.headers, ITTO!$B$2:$F$2, _xlpm.matchMatrix, ISNUMBER(SEARCH(_xlpm.searchText, _xlpm.dataRange)), _xlpm.colMatch, _xlfn.XMATCH(TRUE, _xlfn.BYCOL(_xlpm.matchMatrix, _xlfn.LAMBDA(_xlpm.col, OR(_xlpm.col)))), INDEX(_xlpm.headers, _xlpm.colMatch) ), "" )} | F20: {=IFERROR(_xlfn.LET(_xlpm.searchText, Tests!$C20,_xlpm.dataRange, PMBOK!$B$3:$F$300,_xlpm.headers, PMBOK!$B$2:$F$2,_xlpm.matchMatrix, ISNUMBER(SEARCH(_xlpm.searchText, _xlpm.dataRange)),_xlpm.colMatch, _xlfn.XMATCH(TRUE, _xlfn.BYCOL(_xlpm.matchMatrix, _xlfn.LAMBDA(_xlpm.col, OR(_xlpm.col)))),INDEX(_xlpm.headers, _xlpm.colMatch)),"")} | G20: {=IFERROR(_xlfn.LET(_xlpm.searchText, Tests!$C20,_xlpm.dataRange, 'Rita Quick test'!$B$3:$P$57,_xlpm.headers, 'Rita Quick test'!$B$2:$P$2,_xlpm.matchMatrix, ISNUMBER(SEARCH(_xlpm.searchText, _xlpm.dataRange)),_xlpm.colMatch, _xlfn.XMATCH(TRUE, _xlfn.BYCOL(_xlpm.matchMatrix, _xlfn.LAMBDA(_xlpm.col, OR(_xlpm.col)))),INDEX(_xlpm.headers, _xlpm.colMatch)),"")} | H20: =IFERROR(VLOOKUP("*" & C20 & "*",Terms!D:E,2,FALSE),"") | I20: =IFERROR(VLOOKUP("*" & C20 & "*",'Terms 2'!B:D,3,FALSE),"")
B21: =TRIM(D21) | C21: Approve the changes himself with the help of the project team | E21: {=IFERROR( _xlfn.LET( _xlpm.searchText, Tests!$C21, _xlpm.dataRange, ITTO!$B$3:$F$300, _xlpm.headers, ITTO!$B$2:$F$2, _xlpm.matchMatrix, ISNUMBER(SEARCH(_xlpm.searchText, _xlpm.dataRange)), _xlpm.colMatch, _xlfn.XMATCH(TRUE, _xlfn.BYCOL(_xlpm.matchMatrix, _xlfn.LAMBDA(_xlpm.col, OR(_xlpm.col)))), INDEX(_xlpm.headers, _xlpm.colMatch) ), "" )} | F21: {=IFERROR(_xlfn.LET(_xlpm.searchText, Tests!$C21,_xlpm.dataRange, PMBOK!$B$3:$F$300,_xlpm.headers, PMBOK!$B$2:$F$2,_xlpm.matchMatrix, ISNUMBER(SEARCH(_xlpm.searchText, _xlpm.dataRange)),_xlpm.colMatch, _xlfn.XMATCH(TRUE, _xlfn.BYCOL(_xlpm.matchMatrix, _xlfn.LAMBDA(_xlpm.col, OR(_xlpm.col)))),INDEX(_xlpm.headers, _xlpm.colMatch)),"")} | G21: {=IFERROR(_xlfn.LET(_xlpm.searchText, Tests!$C21,_xlpm.dataRange, 'Rita Quick test'!$B$3:$P$57,_xlpm.headers, 'Rita Quick test'!$B$2:$P$2,_xlpm.matchMatrix, ISNUMBER(SEARCH(_xlpm.searchText, _xlpm.dataRange)),_xlpm.colMatch, _xlfn.XMATCH(TRUE, _xlfn.BYCOL(_xlpm.matchMatrix, _xlfn.LAMBDA(_xlpm.col, OR(_xlpm.col)))),INDEX(_xlpm.headers, _xlpm.colMatch)),"")} | H21: =IFERROR(VLOOKUP("*" & C21 & "*",Terms!D:E,2,FALSE),"") | I21: =IFERROR(VLOOKUP("*" & C21 & "*",'Terms 2'!B:D,3,FALSE),"")
B22: =TRIM(D22) | C22: Ask the agile project manager for permission to add it to the product backlog | E22: {=IFERROR( _xlfn.LET( _xlpm.searchText, Tests!$C22, _xlpm.dataRange, ITTO!$B$3:$F$300, _xlpm.headers, ITTO!$B$2:$F$2, _xlpm.matchMatrix, ISNUMBER(SEARCH(_xlpm.searchText, _xlpm.dataRange)), _xlpm.colMatch, _xlfn.XMATCH(TRUE, _xlfn.BYCOL(_xlpm.matchMatrix, _xlfn.LAMBDA(_xlpm.col, OR(_xlpm.col)))), INDEX(_xlpm.headers, _xlpm.colMatch) ), "" )} | F22: {=IFERROR(_xlfn.LET(_xlpm.searchText, Tests!$C22,_xlpm.dataRange, PMBOK!$B$3:$F$300,_xlpm.headers, PMBOK!$B$2:$F$2,_xlpm.matchMatrix, ISNUMBER(SEARCH(_xlpm.searchText, _xlpm.dataRange)),_xlpm.colMatch, _xlfn.XMATCH(TRUE, _xlfn.BYCOL(_xlpm.matchMatrix, _xlfn.LAMBDA(_xlpm.col, OR(_xlpm.col)))),INDEX(_xlpm.headers, _xlpm.colMatch)),"")} | G22: {=IFERROR(_xlfn.LET(_xlpm.searchText, Tests!$C22,_xlpm.dataRange, 'Rita Quick test'!$B$3:$P$57,_xlpm.headers, 'Rita Quick test'!$B$2:$P$2,_xlpm.matchMatrix, ISNUMBER(SEARCH(_xlpm.searchText, _xlpm.dataRange)),_xlpm.colMatch, _xlfn.XMATCH(TRUE, _xlfn.BYCOL(_xlpm.matchMatrix, _xlfn.LAMBDA(_xlpm.col, OR(_xlpm.col)))),INDEX(_xlpm.headers, _xlpm.colMatch)),"")} | H22: =IFERROR(VLOOKUP("*" & C22 & "*",Terms!D:E,2,FALSE),"") | I22: =IFERROR(VLOOKUP("*" & C22 & "*",'Terms 2'!B:D,3,FALSE),"")
B23: =TRIM(D23) | C23: Ask the product owner when he would like the changes to be implemented | E23: {=IFERROR( _xlfn.LET( _xlpm.searchText, Tests!$C23, _xlpm.dataRange, ITTO!$B$3:$F$300, _xlpm.headers, ITTO!$B$2:$F$2, _xlpm.matchMatrix, ISNUMBER(SEARCH(_xlpm.searchText, _xlpm.dataRange)), _xlpm.colMatch, _xlfn.XMATCH(TRUE, _xlfn.BYCOL(_xlpm.matchMatrix, _xlfn.LAMBDA(_xlpm.col, OR(_xlpm.col)))), INDEX(_xlpm.headers, _xlpm.colMatch) ), "" )} | F23: {=IFERROR(_xlfn.LET(_xlpm.searchText, Tests!$C23,_xlpm.dataRange, PMBOK!$B$3:$F$300,_xlpm.headers, PMBOK!$B$2:$F$2,_xlpm.matchMatrix, ISNUMBER(SEARCH(_xlpm.searchText, _xlpm.dataRange)),_xlpm.colMatch, _xlfn.XMATCH(TRUE, _xlfn.BYCOL(_xlpm.matchMatrix, _xlfn.LAMBDA(_xlpm.col, OR(_xlpm.col)))),INDEX(_xlpm.headers, _xlpm.colMatch)),"")} | G23: {=IFERROR(_xlfn.LET(_xlpm.searchText, Tests!$C23,_xlpm.dataRange, 'Rita Quick test'!$B$3:$P$57,_xlpm.headers, 'Rita Quick test'!$B$2:$P$2,_xlpm.matchMatrix, ISNUMBER(SEARCH(_xlpm.searchText, _xlpm.dataRange)),_xlpm.colMatch, _xlfn.XMATCH(TRUE, _xlfn.BYCOL(_xlpm.matchMatrix, _xlfn.LAMBDA(_xlpm.col, OR(_xlpm.col)))),INDEX(_xlpm.headers, _xlpm.colMatch)),"")} | H23: =IFERROR(VLOOKUP("*" & C23 & "*",Terms!D:E,2,FALSE),"") | I23: =IFERROR(VLOOKUP("*" & C23 & "*",'Terms 2'!B:D,3,FALSE),"")
